Workbook

Sheet RiskRanges
A1: Date | B1: Ticker | C1: High | D1: Low | E1: Prior High | F1: Prior Low | G1: High Structure | H1: Low Structure | I1: Trend Signal
E2: =IF(AND(B2=B1,A2>A1),C1,"") | F2: =IF(AND(B2=B1,A2>A1),D1,"") | G2: =IF(E2="","",IF(C2>E2,"Higher High",IF(C2<E2,"Lower High","Flat"))) | H2: =IF(F2="","",IF(D2>F2,"Higher Low",IF(D2<F2,"Lower Low","Flat"))) | I2: =IF(AND(G2="Higher High",H2="Higher Low"),"Bullish",IF(AND(G2="Lower High",H2="Lower Low"),"Bearish","Mixed")) -> Mixed | O2: INDEX | P2: BUY TRADE | Q2: SELL TRADE | R2: PREV. CLOSE
E3: =IF(AND(B3=B2,A3>A2),C2,"") | F3: =IF(AND(B3=B2,A3>A2),D2,"") | G3: =IF(E3="","",IF(C3>E3,"Higher High",IF(C3<E3,"Lower High","Flat"))) | H3: =IF(F3="","",IF(D3>F3,"Higher Low",IF(D3<F3,"Lower Low","Flat"))) | I3: =IF(AND(G3="Higher High",H3="Higher Low"),"Bullish",IF(AND(G3="Lower High",H3="Lower Low"),"Bearish","Mixed")) -> Mixed | O3: UST30Y (BEARISH)
E4: =IF(AND(B4=B3,A4>A3),C3,"") | F4: =IF(AND(B4=B3,A4>A3),D3,"") | G4: =IF(E4="","",IF(C4>E4,"Higher High",IF(C4<E4,"Lower High","Flat"))) | H4: =IF(F4="","",IF(D4>F4,"Higher Low",IF(D4<F4,"Lower Low","Flat"))) | I4: =IF(AND(G4="Higher High",H4="Higher Low"),"Bullish",IF(AND(G4="Lower High",H4="Lower Low"),"Bearish","Mixed")) -> Mixed | O4: 30-Year U.S. Treasury Yield | P4: 4.75 | Q4: 4.65 | R4: 4.71
E5: =IF(AND(B5=B4,A5>A4),C4,"") | F5: =IF(AND(B5=B4,A5>A4),D4,"") | G5: =IF(E5="","",IF(C5>E5,"Higher High",IF(C5<E5,"Lower High","Flat"))) | H5: =IF(F5="","",IF(D5>F5,"Higher Low",IF(D5<F5,"Lower Low","Flat"))) | I5: =IF(AND(G5="Higher High",H5="Higher Low"),"Bullish",IF(AND(G5="Lower High",H5="Lower Low"),"Bearish","Mixed")) -> Mixed | O5: UST10Y (BEARISH)
E6: =IF(AND(B6=B5,A6>A5),C5,"") | F6: =IF(AND(B6=B5,A6>A5),D5,"") | G6: =IF(E6="","",IF(C6>E6,"Higher High",IF(C6<E6,"Lower High","Flat"))) | H6: =IF(F6="","",IF(D6>F6,"Higher Low",IF(D6<F6,"Lower Low","Flat"))) | I6: =IF(AND(G6="Higher High",H6="Higher Low"),"Bullish",IF(AND(G6="Lower High",H6="Lower Low"),"Bearish","Mixed")) -> Mixed | O6: 10-Year U.S. Treasury Yield | P6: 4.15 | Q6: 4.02 | R6: 4.07
E7: =IF(AND(B7=B6,A7>A6),C6,"") | F7: =IF(AND(B7=B6,A7>A6),D6,"") | G7: =IF(E7="","",IF(C7>E7,"Higher High",IF(C7<E7,"Lower High","Flat"))) | H7: =IF(F7="","",IF(D7>F7,"Higher Low",IF(D7<F7,"Lower Low","Flat"))) | I7: =IF(AND(G7="Higher High",H7="Higher Low"),"Bullish",IF(AND(G7="Lower High",H7="Lower Low"),"Bearish","Mixed")) -> Mixed | O7: UST2Y (BEARISH)
E8: =IF(AND(B8=B7,A8>A7),C7,"") | F8: =IF(AND(B8=B7,A8>A7),D7,"") | G8: =IF(E8="","",IF(C8>E8,"Higher High",IF(C8<E8,"Lower High","Flat"))) | H8: =IF(F8="","",IF(D8>F8,"Higher Low",IF(D8<F8,"Lower Low","Flat"))) | I8: =IF(AND(G8="Higher High",H8="Higher Low"),"Bullish",IF(AND(G8="Lower High",H8="Lower Low"),"Bearish","Mixed")) -> Mixed | O8: 2-Year U.S. Treasury Yield | P8: 3.62 | Q8: 3.49 | R8: 3.52
E9: =IF(AND(B9=B8,A9>A8),C8,"") | F9: =IF(AND(B9=B8,A9>A8),D8,"") | G9: =IF(E9="","",IF(C9>E9,"Higher High",IF(C9<E9,"Lower High","Flat"))) | H9: =IF(F9="","",IF(D9>F9,"Higher Low",IF(D9<F9,"Lower Low","Flat"))) | I9: =IF(AND(G9="Higher High",H9="Higher Low"),"Bullish",IF(AND(G9="Lower High",H9="Lower Low"),"Bearish","Mixed")) -> Mixed | O9: HYG (NEUTRAL)
E10: =IF(AND(B90=B9,A90>A9),C9,"") | F10: =IF(AND(B90=B9,A90>A9),D9,"") | G10: =IF(E10="","",IF(C10>E10,"Higher High",IF(C10<E10,"Lower High","Flat"))) | H10: =IF(F10="","",IF(D10>F10,"Higher Low",IF(D10<F10,"Lower Low","Flat"))) | I10: =IF(AND(G10="Higher High",H10="Higher Low"),"Bullish",IF(AND(G10="Lower High",H10="Lower Low"),"Bearish","Mixed")) -> Mixed | O10: High Yield | P10: 79.85 | Q10: 80.61 | R10: 80.37
E11: =IF(AND(B1010=B10,A1010>A10),C10,"") | F11: =IF(AND(B1010=B10,A1010>A10),D10,"") | G11: =IF(E11="","",IF(C11>E11,"Higher High",IF(C11<E11,"Lower High","Flat"))) | H11: =IF(F11="","",IF(D11>F11,"Higher Low",IF(D11<F11,"Lower Low","Flat"))) | I11: =IF(AND(G11="Higher High",H11="Higher Low"),"Bullish",IF(AND(G11="Lower High",H11="Lower Low"),"Bearish","Mixed")) -> Mixed | O11: LQD (BULLISH)
E12: =IF(AND(B112=B11,A112>A11),C11,"") | F12: =IF(AND(B112=B11,A112>A11),D11,"") | G12: =IF(E12="","",IF(C12>E12,"Higher High",IF(C12<E12,"Lower High","Flat"))) | H12: =IF(F12="","",IF(D12>F12,"Higher Low",IF(D12<F12,"Lower Low","Flat"))) | I12: =IF(AND(G12="Higher High",H12="Higher Low"),"Bullish",IF(AND(G12="Lower High",H12="Lower Low"),"Bearish","Mixed")) -> Mixed | O12: Investment Grade Corporate Bond ETF | P12: 110.1 | Q12: 111.6 | R12: 110.9
E13: =IF(AND(B123=B12,A123>A12),C12,"") | F13: =IF(AND(B123=B12,A123>A12),D12,"") | G13: =IF(E13="","",IF(C13>E13,"Higher High",IF(C13<E13,"Lower High","Flat"))) | H13: =IF(F13="","",IF(D13>F13,"Higher Low",IF(D13<F13,"Lower Low","Flat"))) | I13: =IF(AND(G13="Higher High",H13="Higher Low"),"Bullish",IF(AND(G13="Lower High",H13="Lower Low"),"Bearish","Mixed")) -> Mixed | O13: SPX (BULLISH)
E14: =IF(AND(B134=B13,A134>A13),C13,"") | F14: =IF(AND(B134=B13,A134>A13),D13,"") | G14: =IF(E14="","",IF(C14>E14,"Higher High",IF(C14<E14,"Lower High","Flat"))) | H14: =IF(F14="","",IF(D14>F14,"Higher Low",IF(D14<F14,"Lower Low","Flat"))) | I14: =IF(AND(G14="Higher High",H14="Higher Low"),"Bullish",IF(AND(G14="Lower High",H14="Lower Low"),"Bearish","Mixed")) -> Mixed | O14: S&P 500 | P14: 6476 | Q14: 6713 | R14: 6602
E15: =IF(AND(B145=B14,A145>A14),C14,"") | F15: =IF(AND(B145=B14,A145>A14),D14,"") | G15: =IF(E15="","",IF(C15>E15,"Higher High",IF(C15<E15,"Lower High","Flat"))) | H15: =IF(F15="","",IF(D15>F15,"Higher Low",IF(D15<F15,"Lower Low","Flat"))) | I15: =IF(AND(G15="Higher High",H15="Higher Low"),"Bullish",IF(AND(G15="Lower High",H15="Lower Low"),"Bearish","Mixed")) -> Mixed | O15: COMPQ (BEARISH)
E16: =IF(AND(B156=B15,A156>A15),C15,"") | F16: =IF(AND(B156=B15,A156>A15),D15,"") | G16: =IF(E16="","",IF(C16>E16,"Higher High",IF(C16<E16,"Lower High","Flat"))) | H16: =IF(F16="","",IF(D16>F16,"Higher Low",IF(D16<F16,"Lower Low","Flat"))) | I16: =IF(AND(G16="Higher High",H16="Higher Low"),"Bullish",IF(AND(G16="Lower High",H16="Lower Low"),"Bearish","Mixed")) -> Mixed | O16: NASDAQ Composite | P16: 21830 | Q16: 22906 | R16: 22273
E17: =IF(AND(B167=B16,A167>A16),C16,"") | F17: =IF(AND(B167=B16,A167>A16),D16,"") | G17: =IF(E17="","",IF(C17>E17,"Higher High",IF(C17<E17,"Lower High","Flat"))) | H17: =IF(F17="","",IF(D17>F17,"Higher Low",IF(D17<F17,"Lower Low","Flat"))) | I17: =IF(AND(G17="Higher High",H17="Higher Low"),"Bullish",IF(AND(G17="Lower High",H17="Lower Low"),"Bearish","Mixed")) -> Mixed | O17: RUT (BEARISH)
E18: =IF(AND(B178=B17,A178>A17),C17,"") | F18: =IF(AND(B178=B17,A178>A17),D17,"") | G18: =IF(E18="","",IF(C18>E18,"Higher High",IF(C18<E18,"Lower High","Flat"))) | H18: =IF(F18="","",IF(D18>F18,"Higher Low",IF(D18<F18,"Lower Low","Flat"))) | I18: =IF(AND(G18="Higher High",H18="Higher Low"),"Bullish",IF(AND(G18="Lower High",H18="Lower Low"),"Bearish","Mixed")) -> Mixed | O18: Russell 2000 | P18: 2278 | Q18: 2412 | R18: 2369
E19: =IF(AND(B189=B18,A189>A18),C18,"") | F19: =IF(AND(B189=B18,A189>A18),D18,"") | G19: =IF(E19="","",IF(C19>E19,"Higher High",IF(C19<E19,"Lower High","Flat"))) | H19: =IF(F19="","",IF(D19>F19,"Higher Low",IF(D19<F19,"Lower Low","Flat"))) | I19: =IF(AND(G19="Higher High",H19="Higher Low"),"Bullish",IF(AND(G19="Lower High",H19="Lower Low"),"Bearish","Mixed")) -> Mixed | O19: XLK (BEARISH)
E20: =IF(AND(B20=B19,A20>A19),C19,"") | F20: =IF(AND(B20=B19,A20>A19),D19,"") | G20: =IF(E20="","",IF(C20>E20,"Higher High",IF(C20<E20,"Lower High","Flat"))) | H20: =IF(F20="","",IF(D20>F20,"Higher Low",IF(D20<F20,"Lower Low","Flat"))) | I20: =IF(AND(G20="Higher High",H20="Higher Low"),"Bullish",IF(AND(G20="Lower High",H20="Lower Low"),"Bearish","Mixed")) -> Mixed | O20: Technology Select Sector SPDR Fund | P20: 267 | Q20: 286 | R20: 273
E21: =IF(AND(B220=B20,A220>A20),C20,"") | F21: =IF(AND(B220=B20,A220>A20),D20,"") | G21: =IF(E21="","",IF(C21>E21,"Higher High",IF(C21<E21,"Lower High","Flat"))) | H21: =IF(F21="","",IF(D21>F21,"Higher Low",IF(D21<F21,"Lower Low","Flat"))) | I21: =IF(AND(G21="Higher High",H21="Higher Low"),"Bullish",IF(AND(G21="Lower High",H21="Lower Low"),"Bearish","Mixed")) -> Mixed | O21: XLV (BULLISH)
E22: =IF(AND(B22=B21,A22>A21),C21,"") | F22: =IF(AND(B22=B21,A22>A21),D21,"") | G22: =IF(E22="","",IF(C22>E22,"Higher High",IF(C22<E22,"Lower High","Flat"))) | H22: =IF(F22="","",IF(D22>F22,"Higher Low",IF(D22<F22,"Lower Low","Flat"))) | I22: =IF(AND(G22="Higher High",H22="Higher Low"),"Bullish",IF(AND(G22="Lower High",H22="Lower Low"),"Bearish","Mixed")) -> Mixed | O22: Health Care Select Sector SPDR Fund | P22: 151 | Q22: 156 | R22: 154.61
E23: =IF(AND(B23=B22,A23>A22),C22,"") | F23: =IF(AND(B23=B22,A23>A22),D22,"") | G23: =IF(E23="","",IF(C23>E23,"Higher High",IF(C23<E23,"Lower High","Flat"))) | H23: =IF(F23="","",IF(D23>F23,"Higher Low",IF(D23<F23,"Lower Low","Flat"))) | I23: =IF(AND(G23="Higher High",H23="Higher Low"),"Bullish",IF(AND(G23="Lower High",H23="Lower Low"),"Bearish","Mixed")) -> Mixed | O23: SSEC (BEARISH)
E24: =IF(AND(B24=B23,A24>A23),C23,"") | F24: =IF(AND(B24=B23,A24>A23),D23,"") | G24: =IF(E24="","",IF(C24>E24,"Higher High",IF(C24<E24,"Lower High","Flat"))) | H24: =IF(F24="","",IF(D24>F24,"Higher Low",IF(D24<F24,"Lower Low","Flat"))) | I24: =IF(AND(G24="Higher High",H24="Higher Low"),"Bullish",IF(AND(G24="Lower High",H24="Lower Low"),"Bearish","Mixed")) -> Mixed | O24: Shanghai Composite | P24: 3806 | Q24: 3961 | R24: 3836
E25: =IF(AND(B25=B24,A25>A24),C24,"") | F25: =IF(AND(B25=B24,A25>A24),D24,"") | G25: =IF(E25="","",IF(C25>E25,"Higher High",IF(C25<E25,"Lower High","Flat"))) | H25: =IF(F25="","",IF(D25>F25,"Higher Low",IF(D25<F25,"Lower Low","Flat"))) | I25: =IF(AND(G25="Higher High",H25="Higher Low"),"Bullish",IF(AND(G25="Lower High",H25="Lower Low"),"Bearish","Mixed")) -> Mixed | O25: NIKK (NEUTRAL)
E26: =IF(AND(B26=B25,A26>A25),C25,"") | F26: =IF(AND(B26=B25,A26>A25),D25,"") | G26: =IF(E26="","",IF(C26>E26,"Higher High",IF(C26<E26,"Lower High","Flat"))) | H26: =IF(F26="","",IF(D26>F26,"Higher Low",IF(D26<F26,"Lower Low","Flat"))) | I26: =IF(AND(G26="Higher High",H26="Higher Low"),"Bullish",IF(AND(G26="Lower High",H26="Lower Low"),"Bearish","Mixed")) -> Mixed | O26: Nikkei 225 Index | P26: 48218 | Q26: 51210 | R26: 48625
E27: =IF(AND(B27=B26,A27>A26),C26,"") | F27: =IF(AND(B27=B26,A27>A26),D26,"") | G27: =IF(E27="","",IF(C27>E27,"Higher High",IF(C27<E27,"Lower High","Flat"))) | H27: =IF(F27="","",IF(D27>F27,"Higher Low",IF(D27<F27,"Lower Low","Flat"))) | I27: =IF(AND(G27="Higher High",H27="Higher Low"),"Bullish",IF(AND(G27="Lower High",H27="Lower Low"),"Bearish","Mixed")) -> Mixed | O27: DAX (BEARISH)
E28: =IF(AND(B28=B27,A28>A27),C27,"") | F28: =IF(AND(B28=B27,A28>A27),D27,"") | G28: =IF(E28="","",IF(C28>E28,"Higher High",IF(C28<E28,"Lower High","Flat"))) | H28: =IF(F28="","",IF(D28>F28,"Higher Low",IF(D28<F28,"Lower Low","Flat"))) | I28: =IF(AND(G28="Higher High",H28="Higher Low"),"Bullish",IF(AND(G28="Lower High",H28="Lower Low"),"Bearish","Mixed")) -> Mixed | O28: German DAX Composite | P28: 22708 | Q28: 23815 | R28: 23091
E29: =IF(AND(B29=B28,A29>A28),C28,"") | F29: =IF(AND(B29=B28,A29>A28),D28,"") | G29: =IF(E29="","",IF(C29>E29,"Higher High",IF(C29<E29,"Lower High","Flat"))) | H29: =IF(F29="","",IF(D29>F29,"Higher Low",IF(D29<F29,"Lower Low","Flat"))) | I29: =IF(AND(G29="Higher High",H29="Higher Low"),"Bullish",IF(AND(G29="Lower High",H29="Lower Low"),"Bearish","Mixed")) -> Mixed | O29: VIX (BULLISH)
E30: =IF(AND(B30=B29,A30>A29),C29,"") | F30: =IF(AND(B30=B29,A30>A29),D29,"") | G30: =IF(E30="","",IF(C30>E30,"Higher High",IF(C30<E30,"Lower High","Flat"))) | H30: =IF(F30="","",IF(D30>F30,"Higher Low",IF(D30<F30,"Lower Low","Flat"))) | I30: =IF(AND(G30="Higher High",H30="Higher Low"),"Bullish",IF(AND(G30="Lower High",H30="Lower Low"),"Bearish","Mixed")) -> Mixed | O30: Volatility Index | P30: 19.87 | Q30: 27.97 | R30: 23.43
E31: =IF(AND(B330=B30,A330>A30),C30,"") | F31: =IF(AND(B330=B30,A330>A30),D30,"") | G31: =IF(E31="","",IF(C31>E31,"Higher High",IF(C31<E31,"Lower High","Flat"))) | H31: =IF(F31="","",IF(D31>F31,"Higher Low",IF(D31<F31,"Lower Low","Flat"))) | I31: =IF(AND(G31="Higher High",H31="Higher Low"),"Bullish",IF(AND(G31="Lower High",H31="Lower Low"),"Bearish","Mixed")) -> Mixed | O31: USD (BULLISH)
E32: =IF(AND(B32=B31,A32>A31),C31,"") | F32: =IF(AND(B32=B31,A32>A31),D31,"") | G32: =IF(E32="","",IF(C32>E32,"Higher High",IF(C32<E32,"Lower High","Flat"))) | H32: =IF(F32="","",IF(D32>F32,"Higher Low",IF(D32<F32,"Lower Low","Flat"))) | I32: =IF(AND(G32="Higher High",H32="Higher Low"),"Bullish",IF(AND(G32="Lower High",H32="Lower Low"),"Bearish","Mixed")) -> Mixed | O32: U.S. Dollar Index | P32: 99.46 | Q32: 100.57 | R32: 100.07
E33: =IF(AND(B33=B32,A33>A32),C32,"") | F33: =IF(AND(B33=B32,A33>A32),D32,"") | G33: =IF(E33="","",IF(C33>E33,"Higher High",IF(C33<E33,"Lower High","Flat"))) | H33: =IF(F33="","",IF(D33>F33,"Higher Low",IF(D33<F33,"Lower Low","Flat"))) | I33: =IF(AND(G33="Higher High",H33="Higher Low"),"Bullish",IF(AND(G33="Lower High",H33="Lower Low"),"Bearish","Mixed")) -> Mixed | O33: EUR/USD (BEARISH)
E34: =IF(AND(B34=B33,A34>A33),C33,"") | F34: =IF(AND(B34=B33,A34>A33),D33,"") | G34: =IF(E34="","",IF(C34>E34,"Higher High",IF(C34<E34,"Lower High","Flat"))) | H34: =IF(F34="","",IF(D34>F34,"Higher Low",IF(D34<F34,"Lower Low","Flat"))) | I34: =IF(AND(G34="Higher High",H34="Higher Low"),"Bullish",IF(AND(G34="Lower High",H34="Lower Low"),"Bearish","Mixed")) -> Mixed | O34: Euro to U.S. Dollar | P34: 1.148 | Q34: 1.16 | R34: 1.154
E35: =IF(AND(B35=B34,A35>A34),C34,"") | F35: =IF(AND(B35=B34,A35>A34),D34,"") | G35: =IF(E35="","",IF(C35>E35,"Higher High",IF(C35<E35,"Lower High","Flat"))) | H35: =IF(F35="","",IF(D35>F35,"Higher Low",IF(D35<F35,"Lower Low","Flat"))) | I35: =IF(AND(G35="Higher High",H35="Higher Low"),"Bullish",IF(AND(G35="Lower High",H35="Lower Low"),"Bearish","Mixed")) -> Mixed | O35: USD/YEN (BULLISH)
E36: =IF(AND(B36=B35,A36>A35),C35,"") | F36: =IF(AND(B36=B35,A36>A35),D35,"") | G36: =IF(E36="","",IF(C36>E36,"Higher High",IF(C36<E36,"Lower High","Flat"))) | H36: =IF(F36="","",IF(D36>F36,"Higher Low",IF(D36<F36,"Lower Low","Flat"))) | I36: =IF(AND(G36="Higher High",H36="Higher Low"),"Bullish",IF(AND(G36="Lower High",H36="Lower Low"),"Bearish","Mixed")) -> Mixed | O36: U.S. Dollar to Japanese Yen | P36: 154.18 | Q36: 157.97 | R36: 156.82
E37: =IF(AND(B37=B36,A37>A36),C36,"") | F37: =IF(AND(B37=B36,A37>A36),D36,"") | G37: =IF(E37="","",IF(C37>E37,"Higher High",IF(C37<E37,"Lower High","Flat"))) | H37: =IF(F37="","",IF(D37>F37,"Higher Low",IF(D37<F37,"Lower Low","Flat"))) | I37: =IF(AND(G37="Higher High",H37="Higher Low"),"Bullish",IF(AND(G37="Lower High",H37="Lower Low"),"Bearish","Mixed")) -> Mixed | O37: GBP/USD (BEARISH)
E38: =IF(AND(B38=B37,A38>A37),C37,"") | F38: =IF(AND(B38=B37,A38>A37),D37,"") | G38: =IF(E38="","",IF(C38>E38,"Higher High",IF(C38<E38,"Lower High","Flat"))) | H38: =IF(F38="","",IF(D38>F38,"Higher Low",IF(D38<F38,"Lower Low","Flat"))) | I38: =IF(AND(G38="Higher High",H38="Higher Low"),"Bullish",IF(AND(G38="Lower High",H38="Lower Low"),"Bearish","Mixed")) -> Mixed | O38: British Pound to U.S. Dollar | P38: 1.303 | Q38: 1.319 | R38: 1.311
E39: =IF(AND(B39=B38,A39>A38),C38,"") | F39: =IF(AND(B39=B38,A39>A38),D38,"") | G39: =IF(E39="","",IF(C39>E39,"Higher High",IF(C39<E39,"Lower High","Flat"))) | H39: =IF(F39="","",IF(D39>F39,"Higher Low",IF(D39<F39,"Lower Low","Flat"))) | I39: =IF(AND(G39="Higher High",H39="Higher Low"),"Bullish",IF(AND(G39="Lower High",H39="Lower Low"),"Bearish","Mixed")) -> Mixed | O39: CAD/USD (BEARISH)
E40: =IF(AND(B40=B39,A40>A39),C39,"") | F40: =IF(AND(B40=B39,A40>A39),D39,"") | G40: =IF(E40="","",IF(C40>E40,"Higher High",IF(C40<E40,"Lower High","Flat"))) | H40: =IF(F40="","",IF(D40>F40,"Higher Low",IF(D40<F40,"Lower Low","Flat"))) | I40: =IF(AND(G40="Higher High",H40="Higher Low"),"Bullish",IF(AND(G40="Lower High",H40="Lower Low"),"Bearish","Mixed")) -> Mixed | O40: Canadian Dollar to U.S. Dollar | P40: 0.706 | Q40: 0.717 | R40: 0.708
E41: =IF(AND(B440=B40,A440>A40),C40,"") | F41: =IF(AND(B440=B40,A440>A40),D40,"") | G41: =IF(E41="","",IF(C41>E41,"Higher High",IF(C41<E41,"Lower High","Flat"))) | H41: =IF(F41="","",IF(D41>F41,"Higher Low",IF(D41<F41,"Lower Low","Flat"))) | I41: =IF(AND(G41="Higher High",H41="Higher Low"),"Bullish",IF(AND(G41="Lower High",H41="Lower Low"),"Bearish","Mixed")) -> Mixed | O41: WTIC (BEARISH)
E42: =IF(AND(B42=B41,A42>A41),C41,"") | F42: =IF(AND(B42=B41,A42>A41),D41,"") | G42: =IF(E42="","",IF(C42>E42,"Higher High",IF(C42<E42,"Lower High","Flat"))) | H42: =IF(F42="","",IF(D42>F42,"Higher Low",IF(D42<F42,"Lower Low","Flat"))) | I42: =IF(AND(G42="Higher High",H42="Higher Low"),"Bullish",IF(AND(G42="Lower High",H42="Lower Low"),"Bearish","Mixed")) -> Mixed | O42: Light Crude Oil Continuous Contract | P42: 57.01 | Q42: 59.96 | R42: 57.98
E43: =IF(AND(B43=B42,A43>A42),C42,"") | F43: =IF(AND(B43=B42,A43>A42),D42,"") | G43: =IF(E43="","",IF(C43>E43,"Higher High",IF(C43<E43,"Lower High","Flat"))) | H43: =IF(F43="","",IF(D43>F43,"Higher Low",IF(D43<F43,"Lower Low","Flat"))) | I43: =IF(AND(G43="Higher High",H43="Higher Low"),"Bullish",IF(AND(G43="Lower High",H43="Lower Low"),"Bearish","Mixed")) -> Mixed | O43: BRENT (BEARISH)
E44: =IF(AND(B44=B43,A44>A43),C43,"") | F44: =IF(AND(B44=B43,A44>A43),D43,"") | G44: =IF(E44="","",IF(C44>E44,"Higher High",IF(C44<E44,"Lower High","Flat"))) | H44: =IF(F44="","",IF(D44>F44,"Higher Low",IF(D44<F44,"Lower Low","Flat"))) | I44: =IF(AND(G44="Higher High",H44="Higher Low"),"Bullish",IF(AND(G44="Lower High",H44="Lower Low"),"Bearish","Mixed")) -> Mixed | O44: Brent Crude Oil Continuous Contract | P44: 61 | Q44: 64.15 | R44: 62.47
E45: =IF(AND(B45=B44,A45>A44),C44,"") | F45: =IF(AND(B45=B44,A45>A44),D44,"") | G45: =IF(E45="","",IF(C45>E45,"Higher High",IF(C45<E45,"Lower High","Flat"))) | H45: =IF(F45="","",IF(D45>F45,"Higher Low",IF(D45<F45,"Lower Low","Flat"))) | I45: =IF(AND(G45="Higher High",H45="Higher Low"),"Bullish",IF(AND(G45="Lower High",H45="Lower Low"),"Bearish","Mixed")) -> Mixed | O45: NATGAS (BULLISH)
E46: =IF(AND(B46=B45,A46>A45),C45,"") | F46: =IF(AND(B46=B45,A46>A45),D45,"") | G46: =IF(E46="","",IF(C46>E46,"Higher High",IF(C46<E46,"Lower High","Flat"))) | H46: =IF(F46="","",IF(D46>F46,"Higher Low",IF(D46<F46,"Lower Low","Flat"))) | I46: =IF(AND(G46="Higher High",H46="Higher Low"),"Bullish",IF(AND(G46="Lower High",H46="Lower Low"),"Bearish","Mixed")) -> Mixed | O46: Natural Gas Continuous Contract | P46: 4.28 | Q46: 4.75 | R46: 4.57
E47: =IF(AND(B47=B46,A47>A46),C46,"") | F47: =IF(AND(B47=B46,A47>A46),D46,"") | G47: =IF(E47="","",IF(C47>E47,"Higher High",IF(C47<E47,"Lower High","Flat"))) | H47: =IF(F47="","",IF(D47>F47,"Higher Low",IF(D47<F47,"Lower Low","Flat"))) | I47: =IF(AND(G47="Higher High",H47="Higher Low"),"Bullish",IF(AND(G47="Lower High",H47="Lower Low"),"Bearish","Mixed")) -> Mixed | O47: GOLD (BULLISH)
E48: =IF(AND(B48=B47,A48>A47),C47,"") | F48: =IF(AND(B48=B47,A48>A47),D47,"") | G48: =IF(E48="","",IF(C48>E48,"Higher High",IF(C48<E48,"Lower High","Flat"))) | H48: =IF(F48="","",IF(D48>F48,"Higher Low",IF(D48<F48,"Lower Low","Flat"))) | I48: =IF(AND(G48="Higher High",H48="Higher Low"),"Bullish",IF(AND(G48="Lower High",H48="Lower Low"),"Bearish","Mixed")) -> Mixed | O48: Gold Spot Price | P48: 4001 | Q48: 4208 | R48: 4071
E49: =IF(AND(B49=B48,A49>A48),C48,"") | F49: =IF(AND(B49=B48,A49>A48),D48,"") | G49: =IF(E49="","",IF(C49>E49,"Higher High",IF(C49<E49,"Lower High","Flat"))) | H49: =IF(F49="","",IF(D49>F49,"Higher Low",IF(D49<F49,"Lower Low","Flat"))) | I49: =IF(AND(G49="Higher High",H49="Higher Low"),"Bullish",IF(AND(G49="Lower High",H49="Lower Low"),"Bearish","Mixed")) -> Mixed | O49: COPPER (BULLISH)
E50: =IF(AND(B50=B49,A50>A49),C49,"") | F50: =IF(AND(B50=B49,A50>A49),D49,"") | G50: =IF(E50="","",IF(C50>E50,"Higher High",IF(C50<E50,"Lower High","Flat"))) | H50: =IF(F50="","",IF(D50>F50,"Higher Low",IF(D50<F50,"Lower Low","Flat"))) | I50: =IF(AND(G50="Higher High",H50="Higher Low"),"Bullish",IF(AND(G50="Lower High",H50="Lower Low"),"Bearish","Mixed")) -> Mixed | O50: Copper Continuous Contract | P50: 4.89 | Q50: 5.14 | R50: 4.99
E51: =IF(AND(B550=B50,A550>A50),C50,"") | F51: =IF(AND(B550=B50,A550>A50),D50,"") | G51: =IF(E51="","",IF(C51>E51,"Higher High",IF(C51<E51,"Lower High","Flat"))) | H51: =IF(F51="","",IF(D51>F51,"Higher Low",IF(D51<F51,"Lower Low","Flat"))) | I51: =IF(AND(G51="Higher High",H51="Higher Low"),"Bullish",IF(AND(G51="Lower High",H51="Lower Low"),"Bearish","Mixed")) -> Mixed | O51: SILVER (BULLISH)
E52: =IF(AND(B52=B51,A52>A51),C51,"") | F52: =IF(AND(B52=B51,A52>A51),D51,"") | G52: =IF(E52="","",IF(C52>E52,"Higher High",IF(C52<E52,"Lower High","Flat"))) | H52: =IF(F52="","",IF(D52>F52,"Higher Low",IF(D52<F52,"Lower Low","Flat"))) | I52: =IF(AND(G52="Higher High",H52="Higher Low"),"Bullish",IF(AND(G52="Lower High",H52="Lower Low"),"Bearish","Mixed")) -> Mixed | O52: Silver Spot Price | P52: 49 | Q52: 53.29 | R52: 49.97
E53: =IF(AND(B53=B52,A53>A52),C52,"") | F53: =IF(AND(B53=B52,A53>A52),D52,"") | G53: =IF(E53="","",IF(C53>E53,"Higher High",IF(C53<E53,"Lower High","Flat"))) | H53: =IF(F53="","",IF(D53>F53,"Higher Low",IF(D53<F53,"Lower Low","Flat"))) | I53: =IF(AND(G53="Higher High",H53="Higher Low"),"Bullish",IF(AND(G53="Lower High",H53="Lower Low"),"Bearish","Mixed")) -> Mixed | O53: MSFT (BEARISH)
E54: =IF(AND(B54=B53,A54>A53),C53,"") | F54: =IF(AND(B54=B53,A54>A53),D53,"") | G54: =IF(E54="","",IF(C54>E54,"Higher High",IF(C54<E54,"Lower High","Flat"))) | H54: =IF(F54="","",IF(D54>F54,"Higher Low",IF(D54<F54,"Lower Low","Flat"))) | I54: =IF(AND(G54="Higher High",H54="Higher Low"),"Bullish",IF(AND(G54="Lower High",H54="Lower Low"),"Bearish","Mixed")) -> Mixed | O54: Microsoft Corp. | P54: 466 | Q54: 496 | R54: 472
E55: =IF(AND(B55=B54,A55>A54),C54,"") | F55: =IF(AND(B55=B54,A55>A54),D54,"") | G55: =IF(E55="","",IF(C55>E55,"Higher High",IF(C55<E55,"Lower High","Flat"))) | H55: =IF(F55="","",IF(D55>F55,"Higher Low",IF(D55<F55,"Lower Low","Flat"))) | I55: =IF(AND(G55="Higher High",H55="Higher Low"),"Bullish",IF(AND(G55="Lower High",H55="Lower Low"),"Bearish","Mixed")) -> Mixed | O55: AAPL (BULLISH)
E56: =IF(AND(B56=B55,A56>A55),C55,"") | F56: =IF(AND(B56=B55,A56>A55),D55,"") | G56: =IF(E56="","",IF(C56>E56,"Higher High",IF(C56<E56,"Lower High","Flat"))) | H56: =IF(F56="","",IF(D56>F56,"Higher Low",IF(D56<F56,"Lower Low","Flat"))) | I56: =IF(AND(G56="Higher High",H56="Higher Low"),"Bullish",IF(AND(G56="Lower High",H56="Lower Low"),"Bearish","Mixed")) -> Mixed | O56: Apple Inc. | P56: 265 | Q56: 279 | R56: 271
E57: =IF(AND(B57=B56,A57>A56),C56,"") | F57: =IF(AND(B57=B56,A57>A56),D56,"") | G57: =IF(E57="","",IF(C57>E57,"Higher High",IF(C57<E57,"Lower High","Flat"))) | H57: =IF(F57="","",IF(D57>F57,"Higher Low",IF(D57<F57,"Lower Low","Flat"))) | I57: =IF(AND(G57="Higher High",H57="Higher Low"),"Bullish",IF(AND(G57="Lower High",H57="Lower Low"),"Bearish","Mixed")) -> Mixed | O57: AMZN (BEARISH)
E58: =IF(AND(B58=B57,A58>A57),C57,"") | F58: =IF(AND(B58=B57,A58>A57),D57,"") | G58: =IF(E58="","",IF(C58>E58,"Higher High",IF(C58<E58,"Lower High","Flat"))) | H58: =IF(F58="","",IF(D58>F58,"Higher Low",IF(D58<F58,"Lower Low","Flat"))) | I58: =IF(AND(G58="Higher High",H58="Higher Low"),"Bullish",IF(AND(G58="Lower High",H58="Lower Low"),"Bearish","Mixed")) -> Mixed | O58: Amazon Inc. | P58: 209 | Q58: 231 | R58: 221
E59: =IF(AND(B59=B58,A59>A58),C58,"") | F59: =IF(AND(B59=B58,A59>A58),D58,"") | G59: =IF(E59="","",IF(C59>E59,"Higher High",IF(C59<E59,"Lower High","Flat"))) | H59: =IF(F59="","",IF(D59>F59,"Higher Low",IF(D59<F59,"Lower Low","Flat"))) | I59: =IF(AND(G59="Higher High",H59="Higher Low"),"Bullish",IF(AND(G59="Lower High",H59="Lower Low"),"Bearish","Mixed")) -> Mixed | O59: META (BEARISH)
E60: =IF(AND(B60=B59,A60>A59),C59,"") | F60: =IF(AND(B60=B59,A60>A59),D59,"") | G60: =IF(E60="","",IF(C60>E60,"Higher High",IF(C60<E60,"Lower High","Flat"))) | H60: =IF(F60="","",IF(D60>F60,"Higher Low",IF(D60<F60,"Lower Low","Flat"))) | I60: =IF(AND(G60="Higher High",H60="Higher Low"),"Bullish",IF(AND(G60="Lower High",H60="Lower Low"),"Bearish","Mixed")) -> Mixed | O60: Meta Platforms Inc. | P60: 579 | Q60: 624 | R60: 594
E61: =IF(AND(B660=B60,A660>A60),C60,"") | F61: =IF(AND(B660=B60,A660>A60),D60,"") | G61: =IF(E61="","",IF(C61>E61,"Higher High",IF(C61<E61,"Lower High","Flat"))) | H61: =IF(F61="","",IF(D61>F61,"Higher Low",IF(D61<F61,"Lower Low","Flat"))) | I61: =IF(AND(G61="Higher High",H61="Higher Low"),"Bullish",IF(AND(G61="Lower High",H61="Lower Low"),"Bearish","Mixed")) -> Mixed | O61: GOOGL (BULLISH)
E62: =IF(AND(B62=B61,A62>A61),C61,"") | F62: =IF(AND(B62=B61,A62>A61),D61,"") | G62: =IF(E62="","",IF(C62>E62,"Higher High",IF(C62<E62,"Lower High","Flat"))) | H62: =IF(F62="","",IF(D62>F62,"Higher Low",IF(D62<F62,"Lower Low","Flat"))) | I62: =IF(AND(G62="Higher High",H62="Higher Low"),"Bullish",IF(AND(G62="Lower High",H62="Lower Low"),"Bearish","Mixed")) -> Mixed | O62: Alphabet Inc. | P62: 281 | Q62: 304 | R62: 300
E63: =IF(AND(B63=B62,A63>A62),C62,"") | F63: =IF(AND(B63=B62,A63>A62),D62,"") | G63: =IF(E63="","",IF(C63>E63,"Higher High",IF(C63<E63,"Lower High","Flat"))) | H63: =IF(F63="","",IF(D63>F63,"Higher Low",IF(D63<F63,"Lower Low","Flat"))) | I63: =IF(AND(G63="Higher High",H63="Higher Low"),"Bullish",IF(AND(G63="Lower High",H63="Lower Low"),"Bearish","Mixed")) -> Mixed | O63: NFLX (BEARISH)
E64: =IF(AND(B64=B63,A64>A63),C63,"") | F64: =IF(AND(B64=B63,A64>A63),D63,"") | G64: =IF(E64="","",IF(C64>E64,"Higher High",IF(C64<E64,"Lower High","Flat"))) | H64: =IF(F64="","",IF(D64>F64,"Higher Low",IF(D64<F64,"Lower Low","Flat"))) | I64: =IF(AND(G64="Higher High",H64="Higher Low"),"Bullish",IF(AND(G64="Lower High",H64="Lower Low"),"Bearish","Mixed")) -> Mixed | O64: Netflix Inc. | P64: 100 | Q64: 111 | R64: 104
E65: =IF(AND(B65=B64,A65>A64),C64,"") | F65: =IF(AND(B65=B64,A65>A64),D64,"") | G65: =IF(E65="","",IF(C65>E65,"Higher High",IF(C65<E65,"Lower High","Flat"))) | H65: =IF(F65="","",IF(D65>F65,"Higher Low",IF(D65<F65,"Lower Low","Flat"))) | I65: =IF(AND(G65="Higher High",H65="Higher Low"),"Bullish",IF(AND(G65="Lower High",H65="Lower Low"),"Bearish","Mixed")) -> Mixed | O65: TSLA (BEARISH)
E66: =IF(AND(B66=B65,A66>A65),C65,"") | F66: =IF(AND(B66=B65,A66>A65),D65,"") | G66: =IF(E66="","",IF(C66>E66,"Higher High",IF(C66<E66,"Lower High","Flat"))) | H66: =IF(F66="","",IF(D66>F66,"Higher Low",IF(D66<F66,"Lower Low","Flat"))) | I66: =IF(AND(G66="Higher High",H66="Higher Low"),"Bullish",IF(AND(G66="Lower High",H66="Lower Low"),"Bearish","Mixed")) -> Mixed | O66: Tesla Inc. | P66: 376 | Q66: 423 | R66: 391
E67: =IF(AND(B67=B66,A67>A66),C66,"") | F67: =IF(AND(B67=B66,A67>A66),D66,"") | G67: =IF(E67="","",IF(C67>E67,"Higher High",IF(C67<E67,"Lower High","Flat"))) | H67: =IF(F67="","",IF(D67>F67,"Higher Low",IF(D67<F67,"Lower Low","Flat"))) | I67: =IF(AND(G67="Higher High",H67="Higher Low"),"Bullish",IF(AND(G67="Lower High",H67="Lower Low"),"Bearish","Mixed")) -> Mixed | O67: NVDA (NEUTRAL)
E68: =IF(AND(B68=B67,A68>A67),C67,"") | F68: =IF(AND(B68=B67,A68>A67),D67,"") | G68: =IF(E68="","",IF(C68>E68,"Higher High",IF(C68<E68,"Lower High","Flat"))) | H68: =IF(F68="","",IF(D68>F68,"Higher Low",IF(D68<F68,"Lower Low","Flat"))) | I68: =IF(AND(G68="Higher High",H68="Higher Low"),"Bullish",IF(AND(G68="Lower High",H68="Lower Low"),"Bearish","Mixed")) -> Mixed | O68: NVIDIA Corporation | P68: 174 | Q68: 195 | R68: 179
E69: =IF(AND(B69=B68,A69>A68),C68,"") | F69: =IF(AND(B69=B68,A69>A68),D68,"") | G69: =IF(E69="","",IF(C69>E69,"Higher High",IF(C69<E69,"Lower High","Flat"))) | H69: =IF(F69="","",IF(D69>F69,"Higher Low",IF(D69<F69,"Lower Low","Flat"))) | I69: =IF(AND(G69="Higher High",H69="Higher Low"),"Bullish",IF(AND(G69="Lower High",H69="Lower Low"),"Bearish","Mixed")) -> Mixed | O69: ORCL (BEARISH)
E70: =IF(AND(B70=B69,A70>A69),C69,"") | F70: =IF(AND(B70=B69,A70>A69),D69,"") | G70: =IF(E70="","",IF(C70>E70,"Higher High",IF(C70<E70,"Lower High","Flat"))) | H70: =IF(F70="","",IF(D70>F70,"Higher Low",IF(D70<F70,"Lower Low","Flat"))) | I70: =IF(AND(G70="Higher High",H70="Higher Low"),"Bullish",IF(AND(G70="Lower High",H70="Lower Low"),"Bearish","Mixed")) -> Mixed | O70: Oracle Corporation | P70: 194 | Q70: 224 | R70: 198.76
E71: =IF(AND(B770=B70,A770>A70),C70,"") | F71: =IF(AND(B770=B70,A770>A70),D70,"") | G71: =IF(E71="","",IF(C71>E71,"Higher High",IF(C71<E71,"Lower High","Flat"))) | H71: =IF(F71="","",IF(D71>F71,"Higher Low",IF(D71<F71,"Lower Low","Flat"))) | I71: =IF(AND(G71="Higher High",H71="Higher Low"),"Bullish",IF(AND(G71="Lower High",H71="Lower Low"),"Bearish","Mixed")) -> Mixed | O71: BITCOIN (BEARISH)
E72: =IF(AND(B72=B71,A72>A71),C71,"") | F72: =IF(AND(B72=B71,A72>A71),D71,"") | G72: =IF(E72="","",IF(C72>E72,"Higher High",IF(C72<E72,"Lower High","Flat"))) | H72: =IF(F72="","",IF(D72>F72,"Higher Low",IF(D72<F72,"Lower Low","Flat"))) | I72: =IF(AND(G72="Higher High",H72="Higher Low"),"Bullish",IF(AND(G72="Lower High",H72="Lower Low"),"Bearish","Mixed")) -> Mixed | O72: Bitcoin Spot Price | P72: 80726 | Q72: 89954 | R72: 86157
E73: =IF(AND(B73=B72,A73>A72),C72,"") | F73: =IF(AND(B73=B72,A73>A72),D72,"") | G73: =IF(E73="","",IF(C73>E73,"Higher High",IF(C73<E73,"Lower High","Flat"))) | H73: =IF(F73="","",IF(D73>F73,"Higher Low",IF(D73<F73,"Lower Low","Flat"))) | I73: =IF(AND(G73="Higher High",H73="Higher Low"),"Bullish",IF(AND(G73="Lower High",H73="Lower Low"),"Bearish","Mixed")) -> Mixed
E74: =IF(AND(B74=B73,A74>A73),C73,"") | F74: =IF(AND(B74=B73,A74>A73),D73,"") | G74: =IF(E74="","",IF(C74>E74,"Higher High",IF(C74<E74,"Lower High","Flat"))) | H74: =IF(F74="","",IF(D74>F74,"Higher Low",IF(D74<F74,"Lower Low","Flat"))) | I74: =IF(AND(G74="Higher High",H74="Higher Low"),"Bullish",IF(AND(G74="Lower High",H74="Lower Low"),"Bearish","Mixed")) -> Mixed
E75: =IF(AND(B75=B74,A75>A74),C74,"") | F75: =IF(AND(B75=B74,A75>A74),D74,"") | G75: =IF(E75="","",IF(C75>E75,"Higher High",IF(C75<E75,"Lower High","Flat"))) | H75: =IF(F75="","",IF(D75>F75,"Higher Low",IF(D75<F75,"Lower Low","Flat"))) | I75: =IF(AND(G75="Higher High",H75="Higher Low"),"Bullish",IF(AND(G75="Lower High",H75="Lower Low"),"Bearish","Mixed")) -> Mixed
E76: =IF(AND(B76=B75,A76>A75),C75,"") | F76: =IF(AND(B76=B75,A76>A75),D75,"") | G76: =IF(E76="","",IF(C76>E76,"Higher High",IF(C76<E76,"Lower High","Flat"))) | H76: =IF(F76="","",IF(D76>F76,"Higher Low",IF(D76<F76,"Lower Low","Flat"))) | I76: =IF(AND(G76="Higher High",H76="Higher Low"),"Bullish",IF(AND(G76="Lower High",H76="Lower Low"),"Bearish","Mixed")) -> Mixed
E77: =IF(AND(B77=B76,A77>A76),C76,"") | F77: =IF(AND(B77=B76,A77>A76),D76,"") | G77: =IF(E77="","",IF(C77>E77,"Higher High",IF(C77<E77,"Lower High","Flat"))) | H77: =IF(F77="","",IF(D77>F77,"Higher Low",IF(D77<F77,"Lower Low","Flat"))) | I77: =IF(AND(G77="Higher High",H77="Higher Low"),"Bullish",IF(AND(G77="Lower High",H77="Lower Low"),"Bearish","Mixed")) -> Mixed
E78: =IF(AND(B78=B77,A78>A77),C77,"") | F78: =IF(AND(B78=B77,A78>A77),D77,"") | G78: =IF(E78="","",IF(C78>E78,"Higher High",IF(C78<E78,"Lower High","Flat"))) | H78: =IF(F78="","",IF(D78>F78,"Higher Low",IF(D78<F78,"Lower Low","Flat"))) | I78: =IF(AND(G78="Higher High",H78="Higher Low"),"Bullish",IF(AND(G78="Lower High",H78="Lower Low"),"Bearish","Mixed")) -> Mixed
E79: =IF(AND(B79=B78,A79>A78),C78,"") | F79: =IF(AND(B79=B78,A79>A78),D78,"") | G79: =IF(E79="","",IF(C79>E79,"Higher High",IF(C79<E79,"Lower High","Flat"))) | H79: =IF(F79="","",IF(D79>F79,"Higher Low",IF(D79<F79,"Lower Low","Flat"))) | I79: =IF(AND(G79="Higher High",H79="Higher Low"),"Bullish",IF(AND(G79="Lower High",H79="Lower Low"),"Bearish","Mixed")) -> Mixed
E80: =IF(AND(B80=B79,A80>A79),C79,"") | F80: =IF(AND(B80=B79,A80>A79),D79,"") | G80: =IF(E80="","",IF(C80>E80,"Higher High",IF(C80<E80,"Lower High","Flat"))) | H80: =IF(F80="","",IF(D80>F80,"Higher Low",IF(D80<F80,"Lower Low","Flat"))) | I80: =IF(AND(G80="Higher High",H80="Higher Low"),"Bullish",IF(AND(G80="Lower High",H80="Lower Low"),"Bearish","Mixed")) -> Mixed
E81: =IF(AND(B880=B80,A880>A80),C80,"") | F81: =IF(AND(B880=B80,A880>A80),D80,"") | G81: =IF(E81="","",IF(C81>E81,"Higher High",IF(C81<E81,"Lower High","Flat"))) | H81: =IF(F81="","",IF(D81>F81,"Higher Low",IF(D81<F81,"Lower Low","Flat"))) | I81: =IF(AND(G81="Higher High",H81="Higher Low"),"Bullish",IF(AND(G81="Lower High",H81="Lower Low"),"Bearish","Mixed")) -> Mixed
E82: =IF(AND(B82=B81,A82>A81),C81,"") | F82: =IF(AND(B82=B81,A82>A81),D81,"") | G82: =IF(E82="","",IF(C82>E82,"Higher High",IF(C82<E82,"Lower High","Flat"))) | H82: =IF(F82="","",IF(D82>F82,"Higher Low",IF(D82<F82,"Lower Low","Flat"))) | I82: =IF(AND(G82="Higher High",H82="Higher Low"),"Bullish",IF(AND(G82="Lower High",H82="Lower Low"),"Bearish","Mixed")) -> Mixed
E83: =IF(AND(B83=B82,A83>A82),C82,"") | F83: =IF(AND(B83=B82,A83>A82),D82,"") | G83: =IF(E83="","",IF(C83>E83,"Higher High",IF(C83<E83,"Lower High","Flat"))) | H83: =IF(F83="","",IF(D83>F83,"Higher Low",IF(D83<F83,"Lower Low","Flat"))) | I83: =IF(AND(G83="Higher High",H83="Higher Low"),"Bullish",IF(AND(G83="Lower High",H83="Lower Low"),"Bearish","Mixed")) -> Mixed
E84: =IF(AND(B84=B83,A84>A83),C83,"") | F84: =IF(AND(B84=B83,A84>A83),D83,"") | G84: =IF(E84="","",IF(C84>E84,"Higher High",IF(C84<E84,"Lower High","Flat"))) | H84: =IF(F84="","",IF(D84>F84,"Higher Low",IF(D84<F84,"Lower Low","Flat"))) | I84: =IF(AND(G84="Higher High",H84="Higher Low"),"Bullish",IF(AND(G84="Lower High",H84="Lower Low"),"Bearish","Mixed")) -> Mixed
E85: =IF(AND(B85=B84,A85>A84),C84,"") | F85: =IF(AND(B85=B84,A85>A84),D84,"") | G85: =IF(E85="","",IF(C85>E85,"Higher High",IF(C85<E85,"Lower High","Flat"))) | H85: =IF(F85="","",IF(D85>F85,"Higher Low",IF(D85<F85,"Lower Low","Flat"))) | I85: =IF(AND(G85="Higher High",H85="Higher Low"),"Bullish",IF(AND(G85="Lower High",H85="Lower Low"),"Bearish","Mixed")) -> Mixed
E86: =IF(AND(B86=B85,A86>A85),C85,"") | F86: =IF(AND(B86=B85,A86>A85),D85,"") | G86: =IF(E86="","",IF(C86>E86,"Higher High",IF(C86<E86,"Lower High","Flat"))) | H86: =IF(F86="","",IF(D86>F86,"Higher Low",IF(D86<F86,"Lower Low","Flat"))) | I86: =IF(AND(G86="Higher High",H86="Higher Low"),"Bullish",IF(AND(G86="Lower High",H86="Lower Low"),"Bearish","Mixed")) -> Mixed
E87: =IF(AND(B87=B86,A87>A86),C86,"") | F87: =IF(AND(B87=B86,A87>A86),D86,"") | G87: =IF(E87="","",IF(C87>E87,"Higher High",IF(C87<E87,"Lower High","Flat"))) | H87: =IF(F87="","",IF(D87>F87,"Higher Low",IF(D87<F87,"Lower Low","Flat"))) | I87: =IF(AND(G87="Higher High",H87="Higher Low"),"Bullish",IF(AND(G87="Lower High",H87="Lower Low"),"Bearish","Mixed")) -> Mixed
E88: =IF(AND(B88=B87,A88>A87),C87,"") | F88: =IF(AND(B88=B87,A88>A87),D87,"") | G88: =IF(E88="","",IF(C88>E88,"Higher High",IF(C88<E88,"Lower High","Flat"))) | H88: =IF(F88="","",IF(D88>F88,"Higher Low",IF(D88<F88,"Lower Low","Flat"))) | I88: =IF(AND(G88="Higher High",H88="Higher Low"),"Bullish",IF(AND(G88="Lower High",H88="Lower Low"),"Bearish","Mixed")) -> Mixed
E89: =IF(AND(B89=B88,A89>A88),C88,"") | F89: =IF(AND(B89=B88,A89>A88),D88,"") | G89: =IF(E89="","",IF(C89>E89,"Higher High",IF(C89<E89,"Lower High","Flat"))) | H89: =IF(F89="","",IF(D89>F89,"Higher Low",IF(D89<F89,"Lower Low","Flat"))) | I89: =IF(AND(G89="Higher High",H89="Higher Low"),"Bullish",IF(AND(G89="Lower High",H89="Lower Low"),"Bearish","Mixed")) -> Mixed
E90: =IF(AND(B90=B89,A90>A89),C89,"") | F90: =IF(AND(B90=B89,A90>A89),D89,"") | G90: =IF(E90="","",IF(C90>E90,"Higher High",IF(C90<E90,"Lower High","Flat"))) | H90: =IF(F90="","",IF(D90>F90,"Higher Low",IF(D90<F90,"Lower Low","Flat"))) | I90: =IF(AND(G90="Higher High",H90="Higher Low"),"Bullish",IF(AND(G90="Lower High",H90="Lower Low"),"Bearish","Mixed")) -> Mixed
E91: =IF(AND(B990=B90,A990>A90),C90,"") | F91: =IF(AND(B990=B90,A990>A90),D90,"") | G91: =IF(E91="","",IF(C91>E91,"Higher High",IF(C91<E91,"Lower High","Flat"))) | H91: =IF(F91="","",IF(D91>F91,"Higher Low",IF(D91<F91,"Lower Low","Flat"))) | I91: =IF(AND(G91="Higher High",H91="Higher Low"),"Bullish",IF(AND(G91="Lower High",H91="Lower Low"),"Bearish","Mixed")) -> Mixed
E92: =IF(AND(B92=B91,A92>A91),C91,"") | F92: =IF(AND(B92=B91,A92>A91),D91,"") | G92: =IF(E92="","",IF(C92>E92,"Higher High",IF(C92<E92,"Lower High","Flat"))) | H92: =IF(F92="","",IF(D92>F92,"Higher Low",IF(D92<F92,"Lower Low","Flat"))) | I92: =IF(AND(G92="Higher High",H92="Higher Low"),"Bullish",IF(AND(G92="Lower High",H92="Lower Low"),"Bearish","Mixed")) -> Mixed
E93: =IF(AND(B93=B92,A93>A92),C92,"") | F93: =IF(AND(B93=B92,A93>A92),D92,"") | G93: =IF(E93="","",IF(C93>E93,"Higher High",IF(C93<E93,"Lower High","Flat"))) | H93: =IF(F93="","",IF(D93>F93,"Higher Low",IF(D93<F93,"Lower Low","Flat"))) | I93: =IF(AND(G93="Higher High",H93="Higher Low"),"Bullish",IF(AND(G93="Lower High",H93="Lower Low"),"Bearish","Mixed")) -> Mixed
E94: =IF(AND(B94=B93,A94>A93),C93,"") | F94: =IF(AND(B94=B93,A94>A93),D93,"") | G94: =IF(E94="","",IF(C94>E94,"Higher High",IF(C94<E94,"Lower High","Flat"))) | H94: =IF(F94="","",IF(D94>F94,"Higher Low",IF(D94<F94,"Lower Low","Flat"))) | I94: =IF(AND(G94="Higher High",H94="Higher Low"),"Bullish",IF(AND(G94="Lower High",H94="Lower Low"),"Bearish","Mixed")) -> Mixed
E95: =IF(AND(B95=B94,A95>A94),C94,"") | F95: =IF(AND(B95=B94,A95>A94),D94,"") | G95: =IF(E95="","",IF(C95>E95,"Higher High",IF(C95<E95,"Lower High","Flat"))) | H95: =IF(F95="","",IF(D95>F95,"Higher Low",IF(D95<F95,"Lower Low","Flat"))) | I95: =IF(AND(G95="Higher High",H95="Higher Low"),"Bullish",IF(AND(G95="Lower High",H95="Lower Low"),"Bearish","Mixed")) -> Mixed
E96: =IF(AND(B96=B95,A96>A95),C95,"") | F96: =IF(AND(B96=B95,A96>A95),D95,"") | G96: =IF(E96="","",IF(C96>E96,"Higher High",IF(C96<E96,"Lower High","Flat"))) | H96: =IF(F96="","",IF(D96>F96,"Higher Low",IF(D96<F96,"Lower Low","Flat"))) | I96: =IF(AND(G96="Higher High",H96="Higher Low"),"Bullish",IF(AND(G96="Lower High",H96="Lower Low"),"Bearish","Mixed")) -> Mixed
E97: =IF(AND(B97=B96,A97>A96),C96,"") | F97: =IF(AND(B97=B96,A97>A96),D96,"") | G97: =IF(E97="","",IF(C97>E97,"Higher High",IF(C97<E97,"Lower High","Flat"))) | H97: =IF(F97="","",IF(D97>F97,"Higher Low",IF(D97<F97,"Lower Low","Flat"))) | I97: =IF(AND(G97="Higher High",H97="Higher Low"),"Bullish",IF(AND(G97="Lower High",H97="Lower Low"),"Bearish","Mixed")) -> Mixed
E98: =IF(AND(B98=B97,A98>A97),C97,"") | F98: =IF(AND(B98=B97,A98>A97),D97,"") | G98: =IF(E98="","",IF(C98>E98,"Higher High",IF(C98<E98,"Lower High","Flat"))) | H98: =IF(F98="","",IF(D98>F98,"Higher Low",IF(D98<F98,"Lower Low","Flat"))) | I98: =IF(AND(G98="Higher High",H98="Higher Low"),"Bullish",IF(AND(G98="Lower High",H98="Lower Low"),"Bearish","Mixed")) -> Mixed
E99: =IF(AND(B99=B98,A99>A98),C98,"") | F99: =IF(AND(B99=B98,A99>A98),D98,"") | G99: =IF(E99="","",IF(C99>E99,"Higher High",IF(C99<E99,"Lower High","Flat"))) | H99: =IF(F99="","",IF(D99>F99,"Higher Low",IF(D99<F99,"Lower Low","Flat"))) | I99: =IF(AND(G99="Higher High",H99="Higher Low"),"Bullish",IF(AND(G99="Lower High",H99="Lower Low"),"Bearish","Mixed")) -> Mixed
E100: =IF(AND(B9900=B99,A9900>A99),C99,"") | F100: =IF(AND(B9900=B99,A9900>A99),D99,"") | G100: =IF(E100="","",IF(C100>E100,"Higher High",IF(C100<E100,"Lower High","Flat"))) | H100: =IF(F100="","",IF(D100>F100,"Higher Low",IF(D100<F100,"Lower Low","Flat"))) | I100: =IF(AND(G100="Higher High",H100="Higher Low"),"Bullish",IF(AND(G100="Lower High",H100="Lower Low"),"Bearish","Mixed")) -> Mixed
...

Sheet Nov. 24.2025
A1: INDEX | B1: BUY TRADE | C1: SELL TRADE | D1: PREV. CLOSE
A2: UST30Y (BEARISH)
A3: 30-Year U.S. Treasury Yield | B3: 4.75 | C3: 4.65 | D3: 4.71
A4: UST10Y (BEARISH)
A5: 10-Year U.S. Treasury Yield | B5: 4.15 | C5: 4.02 | D5: 4.07
A6: UST2Y (BEARISH)
A7: 2-Year U.S. Treasury Yield | B7: 3.62 | C7: 3.49 | D7: 3.52
A8: HYG (NEUTRAL)
A9: High Yield | B9: 79.85 | C9: 80.61 | D9: 80.37
A10: LQD (BULLISH)
A11: Investment Grade Corporate Bond ETF | B11: 110.1 | C11: 111.6 | D11: 110.9
A12: SPX (BULLISH)
A13: S&P 500 | B13: 6476 | C13: 6713 | D13: 6602
A14: COMPQ (BEARISH)
A15: NASDAQ Composite | B15: 21830 | C15: 22906 | D15: 22273
A16: RUT (BEARISH)
A17: Russell 2000 | B17: 2278 | C17: 2412 | D17: 2369
A18: XLK (BEARISH)
A19: Technology Select Sector SPDR Fund | B19: 267 | C19: 286 | D19: 273
A20: XLV (BULLISH)
A21: Health Care Select Sector SPDR Fund | B21: 151 | C21: 156 | D21: 154.61
A22: SSEC (BEARISH)
A23: Shanghai Composite | B23: 3806 | C23: 3961 | D23: 3836
A24: NIKK (NEUTRAL)
A25: Nikkei 225 Index | B25: 48218 | C25: 51210 | D25: 48625
A26: DAX (BEARISH)
A27: German DAX Composite | B27: 22708 | C27: 23815 | D27: 23091
A28: VIX (BULLISH)
A29: Volatility Index | B29: 19.87 | C29: 27.97 | D29: 23.43
A30: USD (BULLISH)
A31: U.S. Dollar Index | B31: 99.46 | C31: 100.57 | D31: 100.07
A32: EUR/USD (BEARISH)
A33: Euro to U.S. Dollar | B33: 1.148 | C33: 1.16 | D33: 1.154
A34: USD/YEN (BULLISH)
A35: U.S. Dollar to Japanese Yen | B35: 154.18 | C35: 157.97 | D35: 156.82
A36: GBP/USD (BEARISH)
A37: British Pound to U.S. Dollar | B37: 1.303 | C37: 1.319 | D37: 1.311
A38: CAD/USD (BEARISH)
A39: Canadian Dollar to U.S. Dollar | B39: 0.706 | C39: 0.717 | D39: 0.708
A40: WTIC (BEARISH)
A41: Light Crude Oil Continuous Contract | B41: 57.01 | C41: 59.96 | D41: 57.98
A42: BRENT (BEARISH)
A43: Brent Crude Oil Continuous Contract | B43: 61 | C43: 64.15 | D43: 62.47
A44: NATGAS (BULLISH)
A45: Natural Gas Continuous Contract | B45: 4.28 | C45: 4.75 | D45: 4.57
A46: GOLD (BULLISH)
A47: Gold Spot Price | B47: 4001 | C47: 4208 | D47: 4071
A48: COPPER (BULLISH)
A49: Copper Continuous Contract | B49: 4.89 | C49: 5.14 | D49: 4.99
A50: SILVER (BULLISH)
A51: Silver Spot Price | B51: 49 | C51: 53.29 | D51: 49.97
A52: MSFT (BEARISH)
A53: Microsoft Corp. | B53: 466 | C53: 496 | D53: 472
A54: AAPL (BULLISH)
A55: Apple Inc. | B55: 265 | C55: 279 | D55: 271
A56: AMZN (BEARISH)
A57: Amazon Inc. | B57: 209 | C57: 231 | D57: 221
A58: META (BEARISH)
A59: Meta Platforms Inc. | B59: 579 | C59: 624 | D59: 594
A60: GOOGL (BULLISH)
A61: Alphabet Inc. | B61: 281 | C61: 304 | D61: 300
A62: NFLX (BEARISH)
A63: Netflix Inc. | B63: 100 | C63: 111 | D63: 104
A64: TSLA (BEARISH)
A65: Tesla Inc. | B65: 376 | C65: 423 | D65: 391
A66: NVDA (NEUTRAL)
A67: NVIDIA Corporation | B67: 174 | C67: 195 | D67: 179
A68: ORCL (BEARISH)
A69: Oracle Corporation | B69: 194 | C69: 224 | D69: 198.76
A70: BITCOIN (BEARISH)
A71: Bitcoin Spot Price | B71: 80726 | C71: 89954 | D71: 86157

Sheet Nov. 25.2025
A1: INDEX | B1: BUY TRADE | C1: SELL TRADE | D1: PREV. CLOSE
A2: UST30Y (BEARISH) | B2: 4.74 | C2: 4.64 | D2: 4.67
A3: 30-Year U.S. Treasury Yield
A4: UST10Y (BEARISH) | B4: 4.14 | C4: 4.01 | D4: 4.03
A5: 10-Year U.S. Treasury Yield
A6: UST2Y (BEARISH) | B6: 3.61 | C6: 3.47 | D6: 3.5
A7: 2-Year U.S. Treasury Yield
A8: HYG (BULLISH) | B8: 79.93 | C8: 80.69 | D8: 80.59
A9: High Yield
A10: LQD (BULLISH) | B10: 110.2 | C10: 111.7 | D10: 111.4
A11: Investment Grade Corporate Bond ETF
A12: SPX (BULLISH) | B12: 6496 | C12: 6762 | D12: 6705
A13: S&P 500
A14: COMPQ (NEUTRAL) | B14: 21912 | C14: 23204 | D14: 22872
A15: NASDAQ Composite
A16: RUT (BEARISH) | B16: 2296 | C16: 2446 | D16: 2414
A17: Russell 2000
A18: XLK (BEARISH) | B18: 268 | C18: 286 | D18: 280
A19: Technology Select Sector SPDR Fund
A20: XLV (BULLISH) | B20: 151 | C20: 157 | D20: 155.26
A21: Health Care Select Sector SPDR Fund
A22: SSEC (BEARISH) | B22: 3804 | C22: 3943 | D22: 3870
A23: Shanghai Composite
A24: NIKK (NEUTRAL) | B24: 47813 | C24: 49993 | D24: 48659
A25: Nikkei 225 Index
A26: DAX (BEARISH) | B26: 22567 | C26: 23765 | D26: 23239
A27: German DAX Composite
A28: VIX (BULLISH) | B28: 18.44 | C28: 27.44 | D28: 20.52
A29: Volatility Index
A30: USD (BULLISH) | B30: 99.53 | C30: 100.66 | D30: 100.12
A31: U.S. Dollar Index
A32: EUR/USD (BEARISH) | B32: 1.147 | C32: 1.16 | D32: 1.153
A33: Euro to U.S. Dollar
A34: USD/YEN (BULLISH) | B34: 154.34 | C34: 157.99 | D34: 156.38
A35: U.S. Dollar to Japanese Yen
A36: GBP/USD (BEARISH) | B36: 1.302 | C36: 1.319 | D36: 1.312
A37: British Pound to U.S. Dollar
A38: CAD/USD (BEARISH) | B38: 0.705 | C38: 0.717 | D38: 0.708
A39: Canadian Dollar to U.S. Dollar
A40: WTIC (BEARISH) | B40: 57.12 | C40: 60.73 | D40: 58.89
A41: Light Crude Oil Continuous Contract
A42: BRENT (BEARISH) | B42: 61.04 | C42: 64.69 | D42: 63.39
A43: Brent Crude Oil Continuous Contract
A44: NATGAS (BULLISH) | B44: 4.29 | C44: 4.72 | D44: 4.5
A45: Natural Gas Continuous Contract
A46: GOLD (BULLISH) | B46: 4004 | C46: 4211 | D46: 4133
A47: Gold Spot Price
A48: COPPER (BULLISH) | B48: 4.92 | C48: 5.16 | D48: 4.99
A49: Copper Continuous Contract
A50: SILVER (BULLISH) | B50: 49.07 | C50: 53.24 | D50: 51.34
A51: Silver Spot Price
A52: MSFT (BEARISH) | B52: 461 | C52: 491 | D52: 474
A53: Microsoft Corp.
A54: AAPL (BULLISH) | B54: 267 | C54: 279 | D54: 276
A55: Apple Inc.
A56: AMZN (BEARISH) | B56: 210 | C56: 232 | D56: 226
A57: Amazon Inc.
A58: META (BEARISH) | B58: 582 | C58: 622 | D58: 613
A59: Meta Platforms Inc.
A60: GOOGL (BULLISH) | B60: 290 | C60: 324 | D60: 319
A61: Alphabet Inc.
A62: NFLX (BEARISH) | B62: 101 | C62: 111 | D62: 107
A63: Netflix Inc.
A64: TSLA (BEARISH) | B64: 381 | C64: 430 | D64: 418
A65: Tesla Inc.
A66: NVDA (NEUTRAL) | B66: 174 | C66: 192 | D66: 183
A67: NVIDIA Corporation
A68: ORCL (BEARISH) | B68: 192 | C68: 223 | D68: 200.28
A69: Oracle Corporation
A70: BITCOIN (BEARISH) | B70: 81544 | C70: 93176 | D70: 88336
A71: Bitcoin Spot Price

Sheet Nov. 26.2025
A1: INDEX | B1: BUY TRADE | C1: SELL TRADE | D1: PREV. CLOSE
A2: UST30Y (BEARISH) | B2: 4.73 | C2: 4.62 | D2: 4.65
A3: 30-Year U.S. Treasury Yield
A4: UST10Y (BEARISH) | B4: 4.11 | C4: 3.97 | D4: 4
A5: 10-Year U.S. Treasury Yield
A6: UST2Y (BEARISH) | B6: 3.57 | C6: 3.43 | D6: 3.46
A7: 2-Year U.S. Treasury Yield
A8: HYG (BULLISH) | B8: 80.1 | C8: 80.98 | D8: 80.87
A9: High Yield
A10: LQD (BULLISH) | B10: 110.3 | C10: 111.9 | D10: 111.7
A11: Investment Grade Corporate Bond ETF
A12: SPX (BULLISH) | B12: 6508 | C12: 6804 | D12: 6765
A13: S&P 500
A14: COMPQ (BULLISH) | B14: 22009 | C14: 23262 | D14: 23025
A15: NASDAQ Composite
A16: RUT (BULLISH) | B16: 2297 | C16: 2487 | D16: 2465
A17: Russell 2000
A18: XLK (BEARISH) | B18: 269 | C18: 287 | D18: 280
A19: Technology Select Sector SPDR Fund
A20: XLV (BULLISH) | B20: 153 | C20: 161 | D20: 158.77
A21: Health Care Select Sector SPDR Fund
A22: SSEC (BEARISH) | B22: 3791 | C22: 3933 | D22: 3864
A23: Shanghai Composite
A24: NIKK (BULLISH) | B24: 47803 | C24: 51301 | D24: 49559
A25: Nikkei 225 Index
A26: DAX (BEARISH) | B26: 22601 | C26: 23845 | D26: 23464
A27: German DAX Composite
A28: VIX (BULLISH) | B28: 17.28 | C28: 27.18 | D28: 18.56
A29: Volatility Index
A30: USD (BULLISH) | B30: 99.32 | C30: 100.58 | D30: 99.8
A31: U.S. Dollar Index
A32: EUR/USD (BEARISH) | B32: 1.148 | C32: 1.161 | D32: 1.158
A33: Euro to U.S. Dollar
A34: USD/YEN (BULLISH) | B34: 154.65 | C34: 157.98 | D34: 156.51
A35: U.S. Dollar to Japanese Yen
A36: GBP/USD (BEARISH) | B36: 1.303 | C36: 1.322 | D36: 1.317
A37: British Pound to U.S. Dollar
A38: CAD/USD (BEARISH) | B38: 0.705 | C38: 0.717 | D38: 0.709
A39: Canadian Dollar to U.S. Dollar
A40: WTIC (BEARISH) | B40: 57.03 | C40: 59.73 | D40: 58.11
A41: Light Crude Oil Continuous Contract
A42: BRENT (BEARISH) | B42: 61.01 | C42: 64 | D42: 62.64
A43: Brent Crude Oil Continuous Contract
A44: NATGAS (BULLISH) | B44: 4.3 | C44: 4.71 | D44: 4.47
A45: Natural Gas Continuous Contract
A46: GOLD (BULLISH) | B46: 4025 | C46: 4193 | D46: 4153
A47: Gold Spot Price
A48: COPPER (BULLISH) | B48: 4.93 | C48: 5.17 | D48: 5.02
A49: Copper Continuous Contract
A50: SILVER (BULLISH) | B50: 49.8 | C50: 53.2 | D50: 51.48
A51: Silver Spot Price
A52: MSFT (BEARISH) | B52: 460 | C52: 490 | D52: 477
A53: Microsoft Corp.
A54: AAPL (BULLISH) | B54: 268 | C54: 281 | D54: 277
A55: Apple Inc.
A56: AMZN (BEARISH) | B56: 212 | C56: 235 | D56: 230
A57: Amazon Inc.
A58: META (BEARISH) | B58: 575 | C58: 646 | D58: 636
A59: Meta Platforms Inc.
A60: GOOGL (BULLISH) | B60: 296 | C60: 328 | D60: 323
A61: Alphabet Inc.
A62: NFLX (BEARISH) | B62: 100 | C62: 109 | D62: 104
A63: Netflix Inc.
A64: TSLA (BEARISH) | B64: 384 | C64: 428 | D64: 419
A65: Tesla Inc.
A66: NVDA (BEARISH) | B66: 173 | C66: 188 | D66: 178
A67: NVIDIA Corporation
A68: ORCL (BEARISH) | B68: 188 | C68: 219 | D68: 197.03
A69: Oracle Corporation
A70: BITCOIN (BEARISH) | B70: 81994 | C70: 92108 | D70: 86665
A71: Bitcoin Spot Price

Sheet Nov 28.2025
A1: INDEX | B1: BUY TRADE | C1: SELL TRADE | D1: PREV. CLOSE
A2: UST30Y (BEARISH) | B2: 4.72 | C2: 4.6 | D2: 4.64
A3: 30-Year U.S. Treasury Yield
A4: UST10Y (BEARISH) | B4: 4.09 | C4: 3.95 | D4: 4
A5: 10-Year U.S. Treasury Yield
A6: UST2Y (BEARISH) | B6: 3.55 | C6: 3.43 | D6: 3.48
A7: 2-Year U.S. Treasury Yield
A8: HYG (BULLISH) | B8: 80.31 | C8: 81.1 | D8: 80.95
A9: High Yield
A10: LQD (BULLISH) | B10: 110.6 | C10: 112.4 | D10: 112.1
A11: Investment Grade Corporate Bond ETF
A12: SPX (BULLISH) | B12: 6503 | C12: 6851 | D12: 6812
A13: S&P 500
A14: COMPQ (BULLISH) | B14: 21967 | C14: 23498 | D14: 23214
A15: NASDAQ Composite
A16: RUT (BULLISH) | B16: 2307 | C16: 2506 | D16: 2486
A17: Russell 2000
A18: XLK (NEUTRAL) | B18: 269 | C18: 288 | D18: 284
A19: Technology Select Sector SPDR Fund
A20: XLV (BULLISH) | B20: 154 | C20: 161 | D20: 158.42
A21: Health Care Select Sector SPDR Fund
A22: SSEC (BEARISH) | B22: 3799 | C22: 3973 | D22: 3888
A23: Shanghai Composite
A24: NIKK (BULLISH) | B24: 47882 | C24: 51006 | D24: 50253
A25: Nikkei 225 Index
A26: DAX (BEARISH) | B26: 22807 | C26: 23890 | D26: 23767
A27: German DAX Composite
A28: VIX (BULLISH) | B28: 16.04 | C28: 27.76 | D28: 17.19
A29: Volatility Index
A30: USD (BULLISH) | B30: 99.4 | C30: 100.51 | D30: 99.69
A31: U.S. Dollar Index
A32: EUR/USD (BEARISH) | B32: 1.148 | C32: 1.161 | D32: 1.157
A33: Euro to U.S. Dollar
A34: USD/YEN (BULLISH) | B34: 155.09 | C34: 157.91 | D34: 156.16
A35: U.S. Dollar to Japanese Yen
A36: GBP/USD (BEARISH) | B36: 1.302 | C36: 1.324 | D36: 1.321
A37: British Pound to U.S. Dollar
A38: CAD/USD (BEARISH) | B38: 0.706 | C38: 0.716 | D38: 0.712
A39: Canadian Dollar to U.S. Dollar
A40: WTIC (BEARISH) | B40: 57.14 | C40: 59.95 | D40: 58.65
A41: Light Crude Oil Continuous Contract
A42: BRENT (BEARISH) | B42: 61.92 | C42: 64.76 | D42: 63.13
A43: Brent Crude Oil Continuous Contract
A44: NATGAS (BULLISH) | B44: 4.35 | C44: 4.7 | D44: 4.56
A45: Natural Gas Continuous Contract
A46: GOLD (BULLISH) | B46: 4062 | C46: 4199 | D46: 4174
A47: Gold Spot Price
A48: COPPER (BULLISH) | B48: 4.96 | C48: 5.2 | D48: 5.12
A49: Copper Continuous Contract
A50: SILVER (BULLISH) | B50: 50.27 | C50: 54.2 | D50: 53.35
A51: Silver Spot Price
A52: MSFT (BEARISH) | B52: 462 | C52: 498 | D52: 486
A53: Microsoft Corp.
A54: AAPL (BULLISH) | B54: 269 | C54: 281 | D54: 278
A55: Apple Inc.
A56: AMZN (NEUTRAL) | B56: 214 | C56: 236 | D56: 229
A57: Amazon Inc.
A58: META (BEARISH) | B58: 572 | C58: 645 | D58: 634
A59: Meta Platforms Inc.
A60: GOOGL (BULLISH) | B60: 299 | C60: 333 | D60: 320
A61: Alphabet Inc.
A62: NFLX (BEARISH) | B62: 100 | C62: 110 | D62: 106
A63: Netflix Inc.
A64: TSLA (NEUTRAL) | B64: 391 | C64: 432 | D64: 427
A65: Tesla Inc.
A66: NVDA (BEARISH) | B66: 172 | C66: 187 | D66: 180
A67: NVIDIA Corporation
A68: ORCL (BEARISH) | B68: 188 | C68: 222 | D68: 204.96
A69: Oracle Corporation
A70: BITCOIN (BEARISH) | B70: 83102 | C70: 92993 | D70: 91642
A71: Bitcoin Spot Price

Sheet Dec 1.2025
A1: INDEX | B1: BUY TRADE | C1: SELL TRADE | D1: PREV. CLOSE
A2: UST30Y (BEARISH) | B2: 4.74 | C2: 4.6 | D2: 4.67
A3: 30-Year U.S. Treasury Yield
A4: UST10Y (BEARISH) | B4: 4.13 | C4: 3.95 | D4: 4.02
A5: 10-Year U.S. Treasury Yield
A6: UST2Y (BEARISH) | B6: 3.6 | C6: 3.43 | D6: 3.5
A7: 2-Year U.S. Treasury Yield
A8: HYG (BULLISH) | B8: 80.45 | C8: 81.22 | D8: 80.99
A9: High Yield
A10: LQD (BULLISH) | B10: 110.3 | C10: 112.5 | D10: 111.9
A11: Investment Grade Corporate Bond ETF
A12: SPX (BULLISH) | B12: 6538 | C12: 6876 | D12: 6849
A13: S&P 500
A14: COMPQ (BULLISH) | B14: 21924 | C14: 23540 | D14: 23365
A15: NASDAQ Composite
A16: RUT (BULLISH) | B16: 2310 | C16: 2518 | D16: 2500
A17: Russell 2000
A18: XLK (BULLISH) | B18: 271 | C18: 290 | D18: 286
A19: Technology Select Sector SPDR Fund
A20: XLV (BULLISH) | B20: 153 | C20: 161 | D20: 157.65
A21: Health Care Select Sector SPDR Fund
A22: SSEC (NEUTRAL) | B22: 3821 | C22: 3965 | D22: 3914
A23: Shanghai Composite
A24: NIKK (NEUTRAL) | B24: 47950 | C24: 50849 | D24: 49303
A25: Nikkei 225 Index
A26: DAX (BEARISH) | B26: 22859 | C26: 23849 | D26: 23836
A27: German DAX Composite
A28: VIX (BEARISH) | B28: 15.29 | C28: 26.42 | D28: 16.35
A29: Volatility Index
A30: USD (BULLISH) | B30: 99.02 | C30: 100.5 | D30: 99.13
A31: U.S. Dollar Index
A32: EUR/USD (BEARISH) | B32: 1.149 | C32: 1.164 | D32: 1.164
A33: Euro to U.S. Dollar
A34: USD/YEN (BULLISH) | B34: 154.67 | C34: 157.63 | D34: 154.96
A35: U.S. Dollar to Japanese Yen
A36: GBP/USD (BEARISH) | B36: 1.304 | C36: 1.329 | D36: 1.325
A37: British Pound to U.S. Dollar
A38: CAD/USD (BEARISH) | B38: 0.707 | C38: 0.716 | D38: 0.716
A39: Canadian Dollar to U.S. Dollar
A40: WTIC (BEARISH) | B40: 57.96 | C40: 60.74 | D40: 59.44
A41: Light Crude Oil Continuous Contract
A42: BRENT (BEARISH) | B42: 62.48 | C42: 64.93 | D42: 63.19
A43: Brent Crude Oil Continuous Contract
A44: NATGAS (BULLISH) | B44: 4.37 | C44: 4.86 | D44: 4.77
A45: Natural Gas Continuous Contract
A46: GOLD (BULLISH) | B46: 4076 | C46: 4294 | D46: 4254
A47: Gold Spot Price
A48: COPPER (BULLISH) | B48: 5.01 | C48: 5.32 | D48: 5.19
A49: Copper Continuous Contract
A50: SILVER (BULLISH) | B50: 51.52 | C50: 58.08 | D50: 56.37
A51: Silver Spot Price
A52: MSFT (BEARISH) | B52: 466 | C52: 499 | D52: 492
A53: Microsoft Corp.
A54: AAPL (BULLISH) | B54: 270 | C54: 283 | D54: 279
A55: Apple Inc.
A56: AMZN (NEUTRAL) | B56: 216 | C56: 237 | D56: 233
A57: Amazon Inc.
A58: META (BEARISH) | B58: 566 | C58: 655 | D58: 648
A59: Meta Platforms Inc.
A60: GOOGL (BULLISH) | B60: 301 | C60: 337 | D60: 320
A61: Alphabet Inc.
A62: NFLX (BEARISH) | B62: 101 | C62: 111 | D62: 108
A63: Netflix Inc.
A64: TSLA (BULLISH) | B64: 392 | C64: 440 | D64: 430
A65: Tesla Inc.
A66: NVDA (BEARISH) | B66: 172 | C66: 185 | D66: 177
A67: NVIDIA Corporation
A68: ORCL (BEARISH) | B68: 186 | C68: 220 | D68: 201.95
A69: Oracle Corporation
A70: BITCOIN (BEARISH) | B70: 84495 | C70: 91860 | D70: 85723
A71: Bitcoin Spot Price

Sheet Dec 2. 2025
A1: INDEX | B1: BUY TRADE | C1: SELL TRADE | D1: PREV. CLOSE
A2: UST30Y (BEARISH) | B2: 4.79 | C2: 4.61 | D2: 4.74
A3: 30-Year U.S. Treasury Yield
A4: UST10Y (BEARISH) | B4: 4.13 | C4: 3.95 | D4: 4.09
A5: 10-Year U.S. Treasury Yield
A6: UST2Y (BEARISH) | B6: 3.6 | C6: 3.43 | D6: 3.55
A7: 2-Year U.S. Treasury Yield
A8: HYG (BULLISH) | B8: 80.45 | C8: 81.22 | D8: 80.47
A9: High Yield
A10: LQD (BULLISH) | B10: 110.3 | C10: 112 | D10: 110.9
A11: Investment Grade Corporate Bond ETF
A12: SPX (BULLISH) | B12: 6609 | C12: 6850 | D12: 6812
A13: S&P 500
A14: COMPQ (BULLISH) | B14: 22317 | C14: 23566 | D14: 23275
A15: NASDAQ Composite
A16: RUT (BULLISH) | B16: 2313 | C16: 2509 | D16: 2469
A17: Russell 2000
A18: XLK (BULLISH) | B18: 271 | C18: 291 | D18: 286
A19: Technology Select Sector SPDR Fund
A20: XLV (BULLISH) | B20: 152 | C20: 161 | D20: 155.29
A21: Health Care Select Sector SPDR Fund
A22: SSEC (BEARISH) | B22: 3801 | C22: 3924 | D22: 3897
A23: Shanghai Composite
A24: NIKK (BULLISH) | B24: 47892 | C24: 50583 | D24: 49303
A25: Nikkei 225 Index
A26: DAX (BEARISH) | B26: 22912 | C26: 23844 | D26: 23589
A27: German DAX Composite
A28: BSE (BULLISH) | B28: 84506 | C28: 86333 | D28: 85138
A29: BSE SENSEX
A30: VIX (BEARISH) | B30: 15.79 | C30: 26.43 | D30: 17.24
A31: Volatility Index
A32: USD (BULLISH) | B32: 99.16 | C32: 100.39 | D32: 99.45
A33: U.S. Dollar Index
A34: EUR/USD (NEUTRAL) | B34: 1.151 | C34: 1.163 | D34: 1.161
A35: Euro to U.S. Dollar
A36: USD/YEN (BULLISH) | B36: 155.03 | C36: 157.64 | D36: 155.98
A37: U.S. Dollar to Japanese Yen
A38: GBP/USD (BEARISH) | B38: 1.304 | C38: 1.33 | D38: 1.321
A39: British Pound to U.S. Dollar
A40: CAD/USD (BEARISH) | B40: 0.706 | C40: 0.716 | D40: 0.713
A41: Canadian Dollar to U.S. Dollar
A42: WTIC (BEARISH) | B42: 57.96 | C42: 60.57 | D42: 59.51
A43: Light Crude Oil Continuous Contract
A44: BRENT (BEARISH) | B44: 61.89 | C44: 64.88 | D44: 63.31
A45: Brent Crude Oil Continuous Contract
A46: NATGAS (BULLISH) | B46: 4.37 | C46: 4.94 | D46: 4.9
A47: Natural Gas Continuous Contract
A48: GOLD (BULLISH) | B48: 4086 | C48: 4263 | D48: 4203
A49: Gold Spot Price
A50: COPPER (BULLISH) | B50: 5.02 | C50: 5.29 | D50: 5.17
A51: Copper Continuous Contract
A52: SILVER (BULLISH) | B52: 52.18 | C52: 58.01 | D52: 57.97
A53: Silver Spot Price
A54: MSFT (BEARISH) | B54: 466 | C54: 497 | D54: 487
A55: Microsoft Corp.
A56: AAPL (BULLISH) | B56: 275 | C56: 286 | D56: 283
A57: Apple Inc.
A58: AMZN (BULLISH) | B58: 217 | C58: 238 | D58: 234
A59: Amazon Inc.
A60: META (BEARISH) | B60: 568 | C60: 657 | D60: 641
A61: Meta Platforms Inc.
A62: GOOGL (BULLISH) | B62: 304 | C62: 336 | D62: 315
A63: Alphabet Inc.
A64: NFLX (BEARISH) | B64: 100 | C64: 112 | D64: 109
A65: Netflix Inc.
A66: TSLA (BULLISH) | B66: 391 | C66: 444 | D66: 430
A67: Tesla Inc.
A68: NVDA (BEARISH) | B68: 173 | C68: 186 | D68: 180
A69: NVIDIA Corporation
A70: ORCL (BEARISH) | B70: 185 | C70: 210 | D70: 200.94
A71: Oracle Corporation
A72: BITCOIN (BEARISH) | B72: 85011 | C72: 92988 | D72: 87455
A73: Bitcoin Spot Price

Sheet Dec 3. 2025
A1: INDEX | B1: BUY TRADE | C1: SELL TRADE | D1: PREV. CLOSE
A2: UST30Y (BEARISH) | B2: 4.78 | C2: 4.63 | D2: 4.75
A3: 30-Year U.S. Treasury Yield
A4: UST10Y (BEARISH) | B4: 4.12 | C4: 3.96 | D4: 4.09
A5: 10-Year U.S. Treasury Yield
A6: UST2Y (BEARISH) | B6: 3.58 | C6: 3.43 | D6: 3.52
A7: 2-Year U.S. Treasury Yield
A8: HYG (BULLISH) | B8: 80.12 | C8: 81.06 | D8: 80.62
A9: High Yield
A10: LQD (BULLISH) | B10: 110.2 | C10: 112.1 | D10: 110.9
A11: Investment Grade Corporate Bond ETF
A12: SPX (BULLISH) | B12: 6614 | C12: 6909 | D12: 6829
A13: S&P 500
A14: COMPQ (BULLISH) | B14: 23396 | C14: 23841 | D14: 23413
A15: NASDAQ Composite
A16: RUT (BULLISH) | B16: 2382 | C16: 2523 | D16: 2464
A17: Russell 2000
A18: XLK (BULLISH) | B18: 274 | C18: 295 | D18: 289
A19: Technology Select Sector SPDR Fund
A20: XLV (BULLISH) | B20: 151 | C20: 161 | D20: 154.36
A21: Health Care Select Sector SPDR Fund
A22: SSEC (BEARISH) | B22: 3807 | C22: 3917 | D22: 3878
A23: Shanghai Composite
A24: NIKK (BULLISH) | B24: 48501 | C24: 50601 | D24: 49864
A25: Nikkei 225 Index
A26: DAX (BEARISH) | B26: 23001 | C26: 24016 | D26: 23710
A27: German DAX Composite
A28: BSE (BULLISH) | B28: 84516 | C28: 86339 | D28: 85106
A29: BSE SENSEX
A30: VIX (BEARISH) | B30: 14.61 | C30: 25.31 | D30: 16.59
A31: Volatility Index
A32: USD (NEUTRAL) | B32: 98.79 | C32: 100.35 | D32: 98.96
A33: U.S. Dollar Index
A34: EUR/USD (NEUTRAL) | B34: 1.151 | C34: 1.167 | D34: 1.167
A35: Euro to U.S. Dollar
A36: USD/YEN (BULLISH) | B36: 154.81 | C36: 157 | D36: 155.41
A37: U.S. Dollar to Japanese Yen
A38: GBP/USD (BEARISH) | B38: 1.306 | C38: 1.33 | D38: 1.33
A39: British Pound to U.S. Dollar
A40: CAD/USD (BEARISH) | B40: 0.709 | C40: 0.719 | D40: 0.717
A41: Canadian Dollar to U.S. Dollar
A42: WTIC (BEARISH) | B42: 57.96 | C42: 60.5 | D42: 58.64
A43: Light Crude Oil Continuous Contract
A44: BRENT (BEARISH) | B44: 61.91 | C44: 64.57 | D44: 62.45
A45: Brent Crude Oil Continuous Contract
A46: NATGAS (BULLISH) | B46: 4.38 | C46: 4.99 | D46: 4.82
A47: Natural Gas Continuous Contract
A48: GOLD (BULLISH) | B48: 4095 | C48: 4276 | D48: 4211
A49: Gold Spot Price
A50: COPPER (BULLISH) | B50: 5.04 | C50: 5.4 | D50: 5.17
A51: Copper Continuous Contract
A52: SILVER (BULLISH) | B52: 52.88 | C52: 59.94 | D52: 58.41
A53: Silver Spot Price
A54: MSFT (BEARISH) | B54: 467 | C54: 498 | D54: 490
A55: Microsoft Corp.
A56: AAPL (BULLISH) | B56: 276 | C56: 290 | D56: 286
A57: Apple Inc.
A58: AMZN (BULLISH) | B58: 218 | C58: 240 | D58: 234
A59: Amazon Inc.
A60: META (BEARISH) | B60: 588 | C60: 670 | D60: 647
A61: Meta Platforms Inc.
A62: GOOGL (BULLISH) | B62: 306 | C62: 336 | D62: 316
A63: Alphabet Inc.
A64: NFLX (BEARISH) | B64: 101 | C64: 112 | D64: 109
A65: Netflix Inc.
A66: TSLA (BULLISH) | B66: 392 | C66: 446 | D66: 429
A67: Tesla Inc.
A68: NVDA (BULLISH) | B68: 174 | C68: 187 | D68: 181
A69: NVIDIA Corporation
A70: ORCL (BEARISH) | B70: 186 | C70: 209 | D70: 201.1
A71: Oracle Corporation
A72: BITCOIN (NEUTRAL) | B72: 86006 | C72: 95151 | D72: 92820
A73: Bitcoin Spot Price

Sheet Dec 4.2025
A1: INDEX | B1: BUY TRADE | C1: SELL TRADE | D1: PREV. CLOSE
A2: UST30Y (BEARISH) | B2: 4.77 | C2: 4.64 | D2: 4.73
A3: 30-Year U.S. Treasury Yield
A4: UST10Y (BEARISH) | B4: 4.12 | C4: 3.96 | D4: 4.07
A5: 10-Year U.S. Treasury Yield
A6: UST2Y (BEARISH) | B6: 3.57 | C6: 3.43 | D6: 3.5
A7: 2-Year U.S. Treasury Yield
A8: HYG (BULLISH) | B8: 80.16 | C8: 81.11 | D8: 80.69
A9: High Yield
A10: LQD (BULLISH) | B10: 110.2 | C10: 112 | D10: 111.2
A11: Investment Grade Corporate Bond ETF
A12: SPX (BULLISH) | B12: 6629 | C12: 6945 | D12: 6849
A13: S&P 500
A14: COMPQ (BULLISH) | B14: 23411 | C14: 23986 | D14: 23454
A15: NASDAQ Composite
A16: RUT (BULLISH) | B16: 2417 | C16: 2559 | D16: 2512
A17: Russell 2000
A18: XLK (BULLISH) | B18: 278 | C18: 296 | D18: 290
A19: Technology Select Sector SPDR Fund
A20: XLV (BULLISH) | B20: 151 | C20: 160 | D20: 155.08
A21: Health Care Select Sector SPDR Fund
A22: SSEC (BEARISH) | B22: 3814 | C22: 3915 | D22: 3875
A23: Shanghai Composite
A24: NIKK (BULLISH) | B24: 48409 | C24: 51300 | D24: 51028
A25: Nikkei 225 Index
A26: DAX (BEARISH) | B26: 23018 | C26: 24069 | D26: 23693
A27: German DAX Composite
A28: VIX (BEARISH) | B28: 14.41 | C28: 24.98 | D28: 16.08
A29: Volatility Index
A30: USD (NEUTRAL) | B30: 98.57 | C30: 100.22 | D30: 98.83
A31: U.S. Dollar Index
A32: EUR/USD (BULLISH) | B32: 1.153 | C32: 1.171 | D32: 1.167
A33: Euro to U.S. Dollar
A34: USD/YEN (BULLISH) | B34: 154.45 | C34: 157.01 | D34: 154.66
A35: U.S. Dollar to Japanese Yen
A36: GBP/USD (NEUTRAL) | B36: 1.31 | C36: 1.339 | D36: 1.335
A37: British Pound to U.S. Dollar
A38: CAD/USD (NEUTRAL) | B38: 0.709 | C38: 0.72 | D38: 0.715
A39: Canadian Dollar to U.S. Dollar
A40: WTIC (BEARISH) | B40: 57.92 | C40: 59.85 | D40: 59.11
A41: Light Crude Oil Continuous Contract
A42: BRENT (BEARISH) | B42: 61.99 | C42: 64.66 | D42: 62.8
A43: Brent Crude Oil Continuous Contract
A44: NATGAS (BULLISH) | B44: 4.58 | C44: 5.16 | D44: 5
A45: Natural Gas Continuous Contract
A46: GOLD (BULLISH) | B46: 4103 | C46: 4296 | D46: 4191
A47: Gold Spot Price
A48: COPPER (BULLISH) | B48: 5.1 | C48: 5.43 | D48: 5.31
A49: Copper Continuous Contract
A50: SILVER (BULLISH) | B50: 53.24 | C50: 61.06 | D50: 58.46
A51: Silver Spot Price
A52: MSFT (BEARISH) | B52: 465 | C52: 492 | D52: 478
A53: Microsoft Corp.
A54: AAPL (BULLISH) | B54: 277 | C54: 291 | D54: 284
A55: Apple Inc.
A56: AMZN (BULLISH) | B56: 218 | C56: 241 | D56: 232
A57: Amazon Inc.
A58: META (BEARISH) | B58: 583 | C58: 657 | D58: 640
A59: Meta Platforms Inc.
A60: GOOGL (BULLISH) | B60: 311 | C60: 337 | D60: 320
A61: Alphabet Inc.
A62: NFLX (BEARISH) | B62: 99 | C62: 109 | D62: 104
A63: Netflix Inc.
A64: TSLA (BULLISH) | B64: 406 | C64: 461 | D64: 447
A65: Tesla Inc.
A66: NVDA (NEUTRAL) | B66: 175 | C66: 185 | D66: 180
A67: NVIDIA Corporation
A68: ORCL (BEARISH) | B68: 190 | C68: 211 | D68: 207.73
A69: Oracle Corporation
A70: BITCOIN (NEUTRAL) | B70: 87029 | C70: 94834 | D70: 92903
A71: Bitcoin Spot Price

Sheet Dec 5.2025
A1: INDEX | B1: BUY TRADE | C1: SELL TRADE | D1: PREV. CLOSE
A2: UST30Y (BEARISH) | B2: 4.77 | C2: 4.65 | D2: 4.76
A3: 30-Year U.S. Treasury Yield
A4: UST10Y (BEARISH) | B4: 4.13 | C4: 3.96 | D4: 4.1
A5: 10-Year U.S. Treasury Yield
A6: UST2Y (BEARISH) | B6: 3.56 | C6: 3.44 | D6: 3.53
A7: 2-Year U.S. Treasury Yield
A8: HYG (BULLISH) | B8: 80.22 | C8: 81.01 | D8: 80.75
A9: High Yield
A10: LQD (BULLISH) | B10: 110.3 | C10: 111.9 | D10: 111
A11: Investment Grade Corporate Bond ETF
A12: SPX (BULLISH) | B12: 6720 | C12: 6956 | D12: 6857
A13: S&P 500
A14: COMPQ (BULLISH) | B14: 22488 | C14: 23960 | D14: 23505
A15: NASDAQ Composite
A16: RUT (BULLISH) | B16: 2444 | C16: 2565 | D16: 2531
A17: Russell 2000
A18: XLK (BULLISH) | B18: 139 | C18: 149 | D18: 146
A19: Technology Select Sector SPDR Fund
A20: XLV (BULLISH) | B20: 151 | C20: 160 | D20: 153.9
A21: Health Care Select Sector SPDR Fund
A22: SSEC (NEUTRAL) | B22: 3827 | C22: 3920 | D22: 3902
A23: Shanghai Composite
A24: NIKK (BULLISH) | B24: 48512 | C24: 51209 | D24: 50491
A25: Nikkei 225 Index
A26: DAX (NEUTRAL) | B26: 23209 | C26: 24054 | D26: 23882
A27: German DAX Composite
A28: VIX (BEARISH) | B28: 14.22 | C28: 21.72 | D28: 15.78
A29: Volatility Index
A30: USD (BEARISH) | B30: 98.68 | C30: 99.78 | D30: 99.01
A31: U.S. Dollar Index
A32: EUR/USD (BULLISH) | B32: 1.154 | C32: 1.17 | D32: 1.165
A33: Euro to U.S. Dollar
A34: USD/YEN (BULLISH) | B34: 154.56 | C34: 156.84 | D34: 155.2
A35: U.S. Dollar to Japanese Yen
A36: GBP/USD (NEUTRAL) | B36: 1.312 | C36: 1.339 | D36: 1.334
A37: British Pound to U.S. Dollar
A38: CAD/USD (NEUTRAL) | B38: 0.71 | C38: 0.72 | D38: 0.717
A39: Canadian Dollar to U.S. Dollar
A40: WTIC (BEARISH) | B40: 57.86 | C40: 59.99 | D40: 59.7
A41: Light Crude Oil Continuous Contract
A42: BRENT (BEARISH) | B42: 62.03 | C42: 64.05 | D42: 63.32
A43: Brent Crude Oil Continuous Contract
A44: NATGAS (BULLISH) | B44: 4.65 | C44: 5.22 | D44: 5.09
A45: Natural Gas Continuous Contract
A46: GOLD (BULLISH) | B46: 4110 | C46: 4287 | D46: 4225
A47: Gold Spot Price
A48: COPPER (BULLISH) | B48: 5.12 | C48: 5.46 | D48: 5.28
A49: Copper Continuous Contract
A50: SILVER (BULLISH) | B50: 54.06 | C50: 61.47 | D50: 57.06
A51: Silver Spot Price
A52: MSFT (BEARISH) | B52: 467 | C52: 495 | D52: 481
A53: Microsoft Corp.
A54: AAPL (BULLISH) | B54: 275 | C54: 290 | D54: 281
A55: Apple Inc.
A56: AMZN (BULLISH) | B56: 220 | C56: 240 | D56: 229
A57: Amazon Inc.
A58: META (BEARISH) | B58: 599 | C58: 679 | D58: 662
A59: Meta Platforms Inc.
A60: GOOGL (BULLISH) | B60: 307 | C60: 333 | D60: 318
A61: Alphabet Inc.
A62: NFLX (BEARISH) | B62: 98 | C62: 109 | D62: 103
A63: Netflix Inc.
A64: TSLA (BULLISH) | B64: 408 | C64: 462 | D64: 455
A65: Tesla Inc.
A66: NVDA (BULLISH) | B66: 176 | C66: 186 | D66: 183
A67: NVIDIA Corporation
A68: ORCL (BEARISH) | B68: 192 | C68: 223 | D68: 214.33
A69: Oracle Corporation
A70: BITCOIN (NEUTRAL) | B70: 87206 | C70: 94405 | D70: 91227
A71: Bitcoin Spot Price

Sheet Dec 8.2025
A1: INDEX | B1: BUY TRADE | C1: SELL TRADE | D1: PREV. CLOSE
A2: UST30Y (BULLISH) | B2: 4.82 | C2: 4.67 | D2: 4.79
A3: 30-Year U.S. Treasury Yield
A4: UST10Y (BEARISH) | B4: 4.17 | C4: 3.96 | D4: 4.14
A5: 10-Year U.S. Treasury Yield
A6: UST2Y (BEARISH) | B6: 3.6 | C6: 3.46 | D6: 3.57
A7: 2-Year U.S. Treasury Yield
A8: HYG (BULLISH) | B8: 80.23 | C8: 80.99 | D8: 80.75
A9: High Yield
A10: LQD (BULLISH) | B10: 110.3 | C10: 111.7 | D10: 110.9
A11: Investment Grade Corporate Bond ETF
A12: SPX (BULLISH) | B12: 6714 | C12: 6926 | D12: 6870
A13: S&P 500
A14: COMPQ (BULLISH) | B14: 22905 | C14: 23936 | D14: 23578
A15: NASDAQ Composite
A16: RUT (BULLISH) | B16: 2450 | C16: 2563 | D16: 2521
A17: Russell 2000
A18: XLK (BULLISH) | B18: 139 | C18: 149 | D18: 147
A19: Technology Select Sector SPDR Fund
A20: XLV (BULLISH) | B20: 151 | C20: 160 | D20: 153.26
A21: Health Care Select Sector SPDR Fund
A22: SSEC (NEUTRAL) | B22: 3838 | C22: 3936 | D22: 3924
A23: Shanghai Composite
A24: NIKK (BULLISH) | B24: 48907 | C24: 51308 | D24: 50581
A25: Nikkei 225 Index
A26: DAX (NEUTRAL) | B26: 23331 | C26: 24153 | D26: 24028
A27: German DAX Composite
A28: VIX (BEARISH) | B28: 14.18 | C28: 20.19 | D28: 15.41
A29: Volatility Index
A30: USD (BEARISH) | B30: 98.58 | C30: 99.7 | D30: 98.99
A31: U.S. Dollar Index
A32: EUR/USD (BULLISH) | B32: 1.158 | C32: 1.17 | D32: 1.165
A33: Euro to U.S. Dollar
A34: USD/YEN (BULLISH) | B34: 154.62 | C34: 156.8 | D34: 155.63
A35: U.S. Dollar to Japanese Yen
A36: GBP/USD (BULLISH) | B36: 1.315 | C36: 1.339 | D36: 1.332
A37: British Pound to U.S. Dollar
A38: CAD/USD (BULLISH) | B38: 0.713 | C38: 0.725 | D38: 0.724
A39: Canadian Dollar to U.S. Dollar
A40: WTIC (BEARISH) | B40: 57.96 | C40: 60.34 | D40: 60.14
A41: Light Crude Oil Continuous Contract
A42: BRENT (BEARISH) | B42: 62.05 | C42: 64 | D42: 63.76
A43: Brent Crude Oil Continuous Contract
A44: NATGAS (BULLISH) | B44: 4.68 | C44: 5.39 | D44: 5.34
A45: Natural Gas Continuous Contract
A46: GOLD (BULLISH) | B46: 4115 | C46: 4267 | D46: 4212
A47: Gold Spot Price
A48: COPPER (BULLISH) | B48: 5.1 | C48: 5.45 | D48: 5.37
A49: Copper Continuous Contract
A50: SILVER (BULLISH) | B50: 55.67 | C50: 61.72 | D50: 58.28
A51: Silver Spot Price
A52: MSFT (BEARISH) | B52: 469 | C52: 494 | D52: 483
A53: Microsoft Corp.
A54: AAPL (BULLISH) | B54: 273 | C54: 288 | D54: 279
A55: Apple Inc.
A56: AMZN (BULLISH) | B56: 223 | C56: 238 | D56: 230
A57: Amazon Inc.
A58: META (BEARISH) | B58: 608 | C58: 680 | D58: 673
A59: Meta Platforms Inc.
A60: GOOGL (BULLISH) | B60: 311 | C60: 330 | D60: 321
A61: Alphabet Inc.
A62: NFLX (BEARISH) | B62: 97 | C62: 108 | D62: 100
A63: Netflix Inc.
A64: TSLA (BULLISH) | B64: 419 | C64: 463 | D64: 455
A65: Tesla Inc.
A66: NVDA (BULLISH) | B66: 176 | C66: 186 | D66: 182
A67: NVIDIA Corporation
A68: ORCL (BEARISH) | B68: 188 | C68: 224 | D68: 217.58
A69: Oracle Corporation
A70: BITCOIN (NEUTRAL) | B70: 86768 | C70: 94669 | D70: 91801
A71: Bitcoin Spot Price

Sheet Dec. 9.2025
A1: INDEX | B1: BUY TRADE | C1: SELL TRADE | D1: PREV. CLOSE
A2: UST30Y (BULLISH) | B2: 4.85 | C2: 4.71 | D2: 4.8
A3: 30-Year U.S. Treasury Yield
A4: UST10Y (BEARISH) | B4: 4.18 | C4: 3.95 | D4: 4.17
A5: 10-Year U.S. Treasury Yield
A6: UST2Y (BEARISH) | B6: 3.6 | C6: 3.45 | D6: 3.58
A7: 2-Year U.S. Treasury Yield
A8: HYG (BULLISH) | B8: 80.27 | C8: 80.91 | D8: 80.55
A9: High Yield
A10: LQD (BULLISH) | B10: 110.3 | C10: 111.8 | D10: 110.6
A11: Investment Grade Corporate Bond ETF
A12: SPX (BULLISH) | B12: 6762 | C12: 6902 | D12: 6846
A13: S&P 500
A14: COMPQ (BULLISH) | B14: 23140 | C14: 23810 | D14: 23545
A15: NASDAQ Composite
A16: RUT (BULLISH) | B16: 2444 | C16: 2532 | D16: 2520
A17: Russell 2000
A18: XLK (BULLISH) | B18: 141 | C18: 152 | D18: 148
A19: Technology Select Sector SPDR Fund
A20: XLV (BULLISH) | B20: 150 | C20: 161 | D20: 151.43
A21: Health Care Select Sector SPDR Fund
A22: SSEC (NEUTRAL) | B22: 3840 | C22: 3930 | D22: 3909
A23: Shanghai Composite
A24: NIKK (BULLISH) | B24: 48951 | C24: 51202 | D24: 50655
A25: Nikkei 225 Index
A26: DAX (NEUTRAL) | B26: 23498 | C26: 24199 | D26: 24046
A27: German DAX Composite
A28: VIX (BEARISH) | B28: 14.71 | C28: 18.92 | D28: 16.66
A29: Volatility Index
A30: USD (BEARISH) | B30: 98.6 | C30: 99.74 | D30: 99.12
A31: U.S. Dollar Index
A32: EUR/USD (BULLISH) | B32: 1.159 | C32: 1.169 | D32: 1.164
A33: Euro to U.S. Dollar
A34: USD/YEN (BULLISH) | B34: 154.72 | C34: 156.71 | D34: 156.28
A35: U.S. Dollar to Japanese Yen
A36: GBP/USD (BULLISH) | B36: 1.32 | C36: 1.34 | D36: 1.332
A37: British Pound to U.S. Dollar
A38: CAD/USD (BULLISH) | B38: 0.715 | C38: 0.726 | D38: 0.722
A39: Canadian Dollar to U.S. Dollar
A40: WTIC (BEARISH) | B40: 57.7 | C40: 60.27 | D40: 58.85
A41: Light Crude Oil Continuous Contract
A42: BRENT (BEARISH) | B42: 61.9 | C42: 63.95 | D42: 62.49
A43: Brent Crude Oil Continuous Contract
A44: NATGAS (BULLISH) | B44: 4.5 | C44: 5.31 | D44: 4.87
A45: Natural Gas Continuous Contract
A46: GOLD (BULLISH) | B46: 4132 | C46: 4262 | D46: 4202
A47: Gold Spot Price
A48: COPPER (BULLISH) | B48: 5.11 | C48: 5.46 | D48: 5.35
A49: Copper Continuous Contract
A50: SILVER (BULLISH) | B50: 54.62 | C50: 61.49 | D50: 58.09
A51: Silver Spot Price
A52: MSFT (BEARISH) | B52: 472 | C52: 496 | D52: 491
A53: Microsoft Corp.
A54: AAPL (BULLISH) | B54: 273 | C54: 287 | D54: 278
A55: Apple Inc.
A56: AMZN (BULLISH) | B56: 224 | C56: 237 | D56: 227
A57: Amazon Inc.
A58: META (BEARISH) | B58: 620 | C58: 681 | D58: 667
A59: Meta Platforms Inc.
A60: GOOGL (BULLISH) | B60: 311 | C60: 328 | D60: 314
A61: Alphabet Inc.
A62: NFLX (BEARISH) | B62: 93 | C62: 105 | D62: 97
A63: Netflix Inc.
A64: TSLA (BULLISH) | B64: 420 | C64: 463 | D64: 440
A65: Tesla Inc.
A66: NVDA (BULLISH) | B66: 179 | C66: 194 | D66: 186
A67: NVIDIA Corporation
A68: ORCL (BEARISH) | B68: 187 | C68: 229 | D68: 220.54
A69: Oracle Corporation
A70: BITCOIN (NEUTRAL) | B70: 86447 | C70: 94238 | D70: 90606
A71: Bitcoin Spot Price

Sheet Dec 10.2025
A1: INDEX | B1: BUY TRADE | C1: SELL TRADE | D1: PREV. CLOSE
A2: UST30Y (BULLISH) | B2: 4.86 | C2: 4.72 | D2: 4.81
A3: 30-Year U.S. Treasury Yield
A4: UST10Y (BEARISH) | B4: 4.22 | C4: 3.99 | D4: 4.19
A5: 10-Year U.S. Treasury Yield
A6: UST2Y (BEARISH) | B6: 3.65 | C6: 3.45 | D6: 3.62
A7: 2-Year U.S. Treasury Yield
A8: HYG (BULLISH) | B8: 80.29 | C8: 80.91 | D8: 80.46
A9: High Yield
A10: LQD (BULLISH) | B10: 110 | C10: 111.6 | D10: 110.5
A11: Investment Grade Corporate Bond ETF
A12: SPX (BULLISH) | B12: 6787 | C12: 6897 | D12: 6840
A13: S&P 500
A14: COMPQ (BULLISH) | B14: 23103 | C14: 23883 | D14: 23576
A15: NASDAQ Composite
A16: RUT (BULLISH) | B16: 2470 | C16: 2559 | D16: 2526
A17: Russell 2000
A18: XLK (BULLISH) | B18: 143 | C18: 152 | D18: 148
A19: Technology Select Sector SPDR Fund
A20: XLV (BULLISH) | B20: 149 | C20: 160 | D20: 150
A21: Health Care Select Sector SPDR Fund
A22: SSEC (BEARISH) | B22: 3842 | C22: 3925 | D22: 3900
A23: Shanghai Composite
A24: NIKK (BULLISH) | B24: 49068 | C24: 51328 | D24: 50602
A25: Nikkei 225 Index
A26: DAX (NEUTRAL) | B26: 23422 | C26: 24204 | D26: 24162
A27: German DAX Composite
A28: VIX (BEARISH) | B28: 15.19 | C28: 18.23 | D28: 16.93
A29: Volatility Index
A30: USD (BEARISH) | B30: 98.68 | C30: 99.61 | D30: 99.11
A31: U.S. Dollar Index
A32: EUR/USD (BULLISH) | B32: 1.159 | C32: 1.171 | D32: 1.164
A33: Euro to U.S. Dollar
A34: USD/YEN (BULLISH) | B34: 154.81 | C34: 157.13 | D34: 156.71
A35: U.S. Dollar to Japanese Yen
A36: GBP/USD (BULLISH) | B36: 1.322 | C36: 1.341 | D36: 1.331
A37: British Pound to U.S. Dollar
A38: CAD/USD (BULLISH) | B38: 0.715 | C38: 0.726 | D38: 0.722
A39: Canadian Dollar to U.S. Dollar
A40: WTIC (BEARISH) | B40: 57.95 | C40: 60.08 | D40: 58.39
A41: Light Crude Oil Continuous Contract
A42: BRENT (BEARISH) | B42: 61.63 | C42: 63.75 | D42: 62.12
A43: Brent Crude Oil Continuous Contract
A44: NATGAS (BULLISH) | B44: 4.4 | C44: 5.35 | D44: 4.58
A45: Natural Gas Continuous Contract
A46: GOLD (BULLISH) | B46: 4157 | C46: 4248 | D46: 4208
A47: Gold Spot Price
A48: COPPER (BULLISH) | B48: 5.13 | C48: 5.47 | D48: 5.25
A49: Copper Continuous Contract
A50: SILVER (BULLISH) | B50: 57.13 | C50: 61.76 | D50: 60.52
A51: Silver Spot Price
A52: MSFT (BEARISH) | B52: 474 | C52: 497 | D52: 492
A53: Microsoft Corp.
A54: AAPL (BULLISH) | B54: 274 | C54: 288 | D54: 277
A55: Apple Inc.
A56: AMZN (BULLISH) | B56: 224 | C56: 236 | D56: 228
A57: Amazon Inc.
A58: META (BEARISH) | B58: 623 | C58: 679 | D58: 657
A59: Meta Platforms Inc.
A60: GOOGL (BULLISH) | B60: 310 | C60: 326 | D60: 317
A61: Alphabet Inc.
A62: NFLX (BEARISH) | B62: 93 | C62: 103 | D62: 97
A63: Netflix Inc.
A64: TSLA (BULLISH) | B64: 425 | C64: 462 | D64: 445
A65: Tesla Inc.
A66: NVDA (BULLISH) | B66: 180 | C66: 190 | D66: 185
A67: NVIDIA Corporation
A68: ORCL (BEARISH) | B68: 188 | C68: 231 | D68: 222
A69: Oracle Corporation
A70: BITCOIN (NEUTRAL) | B70: 88008 | C70: 94286 | D70: 92030
A71: Bitcoin Spot Price

Sheet Dec. 11.2025
A1: INDEX | B1: BUY TRADE | C1: SELL TRADE | D1: PREV. CLOSE
A2: UST30Y (BULLISH) | B2: 4.82 | C2: 4.69 | D2: 4.78
A3: 30-Year U.S. Treasury Yield
A4: UST10Y (BEARISH) | B4: 4.19 | C4: 3.99 | D4: 4.16
A5: 10-Year U.S. Treasury Yield
A6: UST2Y (BEARISH) | B6: 3.61 | C6: 3.46 | D6: 3.55
A7: 2-Year U.S. Treasury Yield
A8: HYG (BULLISH) | B8: 80.31 | C8: 80.94 | D8: 80.73
A9: High Yield
A10: LQD (BULLISH) | B10: 110.2 | C10: 111.6 | D10: 111
A11: Investment Grade Corporate Bond ETF
A12: SPX (BULLISH) | B12: 6801 | C12: 6918 | D12: 6886
A13: S&P 500
A14: COMPQ (BULLISH) | B14: 23206 | C14: 23881 | D14: 23654
A15: NASDAQ Composite
A16: RUT (BULLISH) | B16: 2481 | C16: 2582 | D16: 2559
A17: Russell 2000
A18: XLK (BULLISH) | B18: 142 | C18: 150 | D18: 149
A19: Technology Select Sector SPDR Fund
A20: XLV (BULLISH) | B20: 149 | C20: 157 | D20: 152
A21: Health Care Select Sector SPDR Fund
A22: XLY (BULLISH) | B22: 117 | C22: 121 | D22: 120
A23: Consumer Discretionary Select Sector SPDR Fund
A24: SSEC (BEARISH) | B24: 3843 | C24: 3923 | D24: 3873
A25: Shanghai Composite
A26: NIKK (BULLISH) | B26: 49036 | C26: 51316 | D26: 50148
A27: Nikkei 225 Index
A28: DAX (NEUTRAL) | B28: 23501 | C28: 24296 | D28: 24130
A29: German DAX Composite
A30: VIX (BEARISH) | B30: 14.72 | C30: 18.03 | D30: 15.77
A31: Volatility Index
A32: USD (BEARISH) | B32: 98.25 | C32: 99.26 | D32: 98.5
A33: U.S. Dollar Index
A34: EUR/USD (BULLISH) | B34: 1.161 | C34: 1.173 | D34: 1.171
A35: Euro to U.S. Dollar
A36: USD/YEN (BULLISH) | B36: 154.53 | C36: 156.81 | D36: 155.54
A37: U.S. Dollar to Japanese Yen
A38: GBP/USD (BULLISH) | B38: 1.324 | C38: 1.344 | D38: 1.339
A39: British Pound to U.S. Dollar
A40: CAD/USD (BULLISH) | B40: 0.716 | C40: 0.729 | D40: 0.724
A41: Canadian Dollar to U.S. Dollar
A42: WTIC (BEARISH) | B42: 57.02 | C42: 60.07 | D42: 58.77
A43: Light Crude Oil Continuous Contract
A44: BRENT (BEARISH) | B44: 61.11 | C44: 63.27 | D44: 62.21
A45: Brent Crude Oil Continuous Contract
A46: NATGAS (BULLISH) | B46: 4.42 | C46: 5.32 | D46: 4.59
A47: Natural Gas Continuous Contract
A48: GOLD (BULLISH) | B48: 4175 | C48: 4254 | D48: 4225
A49: Gold Spot Price
A50: COPPER (BULLISH) | B50: 5.16 | C50: 5.49 | D50: 5.33
A51: Copper Continuous Contract
A52: SILVER (BULLISH) | B52: 58.5 | C52: 62.49 | D52: 61.87
A53: Silver Spot Price
A54: MSFT (BEARISH) | B54: 470 | C54: 493 | D54: 479
A55: Microsoft Corp.
A56: AAPL (BULLISH) | B56: 274 | C56: 288 | D56: 279
A57: Apple Inc.
A58: AMZN (BULLISH) | B58: 225 | C58: 238 | D58: 232
A59: Amazon Inc.
A60: META (BEARISH) | B60: 628 | C60: 677 | D60: 650
A61: Meta Platforms Inc.
A62: GOOGL (BULLISH) | B62: 311 | C62: 326 | D62: 320
A63: Alphabet Inc.
A64: NFLX (BEARISH) | B64: 90 | C64: 99 | D64: 93
A65: Netflix Inc.
A66: TSLA (BULLISH) | B66: 429 | C66: 465 | D66: 451
A67: Tesla Inc.
A68: NVDA (BULLISH) | B68: 177 | C68: 189 | D68: 184
A69: NVIDIA Corporation
A70: ORCL (BEARISH) | B70: 188 | C70: 224 | D70: 223
A71: Oracle Corporation
A72: BITCOIN (NEUTRAL) | B72: 88103 | C72: 93997 | D72: 90068
A73: Bitcoin Spot Price

Sheet Dec 12.2025
A1: INDEX | B1: BUY TRADE | C1: SELL TRADE | D1: PREV. CLOSE
A2: UST30Y (BULLISH) | B2: 4.84 | C2: 4.71 | D2: 4.8
A3: 30-Year U.S. Treasury Yield
A4: UST10Y (BEARISH) | B4: 4.22 | C4: 4.02 | D4: 4.16
A5: 10-Year U.S. Treasury Yield
A6: UST2Y (BEARISH) | B6: 3.62 | C6: 3.46 | D6: 3.55
A7: 2-Year U.S. Treasury Yield
A8: HYG (BULLISH) | B8: 80.34 | C8: 80.96 | D8: 80.72
A9: High Yield
A10: LQD (BULLISH) | B10: 110.3 | C10: 111.4 | D10: 110.8
A11: Investment Grade Corporate Bond ETF
A12: SPX (BULLISH) | B12: 6812 | C12: 6937 | D12: 6901
A13: S&P 500
A14: COMPQ (BULLISH) | B14: 23291 | C14: 23827 | D14: 23593
A15: NASDAQ Composite
A16: RUT (BULLISH) | B16: 2482 | C16: 2610 | D16: 2590
A17: Russell 2000
A18: XLK (BULLISH) | B18: 143 | C18: 150 | D18: 148
A19: Technology Select Sector SPDR Fund
A20: XLV (BULLISH) | B20: 149 | C20: 157 | D20: 154
A21: Health Care Select Sector SPDR Fund
A22: XLY (BULLISH) | B22: 118 | C22: 122 | D22: 120
A23: Consumer Discretionary Select Sector SPDR Fund
A24: SSEC (BEARISH) | B24: 3844 | C24: 3923 | D24: 3889
A25: Shanghai Composite
A26: NIKK (BULLISH) | B26: 49039 | C26: 51616 | D26: 50836
A27: Nikkei 225 Index
A28: DAX (BULLISH) | B28: 23602 | C28: 24601 | D28: 24294
A29: German DAX Composite
A30: VIX (BEARISH) | B30: 14.49 | C30: 17.24 | D30: 14.85
A31: Volatility Index
A32: USD (BEARISH) | B32: 98.18 | C32: 99.18 | D32: 98.45
A33: U.S. Dollar Index
A34: EUR/USD (BULLISH) | B34: 1.162 | C34: 1.174 | D34: 1.173
A35: Euro to U.S. Dollar
A36: USD/YEN (BULLISH) | B36: 154.52 | C36: 156.8 | D36: 156
A37: U.S. Dollar to Japanese Yen
A38: GBP/USD (BULLISH) | B38: 1.324 | C38: 1.344 | D38: 1.338
A39: British Pound to U.S. Dollar
A40: CAD/USD (BULLISH) | B40: 0.716 | C40: 0.729 | D40: 0.726
A41: Canadian Dollar to U.S. Dollar
A42: WTIC (BEARISH) | B42: 57.03 | C42: 60.01 | D42: 57.92
A43: Light Crude Oil Continuous Contract
A44: BRENT (BEARISH) | B44: 61.01 | C44: 63.21 | D44: 61.59
A45: Brent Crude Oil Continuous Contract
A46: NATGAS (NEUTRAL) | B46: 3.95 | C46: 4.92 | D46: 4.23
A47: Natural Gas Continuous Contract
A48: GOLD (BULLISH) | B48: 4207 | C48: 4374 | D48: 4282
A49: Gold Spot Price
A50: COPPER (BULLISH) | B50: 5.21 | C50: 5.48 | D50: 5.42
A51: Copper Continuous Contract
A52: SILVER (BULLISH) | B52: 59.39 | C52: 64.97 | D52: 63.56
A53: Silver Spot Price
A54: MSFT (BEARISH) | B54: 471 | C54: 492 | D54: 483
A55: Microsoft Corp.
A56: AAPL (BULLISH) | B56: 273 | C56: 287 | D56: 278
A57: Apple Inc.
A58: AMZN (BULLISH) | B58: 225 | C58: 237 | D58: 230
A59: Amazon Inc.
A60: META (BEARISH) | B60: 627 | C60: 674 | D60: 653
A61: Meta Platforms Inc.
A62: GOOGL (BULLISH) | B62: 310 | C62: 325 | D62: 312
A63: Alphabet Inc.
A64: NFLX (BEARISH) | B64: 88 | C64: 98 | D64: 94
A65: Netflix Inc.
A66: TSLA (BULLISH) | B66: 434 | C66: 465 | D66: 447
A67: Tesla Inc.
A68: NVDA (NEUTRAL) | B68: 176 | C68: 186 | D68: 181
A69: NVIDIA Corporation
A70: ORCL (BEARISH) | B70: 187 | C70: 212 | D70: 199
A71: Oracle Corporation
A72: BITCOIN (NEUTRAL) | B72: 88502 | C72: 93903 | D72: 92374
A73: Bitcoin Spot Price

Sheet Dec. 15.2025
A1: INDEX | B1: BUY TRADE | C1: SELL TRADE | D1: PREV. CLOSE
A2: UST30Y (BULLISH) | B2: 4.86 | C2: 4.73 | D2: 4.84
A3: 30-Year U.S. Treasury Yield
A4: UST10Y (BEARISH) | B4: 4.23 | C4: 4.05 | D4: 4.18
A5: 10-Year U.S. Treasury Yield
A6: UST2Y (BEARISH) | B6: 3.62 | C6: 3.46 | D6: 3.53
A7: 2-Year U.S. Treasury Yield
A8: HYG (BULLISH) | B8: 80.35 | C8: 80.94 | D8: 80.57
A9: High Yield
A10: LQD (BULLISH) | B10: 110 | C10: 111.5 | D10: 110.2
A11: Investment Grade Corporate Bond ETF
A12: SPX (BULLISH) | B12: 6805 | C12: 6913 | D12: 6827
A13: S&P 500
A14: COMPQ (BULLISH) | B14: 23195 | C14: 23799 | D14: 23195
A15: NASDAQ Composite
A16: RUT (BULLISH) | B16: 2497 | C16: 2592 | D16: 2551
A17: Russell 2000
A18: XLK (BULLISH) | B18: 141 | C18: 148 | D18: 144
A19: Technology Select Sector SPDR Fund
A20: XLV (BULLISH) | B20: 150 | C20: 157 | D20: 154
A21: Health Care Select Sector SPDR Fund
A22: XLY (BULLISH) | B22: 118 | C22: 122 | D22: 121
A23: Consumer Discretionary Select Sector SPDR Fund
A24: SSEC (BEARISH) | B24: 3843 | C24: 3923 | D24: 3867
A25: Shanghai Composite
A26: NIKK (BULLISH) | B26: 49312 | C26: 51408 | D26: 50168
A27: Nikkei 225 Index
A28: DAX (BULLISH) | B28: 23606 | C28: 24419 | D28: 24186
A29: German DAX Composite
A30: VIX (BEARISH) | B30: 14.53 | C30: 17.67 | D30: 15.74
A31: Volatility Index
A32: USD (BEARISH) | B32: 98.04 | C32: 99.02 | D32: 98.24
A33: U.S. Dollar Index
A34: EUR/USD (BULLISH) | B34: 1.163 | C34: 1.176 | D34: 1.175
A35: Euro to U.S. Dollar
A36: USD/YEN (NEUTRAL) | B36: 154.17 | C36: 156.65 | D36: 154.99
A37: U.S. Dollar to Japanese Yen
A38: GBP/USD (BULLISH) | B38: 1.327 | C38: 1.343 | D38: 1.339
A39: British Pound to U.S. Dollar
A40: CAD/USD (BULLISH) | B40: 0.717 | C40: 0.728 | D40: 0.726
A41: Canadian Dollar to U.S. Dollar
A42: WTIC (BEARISH) | B42: 56.97 | C42: 59.17 | D42: 57.53
A43: Light Crude Oil Continuous Contract
A44: BRENT (BEARISH) | B44: 60.9 | C44: 62.98 | D44: 61.22
A45: Brent Crude Oil Continuous Contract
A46: NATGAS (NEUTRAL) | B46: 3.94 | C46: 4.76 | D46: 4.1
A47: Natural Gas Continuous Contract
A48: GOLD (BULLISH) | B48: 4204 | C48: 4357 | D48: 4347
A49: Gold Spot Price
A50: COPPER (BULLISH) | B50: 5.2 | C50: 5.48 | D50: 5.28
A51: Copper Continuous Contract
A52: SILVER (BULLISH) | B52: 59.92 | C52: 64.21 | D52: 62.01
A53: Silver Spot Price
A54: MSFT (BEARISH) | B54: 471 | C54: 491 | D54: 479
A55: Microsoft Corp.
A56: AAPL (BULLISH) | B56: 273 | C56: 287 | D56: 278
A57: Apple Inc.
A58: AMZN (BULLISH) | B58: 222 | C58: 236 | D58: 226
A59: Amazon Inc.
A60: META (BEARISH) | B60: 629 | C60: 672 | D60: 644
A61: Meta Platforms Inc.
A62: GOOGL (BULLISH) | B62: 307 | C62: 324 | D62: 309
A63: Alphabet Inc.
A64: NFLX (BEARISH) | B64: 87 | C64: 99 | D64: 95
A65: Netflix Inc.
A66: TSLA (BULLISH) | B66: 436 | C66: 468 | D66: 459
A67: Tesla Inc.
A68: NVDA (BEARISH) | B68: 171 | C68: 183 | D68: 175
A69: NVIDIA Corporation
A70: ORCL (BEARISH) | B70: 185 | C70: 210 | D70: 190
A71: Oracle Corporation
A72: BITCOIN (NEUTRAL) | B72: 88008 | C72: 93677 | D72: 89697
A73: Bitcoin Spot Price

Sheet Dec 16.2025
A1: INDEX | B1: BUY TRADE | C1: SELL TRADE | D1: PREV. CLOSE
A2: UST30Y (BULLISH) | B2: 4.88 | C2: 4.75 | D2: 4.85
A3: 30-Year U.S. Treasury Yield
A4: UST10Y (BEARISH) | B4: 4.23 | C4: 4.05 | D4: 4.18
A5: 10-Year U.S. Treasury Yield
A6: UST2Y (BEARISH) | B6: 3.6 | C6: 3.46 | D6: 3.52
A7: 2-Year U.S. Treasury Yield
A8: HYG (BULLISH) | B8: 80.39 | C8: 80.94 | D8: 80.61
A9: High Yield
A10: LQD (BULLISH) | B10: 110 | C10: 111.4 | D10: 110.3
A11: Investment Grade Corporate Bond ETF
A12: SPX (BULLISH) | B12: 6795 | C12: 6916 | D12: 6816
A13: S&P 500
A14: COMPQ (BULLISH) | B14: 22901 | C14: 23862 | D14: 23057
A15: NASDAQ Composite
A16: RUT (BULLISH) | B16: 2484 | C16: 2578 | D16: 2530
A17: Russell 2000
A18: XLK (BULLISH) | B18: 140 | C18: 148 | D18: 142
A19: Technology Select Sector SPDR Fund
A20: XLV (BULLISH) | B20: 152 | C20: 158 | D20: 156
A21: Health Care Select Sector SPDR Fund
A22: XLY (BULLISH) | B22: 119 | C22: 123 | D22: 122
A23: Consumer Discretionary Select Sector SPDR Fund
A24: SSEC (BEARISH) | B24: 3810 | C24: 3905 | D24: 3824
A25: Shanghai Composite
A26: NIKK (BULLISH) | B26: 49003 | C26: 51164 | D26: 49383
A27: Nikkei 225 Index
A28: DAX (BULLISH) | B28: 23708 | C28: 24436 | D28: 24229
A29: German DAX Composite
A30: VIX (BEARISH) | B30: 14.64 | C30: 17.83 | D30: 16.5
A31: Volatility Index
A32: USD (BEARISH) | B32: 97.84 | C32: 99.05 | D32: 98.14
A33: U.S. Dollar Index
A34: EUR/USD (BULLISH) | B34: 1.163 | C34: 1.181 | D34: 1.177
A35: Euro to U.S. Dollar
A36: USD/YEN (NEUTRAL) | B36: 154.07 | C36: 156.61 | D36: 154.8
A37: U.S. Dollar to Japanese Yen
A38: GBP/USD (BULLISH) | B38: 1.329 | C38: 1.345 | D38: 1.343
A39: British Pound to U.S. Dollar
A40: CAD/USD (BULLISH) | B40: 0.718 | C40: 0.728 | D40: 0.726
A41: Canadian Dollar to U.S. Dollar
A42: WTIC (BEARISH) | B42: 55.39 | C42: 58.87 | D42: 56.88
A43: Light Crude Oil Continuous Contract
A44: BRENT (BEARISH) | B44: 59.11 | C44: 62.7 | D44: 60.39
A45: Brent Crude Oil Continuous Contract
A46: NATGAS (BEARISH) | B46: 3.71 | C46: 4.44 | D46: 4.03
A47: Natural Gas Continuous Contract
A48: GOLD (BULLISH) | B48: 4215 | C48: 4342 | D48: 4291
A49: Gold Spot Price
A50: COPPER (BULLISH) | B50: 5.2 | C50: 5.45 | D50: 5.33
A51: Copper Continuous Contract
A52: SILVER (BULLISH) | B52: 60.25 | C52: 65.38 | D52: 64.08
A53: Silver Spot Price
A54: MSFT (BEARISH) | B54: 469 | C54: 489 | D54: 475
A55: Microsoft Corp.
A56: AAPL (BULLISH) | B56: 272 | C56: 286 | D56: 274
A57: Apple Inc.
A58: AMZN (BEARISH) | B58: 217 | C58: 232 | D58: 223
A59: Amazon Inc.
A60: META (BEARISH) | B60: 631 | C60: 672 | D60: 648
A61: Meta Platforms Inc.
A62: GOOGL (BULLISH) | B62: 305 | C62: 325 | D62: 308
A63: Alphabet Inc.
A64: NFLX (BEARISH) | B64: 87 | C64: 97 | D64: 94
A65: Netflix Inc.
A66: TSLA (BULLISH) | B66: 439 | C66: 480 | D66: 475
A67: Tesla Inc.
A68: NVDA (BEARISH) | B68: 172 | C68: 183 | D68: 176
A69: NVIDIA Corporation
A70: ORCL (BEARISH) | B70: 180 | C70: 207 | D70: 185
A71: Oracle Corporation
A72: BITCOIN (BEARISH) | B72: 85238 | C72: 93501 | D72: 87217
A73: Bitcoin Spot Price

Sheet Dec 17.2025
A1: INDEX | B1: BUY TRADE | C1: SELL TRADE | D1: PREV. CLOSE
A2: UST30Y (BULLISH) | B2: 4.87 | C2: 4.74 | D2: 4.82
A3: 30-Year U.S. Treasury Yield
A4: UST10Y (BEARISH) | B4: 4.2 | C4: 4.07 | D4: 4.14
A5: 10-Year U.S. Treasury Yield
A6: UST2Y (BEARISH) | B6: 3.59 | C6: 3.46 | D6: 3.5
A7: 2-Year U.S. Treasury Yield
A8: HYG (BULLISH) | B8: 80.4 | C8: 80.91 | D8: 80.66
A9: High Yield
A10: LQD (BULLISH) | B10: 109.8 | C10: 111.1 | D10: 110.6
A11: Investment Grade Corporate Bond ETF
A12: SPX (BULLISH) | B12: 6777 | C12: 6921 | D12: 6800
A13: S&P 500
A14: COMPQ (BULLISH) | B14: 22954 | C14: 23893 | D14: 23111
A15: NASDAQ Composite
A16: RUT (BULLISH) | B16: 2484 | C16: 2578 | D16: 2519
A17: Russell 2000
A18: XLK (BULLISH) | B18: 140 | C18: 148 | D18: 143
A19: Technology Select Sector SPDR Fund
A20: XLV (BULLISH) | B20: 151 | C20: 157 | D20: 154
A21: Health Care Select Sector SPDR Fund
A22: XLY (BULLISH) | B22: 120 | C22: 124 | D22: 122
A23: Consumer Discretionary Select Sector SPDR Fund
A24: SSEC (BEARISH) | B24: 3820 | C24: 3898 | D24: 3870
A25: Shanghai Composite
A26: NIKK (BULLISH) | B26: 49303 | C26: 51111 | D26: 49512
A27: Nikkei 225 Index
A28: DAX (BULLISH) | B28: 23813 | C28: 24407 | D28: 24076
A29: German DAX Composite
A30: VIX (BEARISH) | B30: 14.64 | C30: 17.81 | D30: 16.48
A31: Volatility Index
A32: USD (BEARISH) | B32: 97.84 | C32: 99.03 | D32: 98.56
A33: U.S. Dollar Index
A34: EUR/USD (BULLISH) | B34: 1.164 | C34: 1.181 | D34: 1.172
A35: Euro to U.S. Dollar
A36: USD/YEN (BULLISH) | B36: 154.4 | C36: 156.78 | D36: 155.51
A37: U.S. Dollar to Japanese Yen
A38: GBP/USD (BULLISH) | B38: 1.327 | C38: 1.345 | D38: 1.333
A39: British Pound to U.S. Dollar
A40: CAD/USD (BULLISH) | B40: 0.72 | C40: 0.729 | D40: 0.725
A41: Canadian Dollar to U.S. Dollar
A42: WTIC (BEARISH) | B42: 55.12 | C42: 58.23 | D42: 55.93
A43: Light Crude Oil Continuous Contract
A44: BRENT (BEARISH) | B44: 58.52 | C44: 61.93 | D44: 58.92
A45: Brent Crude Oil Continuous Contract
A46: NATGAS (BEARISH) | B46: 3.61 | C46: 4.4 | D46: 3.89
A47: Natural Gas Continuous Contract
A48: GOLD (BULLISH) | B48: 4236 | C48: 4356 | D48: 4320
A49: Gold Spot Price
A50: COPPER (BULLISH) | B50: 5.23 | C50: 5.47 | D50: 5.3
A51: Copper Continuous Contract
A52: SILVER (BULLISH) | B52: 61.56 | C52: 66.98 | D52: 65.82
A53: Silver Spot Price
A54: MSFT (BEARISH) | B54: 469 | C54: 487 | D54: 476
A55: Microsoft Corp.
A56: AAPL (BULLISH) | B56: 272 | C56: 283 | D56: 275
A57: Apple Inc.
A58: AMZN (BEARISH) | B58: 219 | C58: 231 | D58: 223
A59: Amazon Inc.
A60: META (BEARISH) | B60: 634 | C60: 675 | D60: 657
A61: Meta Platforms Inc.
A62: GOOGL (BULLISH) | B62: 303 | C62: 325 | D62: 307
A63: Alphabet Inc.
A64: NFLX (BEARISH) | B64: 88 | C64: 98 | D64: 95
A65: Netflix Inc.
A66: TSLA (BULLISH) | B66: 458 | C66: 500 | D66: 490
A67: Tesla Inc.
A68: NVDA (BEARISH) | B68: 172 | C68: 182 | D68: 178
A69: NVIDIA Corporation
A70: ORCL (BEARISH) | B70: 175 | C70: 205 | D70: 189
A71: Oracle Corporation
A72: BITCOIN (BEARISH) | B72: 85002 | C72: 91153 | D72: 87111
A73: Bitcoin Spot Price

Sheet Dec 18.2025
A1: INDEX | B1: BUY TRADE | C1: SELL TRADE | D1: PREV. CLOSE
A2: UST30Y (BULLISH) | B2: 4.88 | C2: 4.76 | D2: 4.84
A3: 30-Year U.S. Treasury Yield
A4: UST10Y (BEARISH) | B4: 4.21 | C4: 4.09 | D4: 4.16
A5: 10-Year U.S. Treasury Yield
A6: UST2Y (BEARISH) | B6: 3.58 | C6: 3.43 | D6: 3.49
A7: 2-Year U.S. Treasury Yield
A8: HYG (BULLISH) | B8: 80.41 | C8: 80.88 | D8: 80.56
A9: High Yield
A10: LQD (BULLISH) | B10: 109.9 | C10: 111.2 | D10: 110.4
A11: Investment Grade Corporate Bond ETF
A12: SPX (BULLISH) | B12: 6694 | C12: 6925 | D12: 6721
A13: S&P 500
A14: COMPQ (BULLISH) | B14: 22602 | C14: 23972 | D14: 22693
A15: NASDAQ Composite
A16: RUT (BULLISH) | B16: 2475 | C16: 2590 | D16: 2492
A17: Russell 2000
A18: XLK (NEUTRAL) | B18: 136 | C18: 145 | D18: 139
A19: Technology Select Sector SPDR Fund
A20: XLV (BULLISH) | B20: 149 | C20: 157 | D20: 154
A21: Health Care Select Sector SPDR Fund
A22: XLY (BULLISH) | B22: 119 | C22: 124 | D22: 121
A23: Consumer Discretionary Select Sector SPDR Fund
A24: SSEC (BEARISH) | B24: 3814 | C24: 3899 | D24: 3876
A25: Shanghai Composite
A26: NIKK (BULLISH) | B26: 48521 | C26: 51107 | D26: 49001
A27: Nikkei 225 Index
A28: DAX (BULLISH) | B28: 23818 | C28: 24301 | D28: 23960
A29: German DAX Composite
A30: VIX (BEARISH) | B30: 14.52 | C30: 18.01 | D30: 17.62
A31: Volatility Index
A32: USD (BEARISH) | B32: 97.78 | C32: 98.99 | D32: 98.52
A33: U.S. Dollar Index
A34: EUR/USD (BULLISH) | B34: 1.162 | C34: 1.181 | D34: 1.172
A35: Euro to U.S. Dollar
A36: USD/YEN (BULLISH) | B36: 154.57 | C36: 156.94 | D36: 155.77
A37: U.S. Dollar to Japanese Yen
A38: GBP/USD (BULLISH) | B38: 1.328 | C38: 1.345 | D38: 1.338
A39: British Pound to U.S. Dollar
A40: CAD/USD (BULLISH) | B40: 0.72 | C40: 0.729 | D40: 0.725
A41: Canadian Dollar to U.S. Dollar
A42: WTIC (BEARISH) | B42: 55.04 | C42: 58.42 | D42: 56.9
A43: Light Crude Oil Continuous Contract
A44: BRENT (BEARISH) | B44: 58.63 | C44: 62.3 | D44: 60.61
A45: Brent Crude Oil Continuous Contract
A46: NATGAS (NEUTRAL) | B46: 3.52 | C46: 4.41 | D46: 4.11
A47: Natural Gas Continuous Contract
A48: GOLD (BULLISH) | B48: 4251 | C48: 4375 | D48: 4320
A49: Gold Spot Price
A50: COPPER (BULLISH) | B50: 5.22 | C50: 5.5 | D50: 5.35
A51: Copper Continuous Contract
A52: SILVER (BULLISH) | B52: 62.13 | C52: 67.47 | D52: 66.11
A53: Silver Spot Price
A54: MSFT (BEARISH) | B54: 467 | C54: 485 | D54: 476
A55: Microsoft Corp.
A56: AAPL (BULLISH) | B56: 270 | C56: 282 | D56: 272
A57: Apple Inc.
A58: AMZN (BEARISH) | B58: 216 | C58: 228 | D58: 221
A59: Amazon Inc.
A60: META (BEARISH) | B60: 635 | C60: 673 | D60: 650
A61: Meta Platforms Inc.
A62: GOOGL (BULLISH) | B62: 291 | C62: 329 | D62: 297
A63: Alphabet Inc.
A64: NFLX (BEARISH) | B64: 89 | C64: 99 | D64: 95
A65: Netflix Inc.
A66: TSLA (BULLISH) | B66: 445 | C66: 590 | D66: 467
A67: Tesla Inc.
A68: NVDA (BEARISH) | B68: 166 | C68: 179 | D68: 171
A69: NVIDIA Corporation
A70: ORCL (BEARISH) | B70: 166 | C70: 199 | D70: 178
A71: Oracle Corporation
A72: BITCOIN (BEARISH) | B72: 84711 | C72: 91759 | D72: 87330
A73: Bitcoin Spot Price

Sheet Dec 19.2025
A1: INDEX | B1: BUY TRADE | C1: SELL TRADE | D1: PREV. CLOSE
A2: UST30Y (BULLISH) | B2: 4.87 | C2: 4.76 | D2: 4.81
A3: 30-Year U.S. Treasury Yield
A4: UST10Y (BEARISH) | B4: 4.2 | C4: 4.1 | D4: 4.12
A5: 10-Year U.S. Treasury Yield
A6: UST2Y (BEARISH) | B6: 3.55 | C6: 3.43 | D6: 3.47
A7: 2-Year U.S. Treasury Yield
A8: HYG (BULLISH) | B8: 80.41 | C8: 80.89 | D8: 80.78
A9: High Yield
A10: LQD (BULLISH) | B10: 109.9 | C10: 111.3 | D10: 110.9
A11: Investment Grade Corporate Bond ETF
A12: SPX (BULLISH) | B12: 6712 | C12: 6937 | D12: 6774
A13: S&P 500
A14: COMPQ (BULLISH) | B14: 22632 | C14: 23913 | D14: 23006
A15: NASDAQ Composite
A16: RUT (BULLISH) | B16: 2484 | C16: 2600 | D16: 2507
A17: Russell 2000
A18: XLK (NEUTRAL) | B18: 137 | C18: 145 | D18: 142
A19: Technology Select Sector SPDR Fund
A20: XLV (BULLISH) | B20: 150 | C20: 157 | D20: 154
A21: Health Care Select Sector SPDR Fund
A22: XLY (BULLISH) | B22: 120 | C22: 125 | D22: 122
A23: Consumer Discretionary Select Sector SPDR Fund
A24: SSEC (BEARISH) | B24: 3820 | C24: 3922 | D24: 3890
A25: Shanghai Composite
A26: NIKK (BULLISH) | B26: 48898 | C26: 51319 | D26: 49507
A27: Nikkei 225 Index
A28: DAX (BULLISH) | B28: 23908 | C28: 24395 | D28: 24199
A29: German DAX Composite
A30: VIX (BEARISH) | B30: 14.73 | C30: 17.97 | D30: 16.87
A31: Volatility Index
A32: USD (BEARISH) | B32: 97.89 | C32: 99.04 | D32: 98.68
A33: U.S. Dollar Index
A34: EUR/USD (BULLISH) | B34: 1.163 | C34: 1.181 | D34: 1.171
A35: Euro to U.S. Dollar
A36: USD/YEN (BULLISH) | B36: 155.36 | C36: 157.49 | D36: 157.28
A37: U.S. Dollar to Japanese Yen
A38: GBP/USD (BULLISH) | B38: 1.329 | C38: 1.346 | D38: 1.337
A39: British Pound to U.S. Dollar
A40: CAD/USD (BULLISH) | B40: 0.721 | C40: 0.729 | D40: 0.724
A41: Canadian Dollar to U.S. Dollar
A42: WTIC (BEARISH) | B42: 54.52 | C42: 58.18 | D42: 56.01
A43: Light Crude Oil Continuous Contract
A44: BRENT (BEARISH) | B44: 58.23 | C44: 62.11 | D44: 59.71
A45: Brent Crude Oil Continuous Contract
A46: NATGAS (BEARISH) | B46: 3.54 | C46: 4.45 | D46: 3.92
A47: Natural Gas Continuous Contract
A48: GOLD (BULLISH) | B48: 4265 | C48: 4398 | D48: 4325
A49: Gold Spot Price
A50: COPPER (BULLISH) | B50: 5.25 | C50: 5.5 | D50: 5.35
A51: Copper Continuous Contract
A52: SILVER (BULLISH) | B52: 62.86 | C52: 67.67 | D52: 65.41
A53: Silver Spot Price
A54: MSFT (BEARISH) | B54: 468 | C54: 491 | D54: 484
A55: Microsoft Corp.
A56: AAPL (BULLISH) | B56: 270 | C56: 283 | D56: 272
A57: Apple Inc.
A58: AMZN (NEUTRAL) | B58: 217 | C58: 230 | D58: 227
A59: Amazon Inc.
A60: META (BEARISH) | B60: 637 | C60: 674 | D60: 664
A61: Meta Platforms Inc.
A62: GOOGL (BULLISH) | B62: 293 | C62: 326 | D62: 302
A63: Alphabet Inc.
A64: NFLX (BEARISH) | B64: 90 | C64: 98 | D64: 94
A65: Netflix Inc.
A66: TSLA (BULLISH) | B66: 461 | C66: 501 | D66: 483
A67: Tesla Inc.
A68: NVDA (BEARISH) | B68: 167 | C68: 181 | D68: 174
A69: NVIDIA Corporation
A70: ORCL (BEARISH) | B70: 165 | C70: 199 | D70: 180
A71: Oracle Corporation
A72: BITCOIN (BEARISH) | B72: 84178 | C72: 91548 | D72: 88216
A73: Bitcoin Spot Price

Sheet Dec 22.2025
A1: INDEX | B1: BUY TRADE | C1: SELL TRADE | D1: PREV. CLOSE
A2: UST30Y (BULLISH) | B2: 4.88 | C2: 4.77 | D2: 4.82
A3: 30-Year U.S. Treasury Yield
A4: UST10Y (BEARISH) | B4: 4.21 | C4: 4.1 | D4: 4.14
A5: 10-Year U.S. Treasury Yield
A6: UST2Y (BEARISH) | B6: 3.53 | C6: 3.43 | D6: 3.49
A7: 2-Year U.S. Treasury Yield
A8: HYG (BULLISH) | B8: 80.1 | C8: 80.67 | D8: 80.36
A9: High Yield
A10: LQD (BULLISH) | B10: 109.8 | C10: 110.9 | D10: 110.1
A11: Investment Grade Corporate Bond ETF
A12: SPX (BULLISH) | B12: 6721 | C12: 6936 | D12: 6834
A13: S&P 500
A14: COMPQ (BULLISH) | B14: 22636 | C14: 23877 | D14: 23307
A15: NASDAQ Composite
A16: RUT (BULLISH) | B16: 2498 | C16: 2601 | D16: 2529
A17: Russell 2000
A18: XLK (BULLISH) | B18: 139 | C18: 148 | D18: 145
A19: Technology Select Sector SPDR Fund
A20: XLV (BULLISH) | B20: 151 | C20: 158 | D20: 155
A21: Health Care Select Sector SPDR Fund
A22: XLY (BULLISH) | B22: 121 | C22: 125 | D22: 122
A23: Consumer Discretionary Select Sector SPDR Fund
A24: SSEC (NEUTRAL) | B24: 3823 | C24: 3930 | D24: 3917
A25: Shanghai Composite
A26: NIKK (BULLISH) | B26: 49001 | C26: 51218 | D26: 50402
A27: Nikkei 225 Index
A28: DAX (BULLISH) | B28: 23912 | C28: 24398 | D28: 24288
A29: German DAX Composite
A30: VIX (BEARISH) | B30: 14.22 | C30: 17.29 | D30: 14.91
A31: Volatility Index
A32: USD (BEARISH) | B32: 98.01 | C32: 98.92 | D32: 98.45
A33: U.S. Dollar Index
A34: EUR/USD (BULLISH) | B34: 1.167 | C34: 1.18 | D34: 1.174
A35: Euro to U.S. Dollar
A36: USD/YEN (BULLISH) | B36: 155.54 | C36: 157.9 | D36: 157.41
A37: U.S. Dollar to Japanese Yen
A38: GBP/USD (BULLISH) | B38: 1.331 | C38: 1.346 | D38: 1.343
A39: British Pound to U.S. Dollar
A40: CAD/USD (BULLISH) | B40: 0.722 | C40: 0.729 | D40: 0.726
A41: Canadian Dollar to U.S. Dollar
A42: WTIC (BEARISH) | B42: 54.67 | C42: 58.16 | D42: 56.55
A43: Light Crude Oil Continuous Contract
A44: BRENT (BEARISH) | B44: 58.21 | C44: 62.03 | D44: 60.5
A45: Brent Crude Oil Continuous Contract
A46: NATGAS (NEUTRAL) | B46: 3.67 | C46: 4.63 | D46: 4.02
A47: Natural Gas Continuous Contract
A48: GOLD (BULLISH) | B48: 4290 | C48: 4426 | D48: 4407
A49: Gold Spot Price
A50: COPPER (BULLISH) | B50: 5.28 | C50: 5.5 | D50: 5.42
A51: Copper Continuous Contract
A52: SILVER (BULLISH) | B52: 64.04 | C52: 69.39 | D52: 67.21
A53: Silver Spot Price
A54: MSFT (BEARISH) | B54: 469 | C54: 492 | D54: 486
A55: Microsoft Corp.
A56: AAPL (BULLISH) | B56: 270 | C56: 282 | D56: 274
A57: Apple Inc.
A58: AMZN (NEUTRAL) | B58: 218 | C58: 232 | D58: 227
A59: Amazon Inc.
A60: META (BEARISH) | B60: 639 | C60: 675 | D60: 659
A61: Meta Platforms Inc.
A62: GOOGL (BULLISH) | B62: 296 | C62: 324 | D62: 307
A63: Alphabet Inc.
A64: NFLX (BEARISH) | B64: 90 | C64: 98 | D64: 94
A65: Netflix Inc.
A66: TSLA (BULLISH) | B66: 455 | C66: 501 | D66: 481
A67: Tesla Inc.
A68: NVDA (NEUTRAL) | B68: 169 | C68: 185 | D68: 181
A69: NVIDIA Corporation
A70: ORCL (BEARISH) | B70: 163 | C70: 208 | D70: 192
A71: Oracle Corporation
A72: BITCOIN (NEUTRAL) | B72: 85226 | C72: 91212 | D72: 90294
A73: Bitcoin Spot Price

Sheet Dec 23.2025
A1: INDEX | B1: BUY TRADE | C1: SELL TRADE | D1: PREV. CLOSE
A2: UST30Y (BULLISH) | B2: 4.87 | C2: 4.77 | D2: 4.84
A3: 30-Year U.S. Treasury Yield
A4: UST10Y (BEARISH) | B4: 4.2 | C4: 4.1 | D4: 4.16
A5: 10-Year U.S. Treasury Yield
A6: UST2Y (BEARISH) | B6: 3.55 | C6: 3.44 | D6: 3.52
A7: 2-Year U.S. Treasury Yield
A8: HYG (BULLISH) | B8: 80.15 | C8: 80.68 | D8: 80.43
A9: High Yield
A10: LQD (BULLISH) | B10: 109.7 | C10: 110.8 | D10: 110.1
A11: Investment Grade Corporate Bond ETF
A12: SPX (BULLISH) | B12: 6751 | C12: 6945 | D12: 6878
A13: S&P 500
A14: COMPQ (BULLISH) | B14: 22667 | C14: 23851 | D14: 23428
A15: NASDAQ Composite
A16: RUT (BULLISH) | B16: 2511 | C16: 2612 | D16: 2558
A17: Russell 2000
A18: XLK (BULLISH) | B18: 140 | C18: 149 | D18: 145
A19: Technology Select Sector SPDR Fund
A20: XLV (BULLISH) | B20: 152 | C20: 157 | D20: 155
A21: Health Care Select Sector SPDR Fund
A22: XLY (BULLISH) | B22: 120 | C22: 124 | D22: 122
A23: Consumer Discretionary Select Sector SPDR Fund
A24: SSEC (NEUTRAL) | B24: 3824 | C24: 3931 | D24: 3919
A25: Shanghai Composite
A26: NIKK (BULLISH) | B26: 49003 | C26: 51197 | D26: 50412
A27: Nikkei 225 Index
A28: DAX (BULLISH) | B28: 23914 | C28: 24443 | D28: 24283
A29: German DAX Composite
A30: VIX (BEARISH) | B30: 13.67 | C30: 17.16 | D30: 14.08
A31: Volatility Index
A32: USD (BEARISH) | B32: 97.61 | C32: 98.6 | D32: 97.88
A33: U.S. Dollar Index
A34: EUR/USD (BULLISH) | B34: 1.169 | C34: 1.182 | D34: 1.18
A35: Euro to U.S. Dollar
A36: USD/YEN (BULLISH) | B36: 154.98 | C36: 157.76 | D36: 155.97
A37: U.S. Dollar to Japanese Yen
A38: GBP/USD (BULLISH) | B38: 1.332 | C38: 1.352 | D38: 1.351
A39: British Pound to U.S. Dollar
A40: CAD/USD (BULLISH) | B40: 0.724 | C40: 0.731 | D40: 0.729
A41: Canadian Dollar to U.S. Dollar
A42: WTIC (BEARISH) | B42: 54.8 | C42: 58.98 | D42: 57.95
A43: Light Crude Oil Continuous Contract
A44: BRENT (BEARISH) | B44: 58.31 | C44: 62.65 | D44: 62.04
A45: Brent Crude Oil Continuous Contract
A46: NATGAS (NEUTRAL) | B46: 3.64 | C46: 4.49 | D46: 3.98
A47: Natural Gas Continuous Contract
A48: GOLD (BULLISH) | B48: 4328 | C48: 4511 | D48: 4484
A49: Gold Spot Price
A50: COPPER (BULLISH) | B50: 5.29 | C50: 5.55 | D50: 5.43
A51: Copper Continuous Contract
A52: SILVER (BULLISH) | B52: 64.97 | C52: 70.28 | D52: 69.03
A53: Silver Spot Price
A54: MSFT (BEARISH) | B54: 470 | C54: 490 | D54: 485
A55: Microsoft Corp.
A56: AAPL (BULLISH) | B56: 267 | C56: 281 | D56: 271
A57: Apple Inc.
A58: AMZN (NEUTRAL) | B58: 218 | C58: 234 | D58: 228
A59: Amazon Inc.
A60: META (BEARISH) | B60: 639 | C60: 676 | D60: 662
A61: Meta Platforms Inc.
A62: GOOGL (BULLISH) | B62: 296 | C62: 323 | D62: 310
A63: Alphabet Inc.
A64: NFLX (BEARISH) | B64: 90 | C64: 97 | D64: 93
A65: Netflix Inc.
A66: TSLA (BULLISH) | B66: 456 | C66: 505 | D66: 489
A67: Tesla Inc.
A68: NVDA (BULLISH) | B68: 170 | C68: 187 | D68: 184
A69: NVIDIA Corporation
A70: ORCL (BEARISH) | B70: 165 | C70: 209 | D70: 198
A71: Oracle Corporation
A72: BITCOIN (BEARISH) | B72: 85213 | C72: 90883 | D72: 87716
A73: Bitcoin Spot Price

Sheet Dec. 24.2025
A1: INDEX | B1: BUY TRADE | C1: SELL TRADE | D1: PREV. CLOSE
A2: UST30Y (BULLISH) | B2: 4.86 | C2: 4.78 | D2: 4.83
A3: 30-Year U.S. Treasury Yield
A4: UST10Y (BEARISH) | B4: 4.19 | C4: 4.11 | D4: 4.17
A5: 10-Year U.S. Treasury Yield
A6: UST2Y (BEARISH) | B6: 3.55 | C6: 3.43 | D6: 3.54
A7: 2-Year U.S. Treasury Yield
A8: HYG (BULLISH) | B8: 80.16 | C8: 80.67 | D8: 80.49
A9: High Yield
A10: LQD (BULLISH) | B10: 109.8 | C10: 110.7 | D10: 110.2
A11: Investment Grade Corporate Bond ETF
A12: SPX (BULLISH) | B12: 6803 | C12: 6954 | D12: 6909
A13: S&P 500
A14: COMPQ (BULLISH) | B14: 22771 | C14: 23852 | D14: 23561
A15: NASDAQ Composite
A16: RUT (BULLISH) | B16: 2501 | C16: 2603 | D16: 2541
A17: Russell 2000
A18: XLK (BULLISH) | B18: 140 | C18: 148 | D18: 146
A19: Technology Select Sector SPDR Fund
A20: XLV (BULLISH) | B20: 152 | C20: 157 | D20: 155
A21: Health Care Select Sector SPDR Fund
A22: XLY (BULLISH) | B22: 120 | C22: 124 | D22: 122
A23: Consumer Discretionary Select Sector SPDR Fund
A24: SSEC (NEUTRAL) | B24: 3826 | C24: 3964 | D24: 3940
A25: Shanghai Composite
A26: NIKK (BULLISH) | B26: 49005 | C26: 51165 | D26: 50344
A27: Nikkei 225 Index
A28: DAX (BULLISH) | B28: 24019 | C28: 24490 | D28: 24340
A29: German DAX Composite
A30: VIX (BEARISH) | B30: 13.15 | C30: 16.94 | D30: 14
A31: Volatility Index
A32: USD (BEARISH) | B32: 97.65 | C32: 98.59 | D32: 97.89
A33: U.S. Dollar Index
A34: EUR/USD (BULLISH) | B34: 1.171 | C34: 1.183 | D34: 1.179
A35: Euro to U.S. Dollar
A36: USD/YEN (BULLISH) | B36: 154.77 | C36: 157.68 | D36: 155.93
A37: U.S. Dollar to Japanese Yen
A38: GBP/USD (BULLISH) | B38: 1.334 | C38: 1.355 | D38: 1.351
A39: British Pound to U.S. Dollar
A40: CAD/USD (BULLISH) | B40: 0.724 | C40: 0.732 | D40: 0.731
A41: Canadian Dollar to U.S. Dollar
A42: WTIC (BEARISH) | B42: 54.79 | C42: 59.01 | D42: 58.49
A43: Light Crude Oil Continuous Contract
A44: BRENT (BEARISH) | B44: 58.8 | C44: 62.97 | D44: 62.46
A45: Brent Crude Oil Continuous Contract
A46: NATGAS (BULLISH) | B46: 3.81 | C46: 4.56 | D46: 4.4
A47: Natural Gas Continuous Contract
A48: GOLD (BULLISH) | B48: 4338 | C48: 4551 | D48: 4493
A49: Gold Spot Price
A50: COPPER (BULLISH) | B50: 5.28 | C50: 5.67 | D50: 5.48
A51: Copper Continuous Contract
A52: SILVER (BULLISH) | B52: 65.94 | C52: 72.67 | D52: 71.44
A53: Silver Spot Price
A54: MSFT (BEARISH) | B54: 471 | C54: 491 | D54: 487
A55: Microsoft Corp.
A56: AAPL (BULLISH) | B56: 268 | C56: 280 | D56: 272
A57: Apple Inc.
A58: AMZN (BULLISH) | B58: 221 | C58: 235 | D58: 232
A59: Amazon Inc.
A60: META (BEARISH) | B60: 640 | C60: 675 | D60: 665
A61: Meta Platforms Inc.
A62: GOOGL (BULLISH) | B62: 297 | C62: 323 | D62: 314
A63: Alphabet Inc.
A64: NFLX (BEARISH) | B64: 91 | C64: 96 | D64: 94
A65: Netflix Inc.
A66: TSLA (BULLISH) | B66: 457 | C66: 505 | D66: 486
A67: Tesla Inc.
A68: NVDA (BULLISH) | B68: 171 | C68: 192 | D68: 189
A69: NVIDIA Corporation
A70: ORCL (BEARISH) | B70: 172 | C70: 205 | D70: 195
A71: Oracle Corporation
A72: BITCOIN (BEARISH) | B72: 85494 | C72: 89997 | D72: 87337
A73: Bitcoin Spot Price

Sheet Dec 26. 2025
A1: INDEX | B1: BUY TRADE | C1: SELL TRADE | D1: PREV. CLOSE
A2: UST30Y (BULLISH) | B2: 4.85 | C2: 4.78 | D2: 4.8
A3: 30-Year U.S. Treasury Yield
A4: UST10Y (BEARISH) | B4: 4.19 | C4: 4.1 | D4: 4.14
A5: 10-Year U.S. Treasury Yield
A6: UST2Y (BEARISH) | B6: 3.54 | C6: 3.46 | D6: 3.51
A7: 2-Year U.S. Treasury Yield
A8: HYG (BULLISH) | B8: 80.18 | C8: 80.79 | D8: 80.64
A9: High Yield
A10: LQD (BULLISH) | B10: 109.9 | C10: 110.8 | D10: 110.7
A11: Investment Grade Corporate Bond ETF
A12: SPX (BULLISH) | B12: 6817 | C12: 6974 | D12: 6932
A13: S&P 500
A14: COMPQ (BULLISH) | B14: 22711 | C14: 23799 | D14: 23613
A15: NASDAQ Composite
A16: RUT (BULLISH) | B16: 2507 | C16: 2601 | D16: 2548
A17: Russell 2000
A18: XLK (BULLISH) | B18: 140 | C18: 149 | D18: 146
A19: Technology Select Sector SPDR Fund
A20: XLV (BULLISH) | B20: 152 | C20: 158 | D20: 156
A21: Health Care Select Sector SPDR Fund
A22: XLY (BULLISH) | B22: 121 | C22: 124 | D22: 123
A23: Consumer Discretionary Select Sector SPDR Fund
A24: SSEC (BULLISH) | B24: 3856 | C24: 3995 | D24: 3963
A25: Shanghai Composite
A26: NIKK (BULLISH) | B26: 49067 | C26: 51168 | D26: 50750
A27: Nikkei 225 Index
A28: DAX (BULLISH) | B28: 24021 | C28: 24474 | D28: 24340
A29: German DAX Composite
A30: VIX (BEARISH) | B30: 12.96 | C30: 16.61 | D30: 13.47
A31: Volatility Index
A32: USD (BEARISH) | B32: 97.61 | C32: 98.58 | D32: 98.04
A33: U.S. Dollar Index
A34: EUR/USD (BULLISH) | B34: 1.172 | C34: 1.182 | D34: 1.178
A35: Euro to U.S. Dollar
A36: USD/YEN (BULLISH) | B36: 154.79 | C36: 157.83 | D36: 156.43
A37: U.S. Dollar to Japanese Yen
A38: GBP/USD (BULLISH) | B38: 1.336 | C38: 1.357 | D38: 1.349
A39: British Pound to U.S. Dollar
A40: CAD/USD (BULLISH) | B40: 0.724 | C40: 0.734 | D40: 0.73
A41: Canadian Dollar to U.S. Dollar
A42: WTIC (BEARISH) | B42: 54.7 | C42: 59.21 | D42: 58.35
A43: Light Crude Oil Continuous Contract
A44: BRENT (BEARISH) | B44: 58.5 | C44: 63.24 | D44: 62.24
A45: Brent Crude Oil Continuous Contract
A46: NATGAS (BULLISH) | B46: 3.9 | C46: 4.54 | D46: 4.24
A47: Natural Gas Continuous Contract
A48: GOLD (BULLISH) | B48: 4380 | C48: 4534 | D48: 4513
A49: Gold Spot Price
A50: COPPER (BULLISH) | B50: 5.39 | C50: 5.77 | D50: 5.5
A51: Copper Continuous Contract
A52: SILVER (BULLISH) | B52: 66.98 | C52: 75.28 | D52: 71.94
A53: Silver Spot Price
A54: MSFT (BEARISH) | B54: 470 | C54: 493 | D54: 488
A55: Microsoft Corp.
A56: AAPL (BULLISH) | B56: 268 | C56: 279 | D56: 274
A57: Apple Inc.
A58: AMZN (BULLISH) | B58: 222 | C58: 237 | D58: 232
A59: Amazon Inc.
A60: META (BEARISH) | B60: 643 | C60: 676 | D60: 668
A61: Meta Platforms Inc.
A62: GOOGL (BULLISH) | B62: 298 | C62: 321 | D62: 314
A63: Alphabet Inc.
A64: NFLX (BEARISH) | B64: 91 | C64: 96 | D64: 94
A65: Netflix Inc.
A66: TSLA (BULLISH) | B66: 467 | C66: 503 | D66: 485
A67: Tesla Inc.
A68: NVDA (BULLISH) | B68: 179 | C68: 193 | D68: 189
A69: NVIDIA Corporation
A70: ORCL (BEARISH) | B70: 173 | C70: 204 | D70: 197
A71: Oracle Corporation
A72: BITCOIN (NEUTRAL) | B72: 85661 | C72: 90606 | D72: 88664
A73: Bitcoin Spot Price

Sheet Dec 29. 2025
A1: INDEX | B1: BUY TRADE | C1: SELL TRADE | D1: PREV. CLOSE
A2: UST30Y (BULLISH) | B2: 4.85 | C2: 4.76 | D2: 4.83
A3: 30-Year U.S. Treasury Yield
A4: UST10Y (BEARISH) | B4: 4.18 | C4: 4.09 | D4: 4.14
A5: 10-Year U.S. Treasury Yield
A6: UST2Y (BEARISH) | B6: 3.53 | C6: 3.44 | D6: 3.48
A7: 2-Year U.S. Treasury Yield
A8: HYG (BULLISH) | B8: 80.21 | C8: 80.82 | D8: 80.6
A9: High Yield
A10: LQD (BULLISH) | B10: 109.8 | C10: 111.1 | D10: 110.6
A11: Investment Grade Corporate Bond ETF
A12: SPX (BULLISH) | B12: 6826 | C12: 6986 | D12: 6929
A13: S&P 500
A14: COMPQ (BULLISH) | B14: 22741 | C14: 23892 | D14: 23593
A15: NASDAQ Composite
A16: RUT (BULLISH) | B16: 2504 | C16: 2577 | D16: 2534
A17: Russell 2000
A18: XLK (BULLISH) | B18: 140 | C18: 149 | D18: 147
A19: Technology Select Sector SPDR Fund
A20: XLV (BULLISH) | B20: 152 | C20: 158 | D20: 156
A21: Health Care Select Sector SPDR Fund
A22: XLY (BULLISH) | B22: 121 | C22: 124 | D22: 122
A23: Consumer Discretionary Select Sector SPDR Fund
A24: SSEC (BULLISH) | B24: 3858 | C24: 3999 | D24: 3965
A25: Shanghai Composite
A26: NIKK (BULLISH) | B26: 49069 | C26: 51178 | D26: 50526
A27: Nikkei 225 Index
A28: DAX (BULLISH) | B28: 24019 | C28: 24471 | D28: 24340
A29: German DAX Composite
A30: VIX (BEARISH) | B30: 12.18 | C30: 16.37 | D30: 13.6
A31: Volatility Index
A32: USD (BEARISH) | B32: 97.64 | C32: 98.61 | D32: 98.14
A33: U.S. Dollar Index
A34: EUR/USD (BULLISH) | B34: 1.171 | C34: 1.182 | D34: 1.176
A35: Euro to U.S. Dollar
A36: USD/YEN (BULLISH) | B36: 154.85 | C36: 157.76 | D36: 156.35
A37: U.S. Dollar to Japanese Yen
A38: GBP/USD (BULLISH) | B38: 1.336 | C38: 1.357 | D38: 1.348
A39: British Pound to U.S. Dollar
A40: CAD/USD (BULLISH) | B40: 0.725 | C40: 0.735 | D40: 0.73
A41: Canadian Dollar to U.S. Dollar
A42: WTIC (BEARISH) | B42: 55.18 | C42: 59.12 | D42: 56.9
A43: Light Crude Oil Continuous Contract
A44: BRENT (BEARISH) | B44: 58.51 | C44: 63.21 | D44: 60.85
A45: Brent Crude Oil Continuous Contract
A46: NATGAS (BULLISH) | B46: 3.94 | C46: 4.58 | D46: 4.4
A47: Natural Gas Continuous Contract
A48: GOLD (BULLISH) | B48: 4392 | C48: 4565 | D48: 4462
A49: Gold Spot Price
A50: COPPER (BULLISH) | B50: 5.42 | C50: 5.75 | D50: 5.61
A51: Copper Continuous Contract
A52: SILVER (BULLISH) | B52: 68.71 | C52: 79.67 | D52: 79.13
A53: Silver Spot Price
A54: MSFT (BEARISH) | B54: 471 | C54: 494 | D54: 488
A55: Microsoft Corp.
A56: AAPL (BULLISH) | B56: 269 | C56: 277 | D56: 273
A57: Apple Inc.
A58: AMZN (BULLISH) | B58: 221 | C58: 237 | D58: 233
A59: Amazon Inc.
A60: META (BEARISH) | B60: 644 | C60: 675 | D60: 663
A61: Meta Platforms Inc.
A62: GOOGL (BULLISH) | B62: 296 | C62: 322 | D62: 314
A63: Alphabet Inc.
A64: NFLX (BEARISH) | B64: 91 | C64: 96 | D64: 94
A65: Netflix Inc.
A66: TSLA (BULLISH) | B66: 465 | C66: 500 | D66: 475
A67: Tesla Inc.
A68: NVDA (BULLISH) | B68: 177 | C68: 193 | D68: 191
A69: NVIDIA Corporation
A70: ORCL (BEARISH) | B70: 174 | C70: 204 | D70: 198
A71: Oracle Corporation
A72: BITCOIN (NEUTRAL) | B72: 86012 | C72: 90001 | D72: 87302
A73: Bitcoin Spot Price

Sheet Dec 30. 2025
A1: INDEX | B1: BUY TRADE | C1: SELL TRADE | D1: PREV. CLOSE
A2: UST30Y (BULLISH) | B2: 4.84 | C2: 4.76 | D2: 4.8
A3: 30-Year U.S. Treasury Yield
A4: UST10Y (BEARISH) | B4: 4.17 | C4: 4.07 | D4: 4.11
A5: 10-Year U.S. Treasury Yield
A6: UST2Y (BEARISH) | B6: 3.52 | C6: 3.43 | D6: 3.44
A7: 2-Year U.S. Treasury Yield
A8: HYG (BULLISH) | B8: 80.29 | C8: 80.85 | D8: 80.63
A9: High Yield
A10: LQD (BULLISH) | B10: 109.9 | C10: 111.2 | D10: 110.8
A11: Investment Grade Corporate Bond ETF
A12: SPX (BULLISH) | B12: 6831 | C12: 6998 | D12: 6905
A13: S&P 500
A14: COMPQ (BULLISH) | B14: 22759 | C14: 23912 | D14: 23474
A15: NASDAQ Composite
A16: RUT (BULLISH) | B16: 2501 | C16: 2587 | D16: 2519
A17: Russell 2000
A18: XLK (BULLISH) | B18: 141 | C18: 150 | D18: 146
A19: Technology Select Sector SPDR Fund
A20: XLV (BULLISH) | B20: 153 | C20: 158 | D20: 156
A21: Health Care Select Sector SPDR Fund
A22: XLY (BULLISH) | B22: 120 | C22: 124 | D22: 121
A23: Consumer Discretionary Select Sector SPDR Fund
A24: SSEC (BULLISH) | B24: 3861 | C24: 3996 | D24: 3965
A25: Shanghai Composite
A26: NIKK (BULLISH) | B26: 49061 | C26: 51212 | D26: 50339
A27: Nikkei 225 Index
A28: DAX (BULLISH) | B28: 24022 | C28: 24472 | D28: 24351
A29: German DAX Composite
A30: VIX (BEARISH) | B30: 12.11 | C30: 17.15 | D30: 14.2
A31: Volatility Index
A32: USD (BEARISH) | B32: 97.57 | C32: 98.54 | D32: 98.08
A33: U.S. Dollar Index
A34: EUR/USD (BULLISH) | B34: 1.171 | C34: 1.182 | D34: 1.176
A35: Euro to U.S. Dollar
A36: USD/YEN (BULLISH) | B36: 154.99 | C36: 157.68 | D36: 155.99
A37: U.S. Dollar to Japanese Yen
A38: GBP/USD (BULLISH) | B38: 1.338 | C38: 1.357 | D38: 1.35
A39: British Pound to U.S. Dollar
A40: CAD/USD (BULLISH) | B40: 0.725 | C40: 0.735 | D40: 0.729
A41: Canadian Dollar to U.S. Dollar
A42: WTIC (BEARISH) | B42: 55.27 | C42: 59.19 | D42: 57.83
A43: Light Crude Oil Continuous Contract
A44: BRENT (BEARISH) | B44: 58.49 | C44: 63.08 | D44: 61.65
A45: Brent Crude Oil Continuous Contract
A46: NATGAS (NEUTRAL) | B46: 3.65 | C46: 4.41 | D46: 3.94
A47: Natural Gas Continuous Contract
A48: GOLD (BULLISH) | B48: 4286 | C48: 4551 | D48: 4392
A49: Gold Spot Price
A50: COPPER (BULLISH) | B50: 5.33 | C50: 5.75 | D50: 5.51
A51: Copper Continuous Contract
A52: SILVER (BULLISH) | B52: 69.78 | C52: 79.11 | D52: 72.15
A53: Silver Spot Price
A54: MSFT (BEARISH) | B54: 473 | C54: 493 | D54: 487
A55: Microsoft Corp.
A56: AAPL (BULLISH) | B56: 270 | C56: 278 | D56: 274
A57: Apple Inc.
A58: AMZN (BULLISH) | B58: 222 | C58: 238 | D58: 232
A59: Amazon Inc.
A60: META (BEARISH) | B60: 646 | C60: 673 | D60: 659
A61: Meta Platforms Inc.
A62: GOOGL (BULLISH) | B62: 297 | C62: 323 | D62: 314
A63: Alphabet Inc.
A64: NFLX (BEARISH) | B64: 92 | C64: 96 | D64: 94
A65: Netflix Inc.
A66: TSLA (BULLISH) | B66: 456 | C66: 501 | D66: 460
A67: Tesla Inc.
A68: NVDA (BULLISH) | B68: 179 | C68: 197 | D68: 188
A69: NVIDIA Corporation
A70: ORCL (BEARISH) | B70: 174 | C70: 203 | D70: 195
A71: Oracle Corporation
A72: BITCOIN (NEUTRAL) | B72: 86201 | C72: 88903 | D72: 87937
A73: Bitcoin Spot Price

Sheet Dec 31. 2025
A1: INDEX | B1: BUY TRADE | C1: SELL TRADE | D1: PREV. CLOSE
A2: UST30Y (BULLISH) | B2: 4.83 | C2: 4.75 | D2: 4.81
A3: 30-Year U.S. Treasury Yield
A4: UST10Y (BEARISH) | B4: 4.18 | C4: 4.09 | D4: 4.13
A5: 10-Year U.S. Treasury Yield
A6: UST2Y (BEARISH) | B6: 3.51 | C6: 3.42 | D6: 3.46
A7: 2-Year U.S. Treasury Yield
A8: HYG (BULLISH) | B8: 80.31 | C8: 80.89 | D8: 80.71
A9: High Yield
A10: LQD (BULLISH) | B10: 110.1 | C10: 111.3 | D10: 110.7
A11: Investment Grade Corporate Bond ETF
A12: SPX (BULLISH) | B12: 6836 | C12: 7011 | D12: 6896
A13: S&P 500
A14: COMPQ (BULLISH) | B14: 22796 | C14: 23941 | D14: 23419
A15: NASDAQ Composite
A16: RUT (BULLISH) | B16: 2485 | C16: 2590 | D16: 2500
A17: Russell 2000
A18: XLK (BULLISH) | B18: 141 | C18: 149 | D18: 145
A19: Technology Select Sector SPDR Fund
A20: XLV (BULLISH) | B20: 153 | C20: 158 | D20: 156
A21: Health Care Select Sector SPDR Fund
A22: XLY (BULLISH) | B22: 119 | C22: 123 | D22: 120
A23: Consumer Discretionary Select Sector SPDR Fund
A24: SSEC (BULLISH) | B24: 3875 | C24: 3999 | D24: 3968
A25: Shanghai Composite
A26: NIKK (BULLISH) | B26: 49145 | C26: 51261 | D26: 50339
A27: Nikkei 225 Index
A28: DAX (BULLISH) | B28: 24074 | C28: 24561 | D28: 24490
A29: German DAX Composite
A30: VIX (BEARISH) | B30: 12 | C30: 16.29 | D30: 14.33
A31: Volatility Index
A32: USD (BEARISH) | B32: 97.63 | C32: 98.6 | D32: 98.22
A33: U.S. Dollar Index
A34: EUR/USD (BULLISH) | B34: 1.17 | C34: 1.182 | D34: 1.175
A35: Euro to U.S. Dollar
A36: USD/YEN (BULLISH) | B36: 155.14 | C36: 157.71 | D36: 156.61
A37: U.S. Dollar to Japanese Yen
A38: GBP/USD (BULLISH) | B38: 1.337 | C38: 1.356 | D38: 1.346
A39: British Pound to U.S. Dollar
A40: CAD/USD (BULLISH) | B40: 0.724 | C40: 0.735 | D40: 0.73
A41: Canadian Dollar to U.S. Dollar
A42: WTIC (BEARISH) | B42: 55.51 | C42: 59.35 | D42: 57.95
A43: Light Crude Oil Continuous Contract
A44: BRENT (BEARISH) | B44: 59.3 | C44: 63.1 | D44: 61.35
A45: Brent Crude Oil Continuous Contract
A46: NATGAS (BEARISH) | B46: 3.62 | C46: 4.23 | D46: 3.97
A47: Natural Gas Continuous Contract
A48: GOLD (BULLISH) | B48: 4288 | C48: 4566 | D48: 4310
A49: Gold Spot Price
A50: COPPER (BULLISH) | B50: 5.36 | C50: 5.78 | D50: 5.7
A51: Copper Continuous Contract
A52: SILVER (BULLISH) | B52: 70.12 | C52: 79.66 | D52: 75.82
A53: Silver Spot Price
A54: MSFT (BEARISH) | B54: 474 | C54: 492 | D54: 487
A55: Microsoft Corp.
A56: AAPL (BULLISH) | B56: 270 | C56: 277 | D56: 273
A57: Apple Inc.
A58: AMZN (BULLISH) | B58: 223 | C58: 237 | D58: 233
A59: Amazon Inc.
A60: META (BEARISH) | B60: 649 | C60: 674 | D60: 666
A61: Meta Platforms Inc.
A62: GOOGL (BULLISH) | B62: 300 | C62: 323 | D62: 314
A63: Alphabet Inc.
A64: NFLX (BEARISH) | B64: 92 | C64: 95 | D64: 94
A65: Netflix Inc.
A66: TSLA (BULLISH) | B66: 450 | C66: 489 | D66: 454
A67: Tesla Inc.
A68: NVDA (BULLISH) | B68: 181 | C68: 198 | D68: 188
A69: NVIDIA Corporation
A70: ORCL (BEARISH) | B70: 175 | C70: 204 | D70: 197
A71: Oracle Corporation
A72: BITCOIN (NEUTRAL) | B72: 86713 | C72: 89150 | D72: 88863
A73: Bitcoin Spot Price

Sheet Jan 2. 2026
A1: INDEX | B1: BUY TRADE | C1: SELL TRADE | D1: PREV. CLOSE
A2: UST30Y (BULLISH) | B2: 4.87 | C2: 4.78 | D2: 4.85
A3: 30-Year U.S. Treasury Yield
A4: UST10Y (BEARISH) | B4: 4.19 | C4: 4.09 | D4: 4.17
A5: 10-Year U.S. Treasury Yield
A6: UST2Y (BEARISH) | B6: 3.52 | C6: 3.43 | D6: 3.48
A7: 2-Year U.S. Treasury Yield
A8: HYG (BULLISH) | B8: 80.34 | C8: 80.88 | D8: 80.63
A9: High Yield
A10: LQD (BULLISH) | B10: 110 | C10: 111.1 | D10: 110.2
A11: Investment Grade Corporate Bond ETF
A12: SPX (BULLISH) | B12: 6791 | C12: 6986 | D12: 6845
A13: S&P 500
A14: COMPQ (BULLISH) | B14: 23007 | C14: 23792 | D14: 23241
A15: NASDAQ Composite
A16: RUT (BULLISH) | B16: 2466 | C16: 2588 | D16: 2481
A17: Russell 2000
A18: XLK (BULLISH) | B18: 141 | C18: 148 | D18: 144
A19: Technology Select Sector SPDR Fund
A20: XLV (BULLISH) | B20: 153 | C20: 157 | D20: 155
A21: Health Care Select Sector SPDR Fund
A22: XLY (BULLISH) | B22: 118 | C22: 123 | D22: 119
A23: Consumer Discretionary Select Sector SPDR Fund
A24: SSEC (BULLISH) | B24: 3875 | C24: 3999 | D24: 3968
A25: Shanghai Composite
A26: NIKK (BULLISH) | B26: 49145 | C26: 51261 | D26: 50339
A27: Nikkei 225 Index
A28: DAX (BULLISH) | B28: 24084 | C28: 24621 | D28: 24490
A29: German DAX Composite
A30: VIX (BEARISH) | B30: 12.45 | C30: 17.11 | D30: 14.95
A31: Volatility Index
A32: USD (BEARISH) | B32: 97.67 | C32: 98.75 | D32: 98.45
A33: U.S. Dollar Index
A34: EUR/USD (BULLISH) | B34: 1.17 | C34: 1.181 | D34: 1.172
A35: Euro to U.S. Dollar
A36: USD/YEN (BULLISH) | B36: 155.46 | C36: 157.6 | D36: 156.98
A37: U.S. Dollar to Japanese Yen
A38: GBP/USD (BULLISH) | B38: 1.338 | C38: 1.354 | D38: 1.344
A39: British Pound to U.S. Dollar
A40: CAD/USD (BULLISH) | B40: 0.726 | C40: 0.734 | D40: 0.728
A41: Canadian Dollar to U.S. Dollar
A42: WTIC (BEARISH) | B42: 55.66 | C42: 58.78 | D42: 57.42
A43: Light Crude Oil Continuous Contract
A44: BRENT (BEARISH) | B44: 59.4 | C44: 62.48 | D44: 60.85
A45: Brent Crude Oil Continuous Contract
A46: NATGAS (BEARISH) | B46: 3.51 | C46: 4.19 | D46: 3.69
A47: Natural Gas Continuous Contract
A48: GOLD (BULLISH) | B48: 4291 | C48: 4567 | D48: 4322
A49: Gold Spot Price
A50: COPPER (BULLISH) | B50: 5.37 | C50: 5.81 | D50: 5.64
A51: Copper Continuous Contract
A52: SILVER (BULLISH) | B52: 68.99 | C52: 79.78 | D52: 71.26
A53: Silver Spot Price
A54: MSFT (BEARISH) | B54: 479 | C54: 490 | D54: 484
A55: Microsoft Corp.
A56: AAPL (BULLISH) | B56: 270 | C56: 276 | D56: 272
A57: Apple Inc.
A58: AMZN (BULLISH) | B58: 225 | C58: 236 | D58: 231
A59: Amazon Inc.
A60: META (BEARISH) | B60: 652 | C60: 674 | D60: 660
A61: Meta Platforms Inc.
A62: GOOGL (BULLISH) | B62: 301 | C62: 323 | D62: 313
A63: Alphabet Inc.
A64: NFLX (BEARISH) | B64: 92 | C64: 95 | D64: 94
A65: Netflix Inc.
A66: TSLA (BULLISH) | B66: 445 | C66: 489 | D66: 450
A67: Tesla Inc.
A68: NVDA (BULLISH) | B68: 180 | C68: 196 | D68: 187
A69: NVIDIA Corporation
A70: ORCL (BEARISH) | B70: 180 | C70: 205 | D70: 195
A71: Oracle Corporation
A72: BITCOIN (NEUTRAL) | B72: 86609 | C72: 90501 | D72: 89383
A73: Bitcoin Spot Price

Sheet Jan 5. 2026
A1: INDEX | B1: BUY TRADE | C1: SELL TRADE | D1: PREV. CLOSE
A2: UST30Y (BULLISH) | B2: 4.89 | C2: 4.79 | D2: 4.88
A3: 30-Year U.S. Treasury Yield
A4: UST10Y (BEARISH) | B4: 4.21 | C4: 4.09 | D4: 4.2
A5: 10-Year U.S. Treasury Yield
A6: UST2Y (BEARISH) | B6: 3.53 | C6: 3.43 | D6: 3.49
A7: 2-Year U.S. Treasury Yield
A8: HYG (BULLISH) | B8: 80.37 | C8: 80.89 | D8: 80.67
A9: High Yield
A10: LQD (BULLISH) | B10: 109.8 | C10: 111 | D10: 110.2
A11: Investment Grade Corporate Bond ETF
A12: SPX (BULLISH) | B12: 6802 | C12: 6966 | D12: 6858
A13: S&P 500
A14: COMPQ (BULLISH) | B14: 23017 | C14: 23723 | D14: 23235
A15: NASDAQ Composite
A16: RUT (BULLISH) | B16: 2485 | C16: 2581 | D16: 2508
A17: Russell 2000
A18: XLK (BULLISH) | B18: 142 | C18: 148 | D18: 144
A19: Technology Select Sector SPDR Fund
A20: XLV (BULLISH) | B20: 153 | C20: 157 | D20: 156
A21: Health Care Select Sector SPDR Fund
A22: XLY (BULLISH) | B22: 117 | C22: 122 | D22: 118
A23: Consumer Discretionary Select Sector SPDR Fund
A24: SSEC (BULLISH) | B24: 3898 | C24: 4033 | D24: 4023
A25: Shanghai Composite
A26: NIKK (BULLISH) | B26: 49155 | C26: 52002 | D26: 51832
A27: Nikkei 225 Index
A28: DAX (BULLISH) | B28: 24118 | C28: 24817 | D28: 24539
A29: German DAX Composite
A30: VIX (BEARISH) | B30: 13.06 | C30: 15.92 | D30: 14.51
A31: Volatility Index
A32: USD (BEARISH) | B32: 97.7 | C32: 98.79 | D32: 98.6
A33: U.S. Dollar Index
A34: EUR/USD (BULLISH) | B34: 1.167 | C34: 1.18 | D34: 1.168
A35: Euro to U.S. Dollar
A36: USD/YEN (BULLISH) | B36: 155.61 | C36: 157.66 | D36: 156.62
A37: U.S. Dollar to Japanese Yen
A38: GBP/USD (BULLISH) | B38: 1.339 | C38: 1.353 | D38: 1.347
A39: British Pound to U.S. Dollar
A40: CAD/USD (BULLISH) | B40: 0.724 | C40: 0.733 | D40: 0.726
A41: Canadian Dollar to U.S. Dollar
A42: WTIC (BEARISH) | B42: 56.06 | C42: 58.99 | D42: 57.32
A43: Light Crude Oil Continuous Contract
A44: BRENT (BEARISH) | B44: 59.69 | C44: 62.49 | D44: 60.79
A45: Brent Crude Oil Continuous Contract
A46: NATGAS (BEARISH) | B46: 3.32 | C46: 4.15 | D46: 3.64
A47: Natural Gas Continuous Contract
A48: GOLD (BULLISH) | B48: 4296 | C48: 4567 | D48: 4413
A49: Gold Spot Price
A50: COPPER (BULLISH) | B50: 5.47 | C50: 5.89 | D50: 5.65
A51: Copper Continuous Contract
A52: SILVER (BULLISH) | B52: 70.61 | C52: 79.21 | D52: 72.25
A53: Silver Spot Price
A54: MSFT (BEARISH) | B54: 470 | C54: 485 | D54: 473
A55: Microsoft Corp.
A56: AAPL (BULLISH) | B56: 270 | C56: 276 | D56: 271
A57: Apple Inc.
A58: AMZN (BULLISH) | B58: 224 | C58: 236 | D58: 227
A59: Amazon Inc.
A60: META (BEARISH) | B60: 648 | C60: 667 | D60: 650
A61: Meta Platforms Inc.
A62: GOOGL (BULLISH) | B62: 305 | C62: 323 | D62: 315
A63: Alphabet Inc.
A64: NFLX (BEARISH) | B64: 89 | C64: 94 | D64: 91
A65: Netflix Inc.
A66: TSLA (BULLISH) | B66: 431 | C66: 488 | D66: 438
A67: Tesla Inc.
A68: NVDA (BULLISH) | B68: 180 | C68: 196 | D68: 189
A69: NVIDIA Corporation
A70: ORCL (BEARISH) | B70: 181 | C70: 196 | D70: 196
A71: Oracle Corporation
A72: BITCOIN (NEUTRAL) | B72: 87501 | C72: 93158 | D72: 92851
A73: Bitcoin Spot Price

Sheet Jan 6. 2026
A1: INDEX | B1: BUY TRADE | C1: SELL TRADE | D1: PREV. CLOSE
A2: UST30Y (BULLISH) | B2: 4.9 | C2: 4.8 | D2: 4.86
A3: 30-Year U.S. Treasury Yield
A4: UST10Y (BEARISH) | B4: 4.19 | C4: 4.09 | D4: 4.17
A5: 10-Year U.S. Treasury Yield
A6: UST2Y (BEARISH) | B6: 3.5 | C6: 3.41 | D6: 3.46
A7: 2-Year U.S. Treasury Yield
A8: HYG (BULLISH) | B8: 80.41 | C8: 80.91 | D8: 80.88
A9: High Yield
A10: LQD (BULLISH) | B10: 109.7 | C10: 111 | D10: 110.5
A11: Investment Grade Corporate Bond ETF
A12: SPX (BULLISH) | B12: 6832 | C12: 6971 | D12: 6902
A13: S&P 500
A14: COMPQ (BULLISH) | B14: 23119 | C14: 23801 | D14: 23395
A15: NASDAQ Composite
A16: RUT (BULLISH) | B16: 2491 | C16: 2595 | D16: 2547
A17: Russell 2000
A18: XLK (BULLISH) | B18: 142 | C18: 148 | D18: 145
A19: Technology Select Sector SPDR Fund
A20: XLV (BULLISH) | B20: 153 | C20: 157 | D20: 155
A21: Health Care Select Sector SPDR Fund
A22: XLY (BULLISH) | B22: 118 | C22: 124 | D22: 120
A23: Consumer Discretionary Select Sector SPDR Fund
A24: SSEC (BULLISH) | B24: 3928 | C24: 4098 | D24: 4083
A25: Shanghai Composite
A26: NIKK (BULLISH) | B26: 50198 | C26: 52611 | D26: 52518
A27: Nikkei 225 Index
A28: DAX (BULLISH) | B28: 24172 | C28: 24908 | D28: 24868
A29: German DAX Composite
A30: VIX (BEARISH) | B30: 13.06 | C30: 15.84 | D30: 14.9
A31: Volatility Index
A32: USD (BEARISH) | B32: 97.81 | C32: 98.63 | D32: 98.41
A33: U.S. Dollar Index
A34: EUR/USD (BULLISH) | B34: 1.168 | C34: 1.179 | D34: 1.171
A35: Euro to U.S. Dollar
A36: USD/YEN (BULLISH) | B36: 155.6 | C36: 157.6 | D36: 156.37
A37: U.S. Dollar to Japanese Yen
A38: GBP/USD (BULLISH) | B38: 1.342 | C38: 1.356 | D38: 1.352
A39: British Pound to U.S. Dollar
A40: CAD/USD (BULLISH) | B40: 0.725 | C40: 0.734 | D40: 0.726
A41: Canadian Dollar to U.S. Dollar
A42: WTIC (BEARISH) | B42: 56.48 | C42: 59.12 | D42: 58.35
A43: Light Crude Oil Continuous Contract
A44: BRENT (BEARISH) | B44: 60.16 | C44: 62.95 | D44: 61.79
A45: Brent Crude Oil Continuous Contract
A46: NATGAS (BEARISH) | B46: 3.3 | C46: 4.14 | D46: 3.52
A47: Natural Gas Continuous Contract
A48: GOLD (BULLISH) | B48: 4306 | C48: 4576 | D48: 4463
A49: Gold Spot Price
A50: COPPER (BULLISH) | B50: 5.52 | C50: 5.98 | D50: 5.93
A51: Copper Continuous Contract
A52: SILVER (BULLISH) | B52: 73.35 | C52: 79.49 | D52: 76.09
A53: Silver Spot Price
A54: MSFT (BEARISH) | B54: 470 | C54: 484 | D54: 473
A55: Microsoft Corp.
A56: AAPL (BULLISH) | B56: 265 | C56: 277 | D56: 267
A57: Apple Inc.
A58: AMZN (BULLISH) | B58: 226 | C58: 238 | D58: 233
A59: Amazon Inc.
A60: META (BEARISH) | B60: 648 | C60: 671 | D60: 659
A61: Meta Platforms Inc.
A62: GOOGL (BULLISH) | B62: 308 | C62: 324 | D62: 317
A63: Alphabet Inc.
A64: NFLX (BEARISH) | B64: 88 | C64: 93 | D64: 91
A65: Netflix Inc.
A66: TSLA (BULLISH) | B66: 431 | C66: 490 | D66: 452
A67: Tesla Inc.
A68: NVDA (BULLISH) | B68: 182 | C68: 195 | D68: 188
A69: NVIDIA Corporation
A70: ORCL (BEARISH) | B70: 186 | C70: 199 | D70: 193
A71: Oracle Corporation
A72: BITCOIN (NEUTRAL) | B72: 89102 | C72: 94998 | D72: 93857
A73: Bitcoin Spot Price

Sheet Jan 7. 2026
A1: INDEX | B1: BUY TRADE | C1: SELL TRADE | D1: PREV. CLOSE
A2: UST30Y (BULLISH) | B2: 4.91 | C2: 4.8 | D2: 4.87
A3: 30-Year U.S. Treasury Yield
A4: UST10Y (BEARISH) | B4: 4.19 | C4: 4.09 | D4: 4.17
A5: 10-Year U.S. Treasury Yield
A6: UST2Y (BEARISH) | B6: 3.5 | C6: 3.41 | D6: 3.47
A7: 2-Year U.S. Treasury Yield
A8: HYG (BULLISH) | B8: 80.47 | C8: 80.99 | D8: 80.9
A9: High Yield
A10: LQD (BULLISH) | B10: 109.8 | C10: 111.1 | D10: 110.5
A11: Investment Grade Corporate Bond ETF
A12: SPX (BULLISH) | B12: 6850 | C12: 6984 | D12: 6944
A13: S&P 500
A14: COMPQ (BULLISH) | B14: 23201 | C14: 23822 | D14: 23547
A15: NASDAQ Composite
A16: RUT (BULLISH) | B16: 2515 | C16: 2601 | D16: 2582
A17: Russell 2000
A18: XLK (BULLISH) | B18: 143 | C18: 148 | D18: 147
A19: Technology Select Sector SPDR Fund
A20: XLV (BULLISH) | B20: 154 | C20: 159 | D20: 158
A21: Health Care Select Sector SPDR Fund
A22: XLI (BULLISH) | B22: 156 | C22: 164 | D22: 162.02
A23: Industrial Select Sector SPDR Fund
A24: SSEC (BULLISH) | B24: 3939 | C24: 4093 | D24: 4085
A25: Shanghai Composite
A26: NIKK (BULLISH) | B26: 50316 | C26: 52608 | D26: 51961
A27: Nikkei 225 Index
A28: DAX (BULLISH) | B28: 24215 | C28: 25049 | D28: 24892
A29: German DAX Composite
A30: VIX (BEARISH) | B30: 13.09 | C30: 15.74 | D30: 14.75
A31: Volatility Index
A32: USD (NEUTRAL) | B32: 97.97 | C32: 98.75 | D32: 98.61
A33: U.S. Dollar Index
A34: EUR/USD (NEUTRAL) | B34: 1.166 | C34: 1.176 | D34: 1.168
A35: Euro to U.S. Dollar
A36: USD/YEN (BULLISH) | B36: 155.9 | C36: 157.21 | D36: 156.54
A37: U.S. Dollar to Japanese Yen
A38: GBP/USD (BULLISH) | B38: 1.343 | C38: 1.354 | D38: 1.349
A39: British Pound to U.S. Dollar
A40: CAD/USD (BULLISH) | B40: 0.723 | C40: 0.734 | D40: 0.724
A41: Canadian Dollar to U.S. Dollar
A42: WTIC (BEARISH) | B42: 55.67 | C42: 58.32 | D42: 56.97
A43: Light Crude Oil Continuous Contract
A44: BRENT (BEARISH) | B44: 59.83 | C44: 61.96 | D44: 60.53
A45: Brent Crude Oil Continuous Contract
A46: NATGAS (BEARISH) | B46: 3.25 | C46: 4.05 | D46: 3.42
A47: Natural Gas Continuous Contract
A48: GOLD (BULLISH) | B48: 4319 | C48: 4590 | D48: 4453
A49: Gold Spot Price
A50: COPPER (BULLISH) | B50: 5.59 | C50: 6.05 | D50: 6.01
A51: Copper Continuous Contract
A52: SILVER (BULLISH) | B52: 74.48 | C52: 81.97 | D52: 81.44
A53: Silver Spot Price
A54: MSFT (BEARISH) | B54: 469 | C54: 486 | D54: 479
A55: Microsoft Corp.
A56: AAPL (NEUTRAL) | B56: 260 | C56: 273 | D56: 262
A57: Apple Inc.
A58: AMZN (BULLISH) | B58: 229 | C58: 243 | D58: 241
A59: Amazon Inc.
A60: META (BEARISH) | B60: 649 | C60: 672 | D60: 661
A61: Meta Platforms Inc.
A62: GOOGL (BULLISH) | B62: 310 | C62: 321 | D62: 314
A63: Alphabet Inc.
A64: NFLX (BEARISH) | B64: 88 | C64: 93 | D64: 91
A65: Netflix Inc.
A66: TSLA (NEUTRAL) | B66: 421 | C66: 459 | D66: 433
A67: Tesla Inc.
A68: NVDA (BULLISH) | B68: 183 | C68: 194 | D68: 187
A69: NVIDIA Corporation
A70: ORCL (BEARISH) | B70: 189 | C70: 199 | D70: 194
A71: Oracle Corporation
A72: BITCOIN (NEUTRAL) | B72: 87422 | C72: 94924 | D72: 91947
A73: Bitcoin Spot Price

Sheet Jan 8. 2026
A1: INDEX | B1: BUY TRADE | C1: SELL TRADE | D1: PREV. CLOSE
A2: UST30Y (BULLISH) | B2: 4.91 | C2: 4.81 | D2: 4.84
A3: 30-Year U.S. Treasury Yield
A4: UST10Y (BEARISH) | B4: 4.2 | C4: 4.1 | D4: 4.16
A5: 10-Year U.S. Treasury Yield
A6: UST2Y (BEARISH) | B6: 3.5 | C6: 3.43 | D6: 3.48
A7: 2-Year U.S. Treasury Yield
A8: HYG (BULLISH) | B8: 80.51 | C8: 81.03 | D8: 80.88
A9: High Yield
A10: LQD (BULLISH) | B10: 109.9 | C10: 111 | D10: 110.6
A11: Investment Grade Corporate Bond ETF
A12: SPX (BULLISH) | B12: 6855 | C12: 6977 | D12: 6920
A13: S&P 500
A14: COMPQ (BULLISH) | B14: 23192 | C14: 23749 | D14: 23584
A15: NASDAQ Composite
A16: RUT (BULLISH) | B16: 2526 | C16: 2603 | D16: 2575
A17: Russell 2000
A18: XLK (BULLISH) | B18: 143 | C18: 148 | D18: 147
A19: Technology Select Sector SPDR Fund
A20: XLV (BULLISH) | B20: 155 | C20: 161 | D20: 160
A21: Health Care Select Sector SPDR Fund
A22: XLI (BULLISH) | B22: 156 | C22: 163 | D22: 158.97
A23: Industrial Select Sector SPDR Fund
A24: SSEC (BULLISH) | B24: 3950 | C24: 4101 | D24: 4082
A25: Shanghai Composite
A26: NIKK (BULLISH) | B26: 50494 | C26: 52631 | D26: 51117
A27: Nikkei 225 Index
A28: DAX (BULLISH) | B28: 24280 | C28: 25199 | D28: 25122
A29: German DAX Composite
A30: VIX (BEARISH) | B30: 13.17 | C30: 15.93 | D30: 15.38
A31: Volatility Index
A32: USD (NEUTRAL) | B32: 97.99 | C32: 98.98 | D32: 98.79
A33: U.S. Dollar Index
A34: EUR/USD (NEUTRAL) | B34: 1.164 | C34: 1.174 | D34: 1.167
A35: Euro to U.S. Dollar
A36: USD/YEN (BULLISH) | B36: 155.91 | C36: 157.27 | D36: 156.72
A37: U.S. Dollar to Japanese Yen
A38: GBP/USD (BULLISH) | B38: 1.342 | C38: 1.353 | D38: 1.344
A39: British Pound to U.S. Dollar
A40: CAD/USD (BULLISH) | B40: 0.72 | C40: 0.734 | D40: 0.721
A41: Canadian Dollar to U.S. Dollar
A42: WTIC (BEARISH) | B42: 56.01 | C42: 57.92 | D42: 56.4
A43: Light Crude Oil Continuous Contract
A44: BRENT (BEARISH) | B44: 59.8 | C44: 61.77 | D44: 60.34
A45: Brent Crude Oil Continuous Contract
A46: NATGAS (BEARISH) | B46: 3.22 | C46: 4.01 | D46: 3.56
A47: Natural Gas Continuous Contract
A48: GOLD (BULLISH) | B48: 4329 | C48: 4585 | D48: 4422
A49: Gold Spot Price
A50: COPPER (BULLISH) | B50: 5.53 | C50: 6.06 | D50: 5.8
A51: Copper Continuous Contract
A52: SILVER (BULLISH) | B52: 74.54 | C52: 82.75 | D52: 78.28
A53: Silver Spot Price
A54: MSFT (BEARISH) | B54: 469 | C54: 488 | D54: 483
A55: Microsoft Corp.
A56: AAPL (BEARISH) | B56: 257 | C56: 269 | D56: 260
A57: Apple Inc.
A58: AMZN (BULLISH) | B58: 232 | C58: 244 | D58: 242
A59: Amazon Inc.
A60: META (BEARISH) | B60: 645 | C60: 667 | D60: 649
A61: Meta Platforms Inc.
A62: GOOGL (BULLISH) | B62: 311 | C62: 323 | D62: 322
A63: Alphabet Inc.
A64: NFLX (BEARISH) | B64: 88 | C64: 96 | D64: 91
A65: Netflix Inc.
A66: TSLA (BEARISH) | B66: 416 | C66: 453 | D66: 431
A67: Tesla Inc.
A68: NVDA (BULLISH) | B68: 185 | C68: 193 | D68: 189
A69: NVIDIA Corporation
A70: ORCL (BEARISH) | B70: 189 | C70: 199 | D70: 193
A71: Oracle Corporation
A72: BITCOIN (NEUTRAL) | B72: 86991 | C72: 94852 | D72: 89804
A73: Bitcoin Spot Price

Sheet Jan 9. 2026
A1: INDEX | B1: BUY TRADE | C1: SELL TRADE | D1: PREV. CLOSE
A2: UST30Y (BULLISH) | B2: 4.92 | C2: 4.82 | D2: 4.84
A3: 30-Year U.S. Treasury Yield
A4: UST10Y (BEARISH) | B4: 4.22 | C4: 4.1 | D4: 4.18
A5: 10-Year U.S. Treasury Yield
A6: UST2Y (BEARISH) | B6: 3.52 | C6: 3.43 | D6: 3.49
A7: 2-Year U.S. Treasury Yield
A8: HYG (BULLISH) | B8: 80.55 | C8: 81.09 | D8: 80.94
A9: High Yield
A10: LQD (BULLISH) | B10: 109.9 | C10: 110.9 | D10: 110.2
A11: Investment Grade Corporate Bond ETF
A12: SPX (BULLISH) | B12: 6861 | C12: 6984 | D12: 6921
A13: S&P 500
A14: COMPQ (BULLISH) | B14: 23200 | C14: 23782 | D14: 23480
A15: NASDAQ Composite
A16: RUT (BULLISH) | B16: 2553 | C16: 2626 | D16: 2603
A17: Russell 2000
A18: XLK (BULLISH) | B18: 142 | C18: 147 | D18: 144
A19: Technology Select Sector SPDR Fund
A20: XLV (BULLISH) | B20: 155 | C20: 160 | D20: 158
A21: Health Care Select Sector SPDR Fund
A22: XLI (BULLISH) | B22: 157 | C22: 164 | D22: 160.17
A23: Industrial Select Sector SPDR Fund
A24: SSEC (BULLISH) | B24: 4010 | C24: 4131 | D24: 4120
A25: Shanghai Composite
A26: NIKK (BULLISH) | B26: 50522 | C26: 52643 | D26: 51939
A27: Nikkei 225 Index
A28: DAX (BULLISH) | B28: 24340 | C28: 25314 | D28: 25127
A29: German DAX Composite
A30: VIX (BEARISH) | B30: 13.37 | C30: 15.98 | D30: 15.45
A31: Volatility Index
A32: USD (BULLISH) | B32: 97.99 | C32: 99.21 | D32: 99.07
A33: U.S. Dollar Index
A34: EUR/USD (BEARISH) | B34: 1.161 | C34: 1.172 | D34: 1.164
A35: Euro to U.S. Dollar
A36: USD/YEN (BULLISH) | B36: 156.45 | C36: 157.96 | D36: 157.69
A37: U.S. Dollar to Japanese Yen
A38: GBP/USD (BULLISH) | B38: 1.337 | C38: 1.353 | D38: 1.341
A39: British Pound to U.S. Dollar
A40: CAD/USD (NEUTRAL) | B40: 0.717 | C40: 0.732 | D40: 0.72
A41: Canadian Dollar to U.S. Dollar
A42: WTIC (BEARISH) | B42: 55.88 | C42: 58.99 | D42: 58.4
A43: Light Crude Oil Continuous Contract
A44: BRENT (BEARISH) | B44: 59.97 | C44: 62.98 | D44: 62.75
A45: Brent Crude Oil Continuous Contract
A46: NATGAS (BEARISH) | B46: 3.2 | C46: 3.97 | D46: 3.42
A47: Natural Gas Continuous Contract
A48: GOLD (BULLISH) | B48: 4340 | C48: 4582 | D48: 4466
A49: Gold Spot Price
A50: COPPER (BULLISH) | B50: 5.56 | C50: 6.08 | D50: 5.75
A51: Copper Continuous Contract
A52: SILVER (BULLISH) | B52: 74.97 | C52: 82.71 | D52: 76.96
A53: Silver Spot Price
A54: MSFT (BEARISH) | B54: 468 | C54: 488 | D54: 478
A55: Microsoft Corp.
A56: AAPL (BEARISH) | B56: 254 | C56: 268 | D56: 259
A57: Apple Inc.
A58: AMZN (BULLISH) | B58: 234 | C58: 249 | D58: 246
A59: Amazon Inc.
A60: META (BEARISH) | B60: 641 | C60: 660 | D60: 646
A61: Meta Platforms Inc.
A62: GOOGL (BULLISH) | B62: 311 | C62: 329 | D62: 325
A63: Alphabet Inc.
A64: NFLX (BEARISH) | B64: 88 | C64: 95 | D64: 91
A65: Netflix Inc.
A66: TSLA (BEARISH) | B66: 418 | C66: 459 | D66: 436
A67: Tesla Inc.
A68: NVDA (BULLISH) | B68: 183 | C68: 192 | D68: 185
A69: NVIDIA Corporation
A70: ORCL (BEARISH) | B70: 186 | C70: 198 | D70: 190
A71: Oracle Corporation
A72: BITCOIN (NEUTRAL) | B72: 88104 | C72: 94798 | D72: 90346
A73: Bitcoin Spot Price

Sheet Jan 12. 2026
A1: INDEX | B1: BUY TRADE | C1: SELL TRADE | D1: PREV. CLOSE
A2: UST30Y (BULLISH) | B2: 4.9 | C2: 4.81 | D2: 4.82
A3: 30-Year U.S. Treasury Yield
A4: UST10Y (BEARISH) | B4: 4.22 | C4: 4.1 | D4: 4.18
A5: 10-Year U.S. Treasury Yield
A6: UST2Y (BEARISH) | B6: 3.55 | C6: 3.43 | D6: 3.54
A7: 2-Year U.S. Treasury Yield
A8: HYG (BULLISH) | B8: 80.58 | C8: 81.11 | D8: 81
A9: High Yield
A10: LQD (BULLISH) | B10: 109.9 | C10: 111 | D10: 110.6
A11: Investment Grade Corporate Bond ETF
A12: SPX (BULLISH) | B12: 6867 | C12: 6990 | D12: 6966
A13: S&P 500
A14: COMPQ (BULLISH) | B14: 23184 | C14: 23795 | D14: 23671
A15: NASDAQ Composite
A16: RUT (BULLISH) | B16: 2537 | C16: 2645 | D16: 2624
A17: Russell 2000
A18: XLK (BULLISH) | B18: 142 | C18: 147 | D18: 146
A19: Technology Select Sector SPDR Fund
A20: XLV (BULLISH) | B20: 154 | C20: 160 | D20: 157
A21: Health Care Select Sector SPDR Fund
A22: XLI (BULLISH) | B22: 157 | C22: 164 | D22: 161.93
A23: Industrial Select Sector SPDR Fund
A24: SSEC (BULLISH) | B24: 3980 | C24: 4177 | D24: 4165
A25: Shanghai Composite
A26: NIKK (BULLISH) | B26: 50602 | C26: 52799 | D26: 51939
A27: Nikkei 225 Index
A28: DAX (BULLISH) | B28: 24404 | C28: 25496 | D28: 25261
A29: German DAX Composite
A30: VIX (BEARISH) | B30: 13.37 | C30: 15.98 | D30: 14.49
A31: Volatility Index
A32: USD (NEUTRAL) | B32: 97.12 | C32: 99.3 | D32: 98.77
A33: U.S. Dollar Index
A34: EUR/USD (NEUTRAL) | B34: 1.161 | C34: 1.174 | D34: 1.169
A35: Euro to U.S. Dollar
A36: USD/YEN (BULLISH) | B36: 156.48 | C36: 157.99 | D36: 157.83
A37: U.S. Dollar to Japanese Yen
A38: GBP/USD (BULLISH) | B38: 1.339 | C38: 1.354 | D38: 1.347
A39: British Pound to U.S. Dollar
A40: CAD/USD (NEUTRAL) | B40: 0.717 | C40: 0.729 | D40: 0.72
A41: Canadian Dollar to U.S. Dollar
A42: WTIC (BEARISH) | B42: 55.99 | C42: 59.26 | D42: 58.78
A43: Light Crude Oil Continuous Contract
A44: BRENT (BEARISH) | B44: 59.98 | C44: 63.24 | D44: 63.03
A45: Brent Crude Oil Continuous Contract
A46: NATGAS (BEARISH) | B46: 3.03 | C46: 3.88 | D46: 3.14
A47: Natural Gas Continuous Contract
A48: GOLD (BULLISH) | B48: 4351 | C48: 4612 | D48: 4585
A49: Gold Spot Price
A50: COPPER (BULLISH) | B50: 5.57 | C50: 6.09 | D50: 5.84
A51: Copper Continuous Contract
A52: SILVER (BULLISH) | B52: 76.11 | C52: 84.67 | D52: 79.34
A53: Silver Spot Price
A54: MSFT (BEARISH) | B54: 467 | C54: 488 | D54: 479
A55: Microsoft Corp.
A56: AAPL (BEARISH) | B56: 252 | C56: 268 | D56: 259
A57: Apple Inc.
A58: AMZN (BULLISH) | B58: 234 | C58: 251 | D58: 247
A59: Amazon Inc.
A60: META (BEARISH) | B60: 641 | C60: 668 | D60: 653
A61: Meta Platforms Inc.
A62: GOOGL (BULLISH) | B62: 313 | C62: 331 | D62: 329
A63: Alphabet Inc.
A64: NFLX (BEARISH) | B64: 87 | C64: 94 | D64: 89
A65: Netflix Inc.
A66: TSLA (NEUTRAL) | B66: 422 | C66: 458 | D66: 445
A67: Tesla Inc.
A68: NVDA (BULLISH) | B68: 182 | C68: 192 | D68: 185
A69: NVIDIA Corporation
A70: ORCL (BEARISH) | B70: 186 | C70: 201 | D70: 199
A71: Oracle Corporation
A72: BITCOIN (NEUTRAL) | B72: 88790 | C72: 94417 | D72: 90682
A73: Bitcoin Spot Price

Sheet Jan 13. 2026
A1: INDEX | B1: BUY TRADE | C1: SELL TRADE | D1: PREV. CLOSE
A2: UST30Y (BULLISH) | B2: 4.9 | C2: 4.81 | D2: 4.83
A3: 30-Year U.S. Treasury Yield
A4: UST10Y (BEARISH) | B4: 4.22 | C4: 4.12 | D4: 4.18
A5: 10-Year U.S. Treasury Yield
A6: UST2Y (BEARISH) | B6: 3.57 | C6: 3.43 | D6: 3.54
A7: 2-Year U.S. Treasury Yield
A8: HYG (BULLISH) | B8: 80.65 | C8: 81.19 | D8: 81.04
A9: High Yield
A10: LQD (BULLISH) | B10: 110 | C10: 111 | D10: 110.5
A11: Investment Grade Corporate Bond ETF
A12: SPX (BULLISH) | B12: 6873 | C12: 7019 | D12: 6977
A13: S&P 500
A14: COMPQ (BULLISH) | B14: 23201 | C14: 23907 | D14: 23733
A15: NASDAQ Composite
A16: RUT (BULLISH) | B16: 2548 | C16: 2687 | D16: 2635
A17: Russell 2000
A18: XLK (BULLISH) | B18: 143 | C18: 148 | D18: 147
A19: Technology Select Sector SPDR Fund
A20: XLV (BULLISH) | B20: 154 | C20: 160 | D20: 157
A21: Health Care Select Sector SPDR Fund
A22: XLI (BULLISH) | B22: 158 | C22: 166 | D22: 163.17
A23: Industrial Select Sector SPDR Fund
A24: SSEC (BULLISH) | B24: 4031 | C24: 4198 | D24: 4138
A25: Shanghai Composite
A26: NIKK (BULLISH) | B26: 50702 | C26: 53601 | D26: 53549
A27: Nikkei 225 Index
A28: DAX (BULLISH) | B28: 24497 | C28: 25598 | D28: 25405
A29: German DAX Composite
A30: VIX (BEARISH) | B30: 13.48 | C30: 15.92 | D30: 15.12
A31: Volatility Index
A32: USD (BULLISH) | B32: 98.22 | C32: 99.37 | D32: 99
A33: U.S. Dollar Index
A34: EUR/USD (BEARISH) | B34: 1.16 | C34: 1.173 | D34: 1.166
A35: Euro to U.S. Dollar
A36: USD/YEN (BULLISH) | B36: 156.86 | C36: 158.98 | D36: 158.92
A37: U.S. Dollar to Japanese Yen
A38: GBP/USD (BULLISH) | B38: 1.339 | C38: 1.353 | D38: 1.346
A39: British Pound to U.S. Dollar
A40: CAD/USD (BEARISH) | B40: 0.715 | C40: 0.726 | D40: 0.72
A41: Canadian Dollar to U.S. Dollar
A42: WTIC (NEUTRAL) | B42: 55.73 | C42: 60.74 | D42: 59.5
A43: Light Crude Oil Continuous Contract
A44: BRENT (NEUTRAL) | B44: 59.99 | C44: 64.96 | D44: 63.87
A45: Brent Crude Oil Continuous Contract
A46: NATGAS (BEARISH) | B46: 3.05 | C46: 3.87 | D46: 3.36
A47: Natural Gas Continuous Contract
A48: GOLD (BULLISH) | B48: 4387 | C48: 4624 | D48: 4584
A49: Gold Spot Price
A50: COPPER (BULLISH) | B50: 5.59 | C50: 6.11 | D50: 5.94
A51: Copper Continuous Contract
A52: SILVER (BULLISH) | B52: 77.16 | C52: 85.92 | D52: 83.94
A53: Silver Spot Price
A54: MSFT (BEARISH) | B54: 467 | C54: 485 | D54: 477
A55: Microsoft Corp.
A56: AAPL (BEARISH) | B56: 252 | C56: 269 | D56: 260
A57: Apple Inc.
A58: AMZN (BULLISH) | B58: 235 | C58: 253 | D58: 246
A59: Amazon Inc.
A60: META (BEARISH) | B60: 638 | C60: 661 | D60: 642
A61: Meta Platforms Inc.
A62: GOOGL (BULLISH) | B62: 315 | C62: 335 | D62: 332
A63: Alphabet Inc.
A64: NFLX (BEARISH) | B64: 87 | C64: 93 | D64: 89
A65: Netflix Inc.
A66: TSLA (BULLISH) | B66: 425 | C66: 460 | D66: 449
A67: Tesla Inc.
A68: NVDA (BULLISH) | B68: 182 | C68: 190 | D68: 185
A69: NVIDIA Corporation
A70: ORCL (BEARISH) | B70: 184 | C70: 208 | D70: 205
A71: Oracle Corporation
A72: BITCOIN (NEUTRAL) | B72: 89314 | C72: 94581 | D72: 92005
A73: Bitcoin Spot Price

Sheet Jan 14. 2026
A1: INDEX | B1: BUY TRADE | C1: SELL TRADE | D1: PREV. CLOSE
A2: UST30Y (BULLISH) | B2: 4.87 | C2: 4.81 | D2: 4.84
A3: 30-Year U.S. Treasury Yield
A4: UST10Y (BEARISH) | B4: 4.19 | C4: 4.12 | D4: 4.18
A5: 10-Year U.S. Treasury Yield
A6: UST2Y (BEARISH) | B6: 3.55 | C6: 3.43 | D6: 3.55
A7: 2-Year U.S. Treasury Yield
A8: HYG (BULLISH) | B8: 80.67 | C8: 81.25 | D8: 81.04
A9: High Yield
A10: LQD (BULLISH) | B10: 110.2 | C10: 111.1 | D10: 110.8
A11: Investment Grade Corporate Bond ETF
A12: SPX (BULLISH) | B12: 6882 | C12: 7025 | D12: 6963
A13: S&P 500
A14: COMPQ (BULLISH) | B14: 23405 | C14: 23906 | D14: 23709
A15: NASDAQ Composite
A16: RUT (BULLISH) | B16: 2555 | C16: 2683 | D16: 2633
A17: Russell 2000
A18: XLK (BULLISH) | B18: 142 | C18: 148 | D18: 146
A19: Technology Select Sector SPDR Fund
A20: XLV (BULLISH) | B20: 154 | C20: 160 | D20: 157
A21: Health Care Select Sector SPDR Fund
A22: XLI (BULLISH) | B22: 158 | C22: 166 | D22: 164
A23: Industrial Select Sector SPDR Fund
A24: SSEC (BULLISH) | B24: 3999 | C24: 4214 | D24: 4126
A25: Shanghai Composite
A26: NIKK (BULLISH) | B26: 51515 | C26: 54574 | D26: 54341
A27: Nikkei 225 Index
A28: DAX (BULLISH) | B28: 24544 | C28: 25671 | D28: 25420
A29: German DAX Composite
A30: VIX (BEARISH) | B30: 13.85 | C30: 16.35 | D30: 15.98
A31: Volatility Index
A32: USD (BULLISH) | B32: 98.24 | C32: 99.43 | D32: 99.03
A33: U.S. Dollar Index
A34: EUR/USD (BEARISH) | B34: 1.161 | C34: 1.173 | D34: 1.165
A35: Euro to U.S. Dollar
A36: USD/YEN (BULLISH) | B36: 156.93 | C36: 159.48 | D36: 158.56
A37: U.S. Dollar to Japanese Yen
A38: GBP/USD (BULLISH) | B38: 1.337 | C38: 1.352 | D38: 1.345
A39: British Pound to U.S. Dollar
A40: CAD/USD (BEARISH) | B40: 0.715 | C40: 0.724 | D40: 0.72
A41: Canadian Dollar to U.S. Dollar
A42: WTIC (BULLISH) | B42: 56.74 | C42: 61.81 | D42: 61.15
A43: Light Crude Oil Continuous Contract
A44: BRENT (BULLISH) | B44: 60.51 | C44: 66.11 | D44: 65.47
A45: Brent Crude Oil Continuous Contract
A46: NATGAS (BEARISH) | B46: 3.1 | C46: 3.84 | D46: 3.42
A47: Natural Gas Continuous Contract
A48: GOLD (BULLISH) | B48: 4407 | C48: 4671 | D48: 4586
A49: Gold Spot Price
A50: COPPER (BULLISH) | B50: 5.64 | C50: 6.15 | D50: 5.97
A51: Copper Continuous Contract
A52: SILVER (BULLISH) | B52: 78.92 | C52: 91.23 | D52: 88.09
A53: Silver Spot Price
A54: MSFT (BEARISH) | B54: 466 | C54: 485 | D54: 471
A55: Microsoft Corp.
A56: AAPL (BEARISH) | B56: 253 | C56: 268 | D56: 261
A57: Apple Inc.
A58: AMZN (BULLISH) | B58: 234 | C58: 254 | D58: 243
A59: Amazon Inc.
A60: META (BEARISH) | B60: 629 | C60: 653 | D60: 631
A61: Meta Platforms Inc.
A62: GOOGL (BULLISH) | B62: 322 | C62: 341 | D62: 336
A63: Alphabet Inc.
A64: NFLX (BEARISH) | B64: 87 | C64: 93 | D64: 90
A65: Netflix Inc.
A66: TSLA (BULLISH) | B66: 430 | C66: 458 | D66: 447
A67: Tesla Inc.
A68: NVDA (BULLISH) | B68: 183 | C68: 191 | D68: 186
A69: NVIDIA Corporation
A70: ORCL (BEARISH) | B70: 185 | C70: 207 | D70: 202
A71: Oracle Corporation
A72: BITCOIN (BULLISH) | B72: 90913 | C72: 96018 | D72: 95005
A73: Bitcoin Spot Price

Sheet Jan 15. 2026
A1: INDEX | B1: BUY TRADE | C1: SELL TRADE | D1: PREV. CLOSE
A2: UST30Y (BULLISH) | B2: 4.87 | C2: 4.77 | D2: 4.78
A3: 30-Year U.S. Treasury Yield
A4: UST10Y (BEARISH) | B4: 4.19 | C4: 4.11 | D4: 4.14
A5: 10-Year U.S. Treasury Yield
A6: UST2Y (BEARISH) | B6: 3.54 | C6: 3.43 | D6: 3.52
A7: 2-Year U.S. Treasury Yield
A8: HYG (BULLISH) | B8: 80.75 | C8: 81.25 | D8: 81.04
A9: High Yield
A10: LQD (BULLISH) | B10: 110.3 | C10: 111.2 | D10: 111
A11: Investment Grade Corporate Bond ETF
A12: SPX (BULLISH) | B12: 6884 | C12: 7021 | D12: 6926
A13: S&P 500
A14: COMPQ (BULLISH) | B14: 23213 | C14: 23860 | D14: 23471
A15: NASDAQ Composite
A16: RUT (BULLISH) | B16: 2590 | C16: 2711 | D16: 2651
A17: Russell 2000
A18: XLK (BULLISH) | B18: 142 | C18: 147 | D18: 145
A19: Technology Select Sector SPDR Fund
A20: XLV (BULLISH) | B20: 155 | C20: 160 | D20: 158
A21: Health Care Select Sector SPDR Fund
A22: XLI (BULLISH) | B22: 160 | C22: 167 | D22: 164
A23: Industrial Select Sector SPDR Fund
A24: SSEC (BULLISH) | B24: 4008 | C24: 4212 | D24: 4112
A25: Shanghai Composite
A26: NIKK (BULLISH) | B26: 52004 | C26: 54518 | D26: 54110
A27: Nikkei 225 Index
A28: DAX (BULLISH) | B28: 24567 | C28: 25687 | D28: 25286
A29: German DAX Composite
A30: VIX (BEARISH) | B30: 13.47 | C30: 16.93 | D30: 16.75
A31: Volatility Index
A32: USD (BULLISH) | B32: 98.32 | C32: 99.54 | D32: 99.27
A33: U.S. Dollar Index
A34: EUR/USD (BEARISH) | B34: 1.16 | C34: 1.173 | D34: 1.162
A35: Euro to U.S. Dollar
A36: USD/YEN (BULLISH) | B36: 156.99 | C36: 159.75 | D36: 158.6
A37: U.S. Dollar to Japanese Yen
A38: GBP/USD (BULLISH) | B38: 1.336 | C38: 1.352 | D38: 1.34
A39: British Pound to U.S. Dollar
A40: CAD/USD (BEARISH) | B40: 0.715 | C40: 0.723 | D40: 0.719
A41: Canadian Dollar to U.S. Dollar
A42: WTIC (BEARISH) | B42: 57.43 | C42: 61.14 | D42: 61.05
A43: Light Crude Oil Continuous Contract
A44: BRENT (BEARISH) | B44: 60.56 | C44: 65.46 | D44: 65.44
A45: Brent Crude Oil Continuous Contract
A46: NATGAS (BEARISH) | B46: 3.01 | C46: 3.61 | D46: 3.1
A47: Natural Gas Continuous Contract
A48: GOLD (BULLISH) | B48: 4501 | C48: 4692 | D48: 4620
A49: Gold Spot Price
A50: COPPER (BULLISH) | B50: 5.71 | C50: 6.19 | D50: 6.09
A51: Copper Continuous Contract
A52: SILVER (BULLISH) | B52: 81.19 | C52: 93.51 | D52: 92.21
A53: Silver Spot Price
A54: MSFT (BEARISH) | B54: 456 | C54: 476 | D54: 459
A55: Microsoft Corp.
A56: AAPL (BEARISH) | B56: 251 | C56: 267 | D56: 260
A57: Apple Inc.
A58: AMZN (BULLISH) | B58: 231 | C58: 251 | D58: 237
A59: Amazon Inc.
A60: META (BEARISH) | B60: 611 | C60: 648 | D60: 616
A61: Meta Platforms Inc.
A62: GOOGL (BULLISH) | B62: 318 | C62: 344 | D62: 336
A63: Alphabet Inc.
A64: NFLX (BEARISH) | B64: 86 | C64: 92 | D64: 89
A65: Netflix Inc.
A66: TSLA (NEUTRAL) | B66: 426 | C66: 455 | D66: 439
A67: Tesla Inc.
A68: NVDA (BULLISH) | B68: 181 | C68: 190 | D68: 183
A69: NVIDIA Corporation
A70: ORCL (BEARISH) | B70: 185 | C70: 198 | D70: 194
A71: Oracle Corporation
A72: BITCOIN (BULLISH) | B72: 91416 | C72: 98111 | D72: 96847
A73: Bitcoin Spot Price

Sheet Jan 16. 2026
A1: INDEX | B1: BUY TRADE | C1: SELL TRADE | D1: PREV. CLOSE
A2: UST30Y (BULLISH) | B2: 4.88 | C2: 4.78 | D2: 4.8
A3: 30-Year U.S. Treasury Yield
A4: UST10Y (BEARISH) | B4: 4.2 | C4: 4.12 | D4: 4.18
A5: 10-Year U.S. Treasury Yield
A6: UST2Y (BEARISH) | B6: 3.58 | C6: 3.43 | D6: 3.58
A7: 2-Year U.S. Treasury Yield
A8: HYG (BULLISH) | B8: 80.79 | C8: 81.2 | D8: 81.04
A9: High Yield
A10: LQD (BULLISH) | B10: 110.3 | C10: 111.2 | D10: 110.9
A11: Investment Grade Corporate Bond ETF
A12: SPX (BULLISH) | B12: 6889 | C12: 7008 | D12: 6944
A13: S&P 500
A14: COMPQ (BULLISH) | B14: 23315 | C14: 23797 | D14: 23530
A15: NASDAQ Composite
A16: RUT (BULLISH) | B16: 2580 | C16: 2698 | D16: 2674
A17: Russell 2000
A18: XLK (BULLISH) | B18: 143 | C18: 148 | D18: 145
A19: Technology Select Sector SPDR Fund
A20: XLV (BULLISH) | B20: 155 | C20: 160 | D20: 157
A21: Health Care Select Sector SPDR Fund
A22: XLI (BULLISH) | B22: 161 | C22: 168 | D22: 166
A23: Industrial Select Sector SPDR Fund
A24: SSEC (BULLISH) | B24: 4020 | C24: 4191 | D24: 4101
A25: Shanghai Composite
A26: NIKK (BULLISH) | B26: 51328 | C26: 54983 | D26: 53936
A27: Nikkei 225 Index
A28: DAX (BULLISH) | B28: 24790 | C28: 25612 | D28: 25352
A29: German DAX Composite
A30: VIX (BEARISH) | B30: 13.9 | C30: 16.84 | D30: 15.84
A31: Volatility Index
A32: USD (BULLISH) | B32: 98.5 | C32: 99.6 | D32: 99.23
A33: U.S. Dollar Index
A34: EUR/USD (BEARISH) | B34: 1.159 | C34: 1.171 | D34: 1.162
A35: Euro to U.S. Dollar
A36: USD/YEN (BULLISH) | B36: 156.91 | C36: 159.59 | D36: 158.15
A37: U.S. Dollar to Japanese Yen
A38: GBP/USD (BULLISH) | B38: 1.336 | C38: 1.351 | D38: 1.34
A39: British Pound to U.S. Dollar
A40: CAD/USD (BEARISH) | B40: 0.716 | C40: 0.722 | D40: 0.72
A41: Canadian Dollar to U.S. Dollar
A42: WTIC (BEARISH) | B42: 55.98 | C42: 62.01 | D42: 59.28
A43: Light Crude Oil Continuous Contract
A44: BRENT (BEARISH) | B44: 59.98 | C44: 66.42 | D44: 63.81
A45: Brent Crude Oil Continuous Contract
A46: NATGAS (BEARISH) | B46: 3 | C46: 3.55 | D46: 3.15
A47: Natural Gas Continuous Contract
A48: GOLD (BULLISH) | B48: 4506 | C48: 4682 | D48: 4619
A49: Gold Spot Price
A50: COPPER (BULLISH) | B50: 5.72 | C50: 6.15 | D50: 5.99
A51: Copper Continuous Contract
A52: SILVER (BULLISH) | B52: 83.67 | C52: 95.73 | D52: 92.73
A53: Silver Spot Price
A54: MSFT (BEARISH) | B54: 453 | C54: 471 | D54: 457
A55: Microsoft Corp.
A56: AAPL (BEARISH) | B56: 252 | C56: 266 | D56: 258
A57: Apple Inc.
A58: AMZN (BULLISH) | B58: 232 | C58: 252 | D58: 238
A59: Amazon Inc.
A60: META (BEARISH) | B60: 608 | C60: 647 | D60: 621
A61: Meta Platforms Inc.
A62: GOOGL (BULLISH) | B62: 319 | C62: 345 | D62: 333
A63: Alphabet Inc.
A64: NFLX (BEARISH) | B64: 86 | C64: 91 | D64: 88
A65: Netflix Inc.
A66: TSLA (NEUTRAL) | B66: 424 | C66: 455 | D66: 439
A67: Tesla Inc.
A68: NVDA (BULLISH) | B68: 183 | C68: 191 | D68: 187
A69: NVIDIA Corporation
A70: ORCL (BEARISH) | B70: 182 | C70: 199 | D70: 190
A71: Oracle Corporation
A72: BITCOIN (BULLISH) | B72: 91609 | C72: 98333 | D72: 95385
A73: Bitcoin Spot Price

Sheet Jan 20. 2026
A1: INDEX | B1: BUY TRADE | C1: SELL TRADE | D1: PREV. CLOSE
A2: UST30Y (BULLISH) | B2: 4.95 | C2: 4.81 | D2: 4.84
A3: 30-Year U.S. Treasury Yield
A4: UST10Y (BULLISH) | B4: 4.32 | C4: 4.13 | D4: 4.23
A5: 10-Year U.S. Treasury Yield
A6: UST2Y (BEARISH) | B6: 3.62 | C6: 3.44 | D6: 3.59
A7: 2-Year U.S. Treasury Yield
A8: HYG (BULLISH) | B8: 80.79 | C8: 81.18 | D8: 81.09
A9: High Yield
A10: LQD (NEUTRAL) | B10: 109.9 | C10: 111 | D10: 110.6
A11: Investment Grade Corporate Bond ETF
A12: SPX (BULLISH) | B12: 6845 | C12: 6993 | D12: 6940
A13: S&P 500
A14: COMPQ (BULLISH) | B14: 23101 | C14: 23775 | D14: 23515
A15: NASDAQ Composite
A16: RUT (BULLISH) | B16: 2575 | C16: 2702 | D16: 2677
A17: Russell 2000
A18: XLK (NEUTRAL) | B18: 141 | C18: 146 | D18: 146
A19: Technology Select Sector SPDR Fund
A20: XLV (BULLISH) | B20: 153 | C20: 160 | D20: 156
A21: Health Care Select Sector SPDR Fund
A22: XLI (BULLISH) | B22: 160 | C22: 169 | D22: 167
A23: Industrial Select Sector SPDR Fund
A24: SSEC (BULLISH) | B24: 4037 | C24: 4184 | D24: 4113
A25: Shanghai Composite
A26: NIKK (BULLISH) | B26: 51426 | C26: 54999 | D26: 52991
A27: Nikkei 225 Index
A28: DAX (BULLISH) | B28: 24404 | C28: 25411 | D28: 24959
A29: German DAX Composite
A30: VIX (BEARISH) | B30: 14.12 | C30: 19.92 | D30: 15.86
A31: Volatility Index
A32: USD (BEARISH) | B32: 98.14 | C32: 99.38 | D32: 98.44
A33: U.S. Dollar Index
A34: EUR/USD (BULLISH) | B34: 1.163 | C34: 1.178 | D34: 1.174
A35: Euro to U.S. Dollar
A36: USD/YEN (BULLISH) | B36: 156.9 | C36: 159.13 | D36: 157.8
A37: U.S. Dollar to Japanese Yen
A38: GBP/USD (BULLISH) | B38: 1.337 | C38: 1.352 | D38: 1.345
A39: British Pound to U.S. Dollar
A40: CAD/USD (NEUTRAL) | B40: 0.717 | C40: 0.726 | D40: 0.723
A41: Canadian Dollar to U.S. Dollar
A42: WTIC (NEUTRAL) | B42: 56.14 | C42: 62.03 | D42: 59.34
A43: Light Crude Oil Continuous Contract
A44: BRENT (NEUTRAL) | B44: 60.16 | C44: 66.51 | D44: 64.13
A45: Brent Crude Oil Continuous Contract
A46: NATGAS (NEUTRAL) | B46: 3.08 | C46: 3.84 | D46: 3.1
A47: Natural Gas Continuous Contract
A48: GOLD (BULLISH) | B48: 4561 | C48: 4749 | D48: 4724
A49: Gold Spot Price
A50: COPPER (BULLISH) | B50: 5.71 | C50: 6.17 | D50: 5.83
A51: Copper Continuous Contract
A52: SILVER (BULLISH) | B52: 84.97 | C52: 96.91 | D52: 89.94
A53: Silver Spot Price
A54: MSFT (BEARISH) | B54: 450 | C54: 471 | D54: 460
A55: Microsoft Corp.
A56: AAPL (BEARISH) | B56: 250 | C56: 261 | D56: 256
A57: Apple Inc.
A58: AMZN (BULLISH) | B58: 230 | C58: 250 | D58: 239
A59: Amazon Inc.
A60: META (BEARISH) | B60: 603 | C60: 644 | D60: 620
A61: Meta Platforms Inc.
A62: GOOGL (BULLISH) | B62: 315 | C62: 342 | D62: 330
A63: Alphabet Inc.
A64: NFLX (BEARISH) | B64: 84 | C64: 93 | D64: 88
A65: Netflix Inc.
A66: TSLA (BEARISH) | B66: 420 | C66: 450 | D66: 438
A67: Tesla Inc.
A68: NVDA (BULLISH) | B68: 180 | C68: 190 | D68: 186
A69: NVIDIA Corporation
A70: ORCL (BEARISH) | B70: 181 | C70: 198 | D70: 191
A71: Oracle Corporation
A72: BITCOIN (NEUTRAL) | B72: 90108 | C72: 96901 | D72: 91158 | E72: bitcoin trend is north of 94000
A73: Bitcoin Spot Price

Sheet Jan 21. 2026
A1: INDEX | B1: BUY TRADE | C1: SELL TRADE | D1: PREV. CLOSE
A2: UST30Y (BULLISH) | B2: 4.93 | C2: 4.82 | D2: 4.92
A3: 30-Year U.S. Treasury Yield
A4: UST10Y (BULLISH) | B4: 4.31 | C4: 4.15 | D4: 4.3
A5: 10-Year U.S. Treasury Yield
A6: UST2Y (BEARISH) | B6: 3.61 | C6: 3.47 | D6: 3.61
A7: 2-Year U.S. Treasury Yield
A8: HYG (BULLISH) | B8: 80.76 | C8: 81.17 | D8: 80.88
A9: High Yield
A10: LQD (NEUTRAL) | B10: 109.7 | C10: 110.7 | D10: 109.9
A11: Investment Grade Corporate Bond ETF
A12: SPX (BULLISH) | B12: 6773 | C12: 7039 | D12: 6796
A13: S&P 500
A14: COMPQ (BEARISH) | B14: 22714 | C14: 23616 | D14: 22954
A15: NASDAQ Composite
A16: RUT (BULLISH) | B16: 2594 | C16: 2704 | D16: 2645
A17: Russell 2000
A18: XLK (BEARISH) | B18: 139 | C18: 145 | D18: 142
A19: Technology Select Sector SPDR Fund
A20: XLV (BULLISH) | B20: 153 | C20: 159 | D20: 155
A21: Health Care Select Sector SPDR Fund
A22: XLI (BULLISH) | B22: 159 | C22: 169 | D22: 164
A23: Industrial Select Sector SPDR Fund
A24: SSEC (BULLISH) | B24: 4055 | C24: 4173 | D24: 4116
A25: Shanghai Composite
A26: NIKK (BULLISH) | B26: 51730 | C26: 55204 | D26: 52774
A27: Nikkei 225 Index
A28: DAX (BULLISH) | B28: 24321 | C28: 25412 | D28: 24703
A29: German DAX Composite
A30: VIX (BEARISH) | B30: 13.46 | C30: 21.65 | D30: 20.09
A31: Volatility Index
A32: USD (BEARISH) | B32: 98.4 | C32: 99.38 | D32: 98.48
A33: U.S. Dollar Index
A34: EUR/USD (BULLISH) | B34: 1.161 | C34: 1.175 | D34: 1.173
A35: Euro to U.S. Dollar
A36: USD/YEN (BULLISH) | B36: 157.17 | C36: 159.11 | D36: 157.78
A37: U.S. Dollar to Japanese Yen
A38: GBP/USD (NEUTRAL) | B38: 1.335 | C38: 1.35 | D38: 1.342
A39: British Pound to U.S. Dollar
A40: CAD/USD (NEUTRAL) | B40: 0.718 | C40: 0.724 | D40: 0.724
A41: Canadian Dollar to U.S. Dollar
A42: WTIC (NEUTRAL) | B42: 56.74 | C42: 61.99 | D42: 59.52
A43: Light Crude Oil Continuous Contract
A44: BRENT (NEUTRAL) | B44: 61.73 | C44: 66.62 | D44: 63.91
A45: Brent Crude Oil Continuous Contract
A46: NATGAS (BULLISH) | B46: 3.12 | C46: 4.75 | D46: 3.9
A47: Natural Gas Continuous Contract
A48: GOLD (BULLISH) | B48: 4603 | C48: 4893 | D48: 4865
A49: Gold Spot Price
A50: COPPER (BULLISH) | B50: 5.79 | C50: 6.19 | D50: 5.82
A51: Copper Continuous Contract
A52: SILVER (BULLISH) | B52: 85.98 | C52: 98.91 | D52: 94.06
A53: Silver Spot Price
A54: MSFT (BEARISH) | B54: 445 | C54: 470 | D54: 455
A55: Microsoft Corp.
A56: AAPL (BEARISH) | B56: 245 | C56: 257 | D56: 247
A57: Apple Inc.
A58: AMZN (BULLISH) | B58: 228 | C58: 252 | D58: 231
A59: Amazon Inc.
A60: META (BEARISH) | B60: 596 | C60: 635 | D60: 604
A61: Meta Platforms Inc.
A62: GOOGL (BULLISH) | B62: 315 | C62: 340 | D62: 322
A63: Alphabet Inc.
A64: NFLX (BEARISH) | B64: 80 | C64: 90 | D64: 87
A65: Netflix Inc.
A66: TSLA (BEARISH) | B66: 411 | C66: 446 | D66: 419
A67: Tesla Inc.
A68: NVDA (BEARISH) | B68: 171 | C68: 186 | D68: 178
A69: NVIDIA Corporation
A70: ORCL (BEARISH) | B70: 174 | C70: 194 | D70: 180
A71: Oracle Corporation
A72: BITCOIN (BEARISH) | B72: 87564 | C72: 94231 | D72: 88545 | E72: bitcoin trend is north of 94000
A73: Bitcoin Spot Price

Sheet Jan 22. 2026
A1: INDEX | B1: BUY TRADE | C1: SELL TRADE | D1: PREV. CLOSE
A2: UST30Y (BULLISH) | B2: 4.92 | C2: 4.79 | D2: 4.86
A3: 30-Year U.S. Treasury Yield
A4: UST10Y (BULLISH) | B4: 4.3 | C4: 4.12 | D4: 4.24
A5: 10-Year U.S. Treasury Yield
A6: UST2Y (BEARISH) | B6: 3.61 | C6: 3.46 | D6: 3.6
A7: 2-Year U.S. Treasury Yield
A8: HYG (BULLISH) | B8: 80.78 | C8: 81.25 | D8: 81.12
A9: High Yield
A10: LQD (BULLISH) | B10: 109.8 | C10: 110.9 | D10: 110.6
A11: Investment Grade Corporate Bond ETF
A12: SPX (BULLISH) | B12: 6807 | C12: 7038 | D12: 6875
A13: S&P 500
A14: COMPQ (NEUTRAL) | B14: 22905 | C14: 23576 | D14: 23224
A15: NASDAQ Composite
A16: RUT (BULLISH) | B16: 2620 | C16: 2728 | D16: 2698
A17: Russell 2000
A18: XLK (BEARISH) | B18: 140 | C18: 146 | D18: 144
A19: Technology Select Sector SPDR Fund
A20: XLV (BULLISH) | B20: 155 | C20: 160 | D20: 158
A21: Health Care Select Sector SPDR Fund
A22: XLI (BULLISH) | B22: 162 | C22: 170 | D22: 166
A23: Industrial Select Sector SPDR Fund
A24: SSEC (BULLISH) | B24: 4076 | C24: 4166 | D24: 4122
A25: Shanghai Composite
A26: NIKK (BULLISH) | B26: 51817 | C26: 54501 | D26: 53688
A27: Nikkei 225 Index
A28: DAX (BULLISH) | B28: 24401 | C28: 25417 | D28: 24560
A29: German DAX Composite
A30: VIX (BEARISH) | B30: 13.13 | C30: 19.5 | D30: 16.9
A31: Volatility Index
A32: USD (NEUTRAL) | B32: 98.43 | C32: 99.31 | D32: 98.67
A33: U.S. Dollar Index
A34: EUR/USD (BULLISH) | B34: 1.16 | C34: 1.173 | D34: 1.17
A35: Euro to U.S. Dollar
A36: USD/YEN (BULLISH) | B36: 157.17 | C36: 159.11 | D36: 158.64
A37: U.S. Dollar to Japanese Yen
A38: GBP/USD (NEUTRAL) | B38: 1.336 | C38: 1.35 | D38: 1.343
A39: British Pound to U.S. Dollar
A40: CAD/USD (NEUTRAL) | B40: 0.719 | C40: 0.725 | D40: 0.723
A41: Canadian Dollar to U.S. Dollar
A42: WTIC (BULLISH) | B42: 57.6 | C42: 62.32 | D42: 60.62
A43: Light Crude Oil Continuous Contract
A44: BRENT (BULLISH) | B44: 61.94 | C44: 66.98 | D44: 65.24
A45: Brent Crude Oil Continuous Contract
A46: NATGAS (BULLISH) | B46: 3.71 | C46: 5.36 | D46: 5.04
A47: Natural Gas Continuous Contract
A48: GOLD (BULLISH) | B48: 4613 | C48: 4874 | D48: 4831
A49: Gold Spot Price
A50: COPPER (BULLISH) | B50: 5.7 | C50: 6.14 | D50: 5.79
A51: Copper Continuous Contract
A52: SILVER (BULLISH) | B52: 87.64 | C52: 99.92 | D52: 91.59
A53: Silver Spot Price
A54: MSFT (BEARISH) | B54: 440 | C54: 466 | D54: 444
A55: Microsoft Corp.
A56: AAPL (BEARISH) | B56: 244 | C56: 256 | D56: 248
A57: Apple Inc.
A58: AMZN (BULLISH) | B58: 228 | C58: 247 | D58: 231
A59: Amazon Inc.
A60: META (BEARISH) | B60: 594 | C60: 639 | D60: 613
A61: Meta Platforms Inc.
A62: GOOGL (BULLISH) | B62: 322 | C62: 341 | D62: 328
A63: Alphabet Inc.
A64: NFLX (BEARISH) | B64: 81 | C64: 89 | D64: 85
A65: Netflix Inc.
A66: TSLA (BEARISH) | B66: 413 | C66: 444 | D66: 431
A67: Tesla Inc.
A68: NVDA (NEUTRAL) | B68: 177 | C68: 187 | D68: 183
A69: NVIDIA Corporation
A70: ORCL (BEARISH) | B70: 171 | C70: 190 | D70: 174
A71: Oracle Corporation
A72: BITCOIN (BEARISH) | B72: 87101 | C72: 94134 | D72: 90001 | E72: bitcoin trend is north of 94000
A73: Bitcoin Spot Price

Sheet Jan 23. 2026
A1: INDEX | B1: BUY TRADE | C1: SELL TRADE | D1: PREV. CLOSE
A2: UST30Y (BULLISH) | B2: 4.92 | C2: 4.78 | D2: 4.84
A3: 30-Year U.S. Treasury Yield
A4: UST10Y (BULLISH) | B4: 4.29 | C4: 4.16 | D4: 4.25
A5: 10-Year U.S. Treasury Yield
A6: UST2Y (BEARISH) | B6: 3.62 | C6: 3.48 | D6: 3.61
A7: 2-Year U.S. Treasury Yield
A8: HYG (BULLISH) | B8: 80.91 | C8: 81.3 | D8: 81.18
A9: High Yield
A10: LQD (BULLISH) | B10: 110.1 | C10: 111.2 | D10: 110.8
A11: Investment Grade Corporate Bond ETF
A12: SPX (BULLISH) | B12: 6825 | C12: 7039 | D12: 6913
A13: S&P 500
A14: COMPQ (NEUTRAL) | B14: 22977 | C14: 23791 | D14: 23436
A15: NASDAQ Composite
A16: RUT (BULLISH) | B16: 2651 | C16: 2742 | D16: 2718
A17: Russell 2000
A18: XLK (NEUTRAL) | B18: 141 | C18: 146 | D18: 145
A19: Technology Select Sector SPDR Fund
A20: XLV (BULLISH) | B20: 155 | C20: 160 | D20: 158
A21: Health Care Select Sector SPDR Fund
A22: XLI (BULLISH) | B22: 162 | C22: 169 | D22: 166
A23: Industrial Select Sector SPDR Fund
A24: SSEC (BULLISH) | B24: 4080 | C24: 4167 | D24: 4136
A25: Shanghai Composite
A26: NIKK (BULLISH) | B26: 52122 | C26: 54818 | D26: 53846
A27: Nikkei 225 Index
A28: DAX (BULLISH) | B28: 24405 | C28: 25461 | D28: 24856
A29: German DAX Composite
A30: VIX (BEARISH) | B30: 13.08 | C30: 19.42 | D30: 15.64
A31: Volatility Index
A32: USD (NEUTRAL) | B32: 98.03 | C32: 98.99 | D32: 98.3
A33: U.S. Dollar Index
A34: EUR/USD (BULLISH) | B34: 1.16 | C34: 1.175 | D34: 1.174
A35: Euro to U.S. Dollar
A36: USD/YEN (BULLISH) | B36: 157.55 | C36: 159.12 | D36: 158.21
A37: U.S. Dollar to Japanese Yen
A38: GBP/USD (NEUTRAL) | B38: 1.335 | C38: 1.351 | D38: 1.35
A39: British Pound to U.S. Dollar
A40: CAD/USD (NEUTRAL) | B40: 0.719 | C40: 0.725 | D40: 0.725
A41: Canadian Dollar to U.S. Dollar
A42: WTIC (BULLISH) | B42: 58.42 | C42: 62.11 | D42: 59.67
A43: Light Crude Oil Continuous Contract
A44: BRENT (BULLISH) | B44: 62.9 | C44: 66.72 | D44: 64.38
A45: Brent Crude Oil Continuous Contract
A46: NATGAS (BULLISH) | B46: 3.77 | C46: 5.17 | D46: 4.93
A47: Natural Gas Continuous Contract
A48: GOLD (BULLISH) | B48: 4696 | C48: 4967 | D48: 4937
A49: Gold Spot Price
A50: COPPER (BULLISH) | B50: 5.72 | C50: 6.16 | D50: 5.81
A51: Copper Continuous Contract
A52: SILVER (BULLISH) | B52: 90.42 | C52: 101.24 | D52: 96.82
A53: Silver Spot Price
A54: MSFT (BEARISH) | B54: 436 | C54: 469 | D54: 451
A55: Microsoft Corp.
A56: AAPL (BEARISH) | B56: 242 | C56: 256 | D56: 248
A57: Apple Inc.
A58: AMZN (BULLISH) | B58: 226 | C58: 247 | D58: 234
A59: Amazon Inc.
A60: META (BEARISH) | B60: 594 | C60: 661 | D60: 648
A61: Meta Platforms Inc.
A62: GOOGL (BULLISH) | B62: 321 | C62: 339 | D62: 331
A63: Alphabet Inc.
A64: NFLX (BEARISH) | B64: 81 | C64: 88 | D64: 84
A65: Netflix Inc.
A66: TSLA (BULLISH) | B66: 419 | C66: 467 | D66: 449
A67: Tesla Inc.
A68: NVDA (NEUTRAL) | B68: 178 | C68: 190 | D68: 185
A69: NVIDIA Corporation
A70: ORCL (BEARISH) | B70: 168 | C70: 189 | D70: 178
A71: Oracle Corporation
A72: BITCOIN (BEARISH) | B72: 85539 | C72: 92172 | D72: 89132
A73: Bitcoin Spot Price

Sheet Jan 26. 2026
A1: INDEX | B1: BUY TRADE | C1: SELL TRADE | D1: PREV. CLOSE
A2: UST30Y (BULLISH) | B2: 4.91 | C2: 4.77 | D2: 4.83
A3: 30-Year U.S. Treasury Yield
A4: UST10Y (NEUTRAL) | B4: 4.29 | C4: 4.13 | D4: 4.23
A5: 10-Year U.S. Treasury Yield
A6: UST2Y (BEARISH) | B6: 3.62 | C6: 3.49 | D6: 3.61
A7: 2-Year U.S. Treasury Yield
A8: HYG (BULLISH) | B8: 80.92 | C8: 81.28 | D8: 81.14
A9: High Yield
A10: LQD (BULLISH) | B10: 110.2 | C10: 111.4 | D10: 110.8
A11: Investment Grade Corporate Bond ETF
A12: SPX (BULLISH) | B12: 6824 | C12: 7030 | D12: 6915
A13: S&P 500
A14: COMPQ (BULLISH) | B14: 22981 | C14: 23721 | D14: 23501
A15: NASDAQ Composite
A16: RUT (BULLISH) | B16: 2615 | C16: 2724 | D16: 2669
A17: Russell 2000
A18: XLK (NEUTRAL) | B18: 142 | C18: 146 | D18: 145
A19: Technology Select Sector SPDR Fund
A20: XLV (BULLISH) | B20: 155 | C20: 159 | D20: 157
A21: Health Care Select Sector SPDR Fund
A22: XLI (BULLISH) | B22: 162 | C22: 168 | D22: 164
A23: Industrial Select Sector SPDR Fund
A24: SSEC (BULLISH) | B24: 4086 | C24: 4166 | D24: 4132
A25: Shanghai Composite
A26: NIKK (BULLISH) | B26: 52604 | C26: 54606 | D26: 52885
A27: Nikkei 225 Index
A28: DAX (BULLISH) | B28: 24441 | C28: 25500 | D28: 24900
A29: German DAX Composite
A30: VIX (BEARISH) | B30: 13.57 | C30: 19.33 | D30: 16.09
A31: Volatility Index
A32: USD (BEARISH) | B32: 96.9 | C32: 98.72 | D32: 97.15
A33: U.S. Dollar Index
A34: EUR/USD (BULLISH) | B34: 1.166 | C34: 1.188 | D34: 1.185
A35: Euro to U.S. Dollar
A36: USD/YEN (NEUTRAL) | B36: 152.96 | C36: 157.53 | D36: 153.87
A37: U.S. Dollar to Japanese Yen
A38: GBP/USD (BULLISH) | B38: 1.344 | C38: 1.369 | D38: 1.366
A39: British Pound to U.S. Dollar
A40: CAD/USD (BULLISH) | B40: 0.721 | C40: 0.733 | D40: 0.73
A41: Canadian Dollar to U.S. Dollar
A42: WTIC (BULLISH) | B42: 58.48 | C42: 62.45 | D42: 61.28
A43: Light Crude Oil Continuous Contract
A44: BRENT (BULLISH) | B44: 63.28 | C44: 67.23 | D44: 66.2
A45: Brent Crude Oil Continuous Contract
A46: NATGAS (BULLISH) | B46: 3.91 | C46: 6.39 | D46: 5.35
A47: Natural Gas Continuous Contract
A48: GOLD (BULLISH) | B48: 4736 | C48: 5124 | D48: 5091
A49: Gold Spot Price
A50: COPPER (BULLISH) | B50: 5.7 | C50: 6.14 | D50: 5.94
A51: Copper Continuous Contract
A52: SILVER (BULLISH) | B52: 92.9 | C52: 111.4 | D52: 102.95
A53: Silver Spot Price
A54: MSFT (BEARISH) | B54: 439 | C54: 472 | D54: 466
A55: Microsoft Corp.
A56: AAPL (BEARISH) | B56: 240 | C56: 258 | D56: 248
A57: Apple Inc.
A58: AMZN (BULLISH) | B58: 229 | C58: 248 | D58: 239
A59: Amazon Inc.
A60: META (BEARISH) | B60: 592 | C60: 664 | D60: 659
A61: Meta Platforms Inc.
A62: GOOGL (BULLISH) | B62: 320 | C62: 340 | D62: 328
A63: Alphabet Inc.
A64: NFLX (BEARISH) | B64: 82 | C64: 89 | D64: 86
A65: Netflix Inc.
A66: TSLA (BULLISH) | B66: 420 | C66: 464 | D66: 449
A67: Tesla Inc.
A68: NVDA (BULLISH) | B68: 179 | C68: 191 | D68: 188
A69: NVIDIA Corporation
A70: ORCL (BEARISH) | B70: 165 | C70: 188 | D70: 177
A71: Oracle Corporation
A72: BITCOIN (BEARISH) | B72: 84901 | C72: 91636 | D72: 87868
A73: Bitcoin Spot Price

Sheet Jan 27. 2026
A1: INDEX | B1: BUY TRADE | C1: SELL TRADE | D1: PREV. CLOSE
A2: UST30Y (NEUTRAL) | B2: 4.9 | C2: 4.77 | D2: 4.8
A3: 30-Year U.S. Treasury Yield
A4: UST10Y (NEUTRAL) | B4: 4.29 | C4: 4.14 | D4: 4.22
A5: 10-Year U.S. Treasury Yield
A6: UST2Y (BEARISH) | B6: 3.62 | C6: 3.49 | D6: 3.6
A7: 2-Year U.S. Treasury Yield
A8: HYG (BULLISH) | B8: 80.91 | C8: 81.29 | D8: 81.18
A9: High Yield
A10: LQD (BULLISH) | B10: 110.2 | C10: 111.3 | D10: 110.9
A11: Investment Grade Corporate Bond ETF
A12: SPX (BULLISH) | B12: 6828 | C12: 7021 | D12: 6950
A13: S&P 500
A14: COMPQ (BULLISH) | B14: 23026 | C14: 23829 | D14: 23601
A15: NASDAQ Composite
A16: RUT (BULLISH) | B16: 2621 | C16: 2723 | D16: 2659
A17: Russell 2000
A18: XLK (BULLISH) | B18: 142 | C18: 147 | D18: 146
A19: Technology Select Sector SPDR Fund
A20: XLV (BULLISH) | B20: 156 | C20: 160 | D20: 158
A21: Health Care Select Sector SPDR Fund
A22: XLI (BULLISH) | B22: 162 | C22: 168 | D22: 164
A23: Industrial Select Sector SPDR Fund
A24: SSEC (BULLISH) | B24: 4087 | C24: 4168 | D24: 4139
A25: Shanghai Composite
A26: NIKK (BULLISH) | B26: 52518 | C26: 54667 | D26: 53333
A27: Nikkei 225 Index
A28: DAX (BULLISH) | B28: 24412 | C28: 25501 | D28: 24933
A29: German DAX Composite
A30: VIX (BEARISH) | B30: 13.77 | C30: 19.11 | D30: 16.15
A31: Volatility Index
A32: USD (BEARISH) | B32: 96.41 | C32: 98.45 | D32: 96.74
A33: U.S. Dollar Index
A34: EUR/USD (BULLISH) | B34: 1.171 | C34: 1.193 | D34: 1.191
A35: Euro to U.S. Dollar
A36: USD/YEN (NEUTRAL) | B36: 153.13 | C36: 156.85 | D36: 153.51
A37: U.S. Dollar to Japanese Yen
A38: GBP/USD (BULLISH) | B38: 1.346 | C38: 1.373 | D38: 1.373
A39: British Pound to U.S. Dollar
A40: CAD/USD (BULLISH) | B40: 0.721 | C40: 0.733 | D40: 0.73
A41: Canadian Dollar to U.S. Dollar
A42: WTIC (BULLISH) | B42: 59.07 | C42: 62.43 | D42: 60.63
A43: Light Crude Oil Continuous Contract
A44: BRENT (BULLISH) | B44: 63.5 | C44: 67.2 | D44: 65.59
A45: Brent Crude Oil Continuous Contract
A46: NATGAS (BULLISH) | B46: 4.07 | C46: 6.92 | D46: 6.8
A47: Natural Gas Continuous Contract
A48: GOLD (BULLISH) | B48: 4786 | C48: 5136 | D48: 5088
A49: Gold Spot Price
A50: COPPER (BULLISH) | B50: 5.7 | C50: 6.15 | D50: 5.92
A51: Copper Continuous Contract
A52: SILVER (BULLISH) | B52: 95.01 | C52: 116.11 | D52: 106.22
A53: Silver Spot Price
A54: MSFT (BEARISH) | B54: 440 | C54: 475 | D54: 470
A55: Microsoft Corp.
A56: AAPL (BEARISH) | B56: 243 | C56: 260 | D56: 255
A57: Apple Inc.
A58: AMZN (BULLISH) | B58: 229 | C58: 246 | D58: 238
A59: Amazon Inc.
A60: META (BEARISH) | B60: 590 | C60: 677 | D60: 672
A61: Meta Platforms Inc.
A62: GOOGL (BULLISH) | B62: 322 | C62: 342 | D62: 333
A63: Alphabet Inc.
A64: NFLX (BEARISH) | B64: 82 | C64: 89 | D64: 86
A65: Netflix Inc.
A66: TSLA (BEARISH) | B66: 418 | C66: 451 | D66: 435
A67: Tesla Inc.
A68: NVDA (BULLISH) | B68: 179 | C68: 191 | D68: 186
A69: NVIDIA Corporation
A70: ORCL (BEARISH) | B70: 165 | C70: 191 | D70: 182
A71: Oracle Corporation
A72: BITCOIN (BEARISH) | B72: 85107 | C72: 90668 | D72: 87957
A73: Bitcoin Spot Price

Sheet Jan 28. 2026
A1: INDEX | B1: BUY TRADE | C1: SELL TRADE | D1: PREV. CLOSE
A2: UST30Y (BULLISH) | B2: 4.92 | C2: 4.78 | D2: 4.86
A3: 30-Year U.S. Treasury Yield
A4: UST10Y (BULLISH) | B4: 4.31 | C4: 4.16 | D4: 4.25
A5: 10-Year U.S. Treasury Yield
A6: UST2Y (BEARISH) | B6: 3.6 | C6: 3.5 | D6: 3.59
A7: 2-Year U.S. Treasury Yield
A8: HYG (BULLISH) | B8: 80.93 | C8: 81.33 | D8: 81.17
A9: High Yield
A10: LQD (BULLISH) | B10: 110 | C10: 111.1 | D10: 110.8
A11: Investment Grade Corporate Bond ETF
A12: SPX (BULLISH) | B12: 6834 | C12: 7026 | D12: 6978
A13: S&P 500
A14: COMPQ (BULLISH) | B14: 23014 | C14: 23926 | D14: 23817
A15: NASDAQ Composite
A16: RUT (BULLISH) | B16: 2626 | C16: 2717 | D16: 2666
A17: Russell 2000
A18: XLK (BULLISH) | B18: 143 | C18: 150 | D18: 148
A19: Technology Select Sector SPDR Fund
A20: XLI (BULLISH) | B20: 163 | C20: 168 | D20: 165
A21: Industrial Select Sector SPDR Fund
A22: SSEC (BULLISH) | B22: 4101 | C22: 4165 | D22: 4151
A23: Shanghai Composite
A24: NIKK (BULLISH) | B24: 52521 | C24: 54404 | D24: 53358
A25: Nikkei 225 Index
A26: DAX (BULLISH) | B26: 24415 | C26: 25418 | D26: 24894
A27: German DAX Composite
A28: VIX (BEARISH) | B28: 13.48 | C28: 19.1 | D28: 16.35
A29: Volatility Index
A30: USD (BEARISH) | B30: 95.41 | C30: 97.97 | D30: 96.13
A31: U.S. Dollar Index
A32: EUR/USD (BULLISH) | B32: 1.173 | C32: 1.204 | D32: 1.198
A33: Euro to U.S. Dollar
A34: USD/YEN (BEARISH) | B34: 151.5 | C34: 156.38 | D34: 152.43
A35: U.S. Dollar to Japanese Yen
A36: GBP/USD (BULLISH) | B36: 1.349 | C36: 1.384 | D36: 1.379
A37: British Pound to U.S. Dollar
A38: CAD/USD (BULLISH) | B38: 0.722 | C38: 0.739 | D38: 0.737
A39: Canadian Dollar to U.S. Dollar
A40: WTIC (BULLISH) | B40: 59.43 | C40: 62.9 | D40: 62.57
A41: Light Crude Oil Continuous Contract
A42: BRENT (BULLISH) | B42: 63.8 | C42: 67.98 | D42: 67.66
A43: Brent Crude Oil Continuous Contract
A44: NATGAS (BULLISH) | B44: 4.33 | C44: 7.25 | D44: 6.4
A45: Natural Gas Continuous Contract
A46: GOLD (BULLISH) | B46: 4858 | C46: 5296 | D46: 5266
A47: Gold Spot Price
A48: COPPER (BULLISH) | B48: 5.71 | C48: 6.17 | D48: 5.95
A49: Copper Continuous Contract
A50: SILVER (BULLISH) | B50: 98 | C50: 115 | D50: 111.2
A51: Silver Spot Price
A52: PPLT (BULLISH) | B52: 220 | C52: 267 | D52: 237.78
A53: abrdn Physical Platinum Shares ETF
A54: MSFT (BEARISH) | B54: 444 | C54: 484 | D54: 481
A55: Microsoft Corp.
A56: AAPL (BEARISH) | B56: 242 | C56: 263 | D56: 258
A57: Apple Inc.
A58: AMZN (BULLISH) | B58: 231 | C58: 249 | D58: 245
A59: Amazon Inc.
A60: META (NEUTRAL) | B60: 591 | C60: 681 | D60: 673
A61: Meta Platforms Inc.
A62: GOOGL (BULLISH) | B62: 323 | C62: 342 | D62: 335
A63: Alphabet Inc.
A64: NFLX (BEARISH) | B64: 82 | C64: 88 | D64: 86
A65: Netflix Inc.
A66: TSLA (BEARISH) | B66: 414 | C66: 449 | D66: 431
A67: Tesla Inc.
A68: NVDA (BULLISH) | B68: 180 | C68: 193 | D68: 189
A69: NVIDIA Corporation
A70: ORCL (BEARISH) | B70: 166 | C70: 190 | D70: 175
A71: Oracle Corporation
A72: BITCOIN (BEARISH) | B72: 86112 | C72: 90667 | D72: 89736
A73: Bitcoin Spot Price

Sheet Jan 29. 2026
A1: INDEX | B1: BUY TRADE | C1: SELL TRADE | D1: PREV. CLOSE
A2: UST30Y (BULLISH) | B2: 4.92 | C2: 4.79 | D2: 4.85
A3: 30-Year U.S. Treasury Yield
A4: UST10Y (BULLISH) | B4: 4.31 | C4: 4.16 | D4: 4.25
A5: 10-Year U.S. Treasury Yield
A6: UST2Y (BEARISH) | B6: 3.61 | C6: 3.51 | D6: 3.58
A7: 2-Year U.S. Treasury Yield
A8: HYG (BULLISH) | B8: 80.91 | C8: 81.3 | D8: 81.04
A9: High Yield
A10: LQD (BULLISH) | B10: 110 | C10: 111 | D10: 110.7
A11: Investment Grade Corporate Bond ETF
A12: SPX (BULLISH) | B12: 6876 | C12: 7039 | D12: 6978
A13: S&P 500
A14: COMPQ (BULLISH) | B14: 23054 | C14: 24036 | D14: 23857
A15: NASDAQ Composite
A16: RUT (BULLISH) | B16: 2629 | C16: 2727 | D16: 2653
A17: Russell 2000
A18: XLK (BULLISH) | B18: 144 | C18: 152 | D18: 149
A19: Technology Select Sector SPDR Fund
A20: XLI (BULLISH) | B20: 162 | C20: 168 | D20: 164
A21: Industrial Select Sector SPDR Fund
A22: SSEC (BULLISH) | B22: 4090 | C22: 4163 | D22: 4157
A23: Shanghai Composite
A24: NIKK (BULLISH) | B24: 52509 | C24: 54300 | D24: 53375
A25: Nikkei 225 Index
A26: DAX (BULLISH) | B26: 24493 | C26: 25308 | D26: 24822
A27: German DAX Composite
A28: VIX (BEARISH) | B28: 13.81 | C28: 19.06 | D28: 16.35
A29: Volatility Index
A30: USD (BEARISH) | B30: 95.51 | C30: 98.01 | D30: 96.37
A31: U.S. Dollar Index
A32: EUR/USD (BULLISH) | B32: 1.175 | C32: 1.206 | D32: 1.195
A33: Euro to U.S. Dollar
A34: USD/YEN (BEARISH) | B34: 151.07 | C34: 156.22 | D34: 153.38
A35: U.S. Dollar to Japanese Yen
A36: GBP/USD (BULLISH) | B36: 1.351 | C36: 1.39 | D36: 1.38
A37: British Pound to U.S. Dollar
A38: CAD/USD (BULLISH) | B38: 0.723 | C38: 0.74 | D38: 0.738
A39: Canadian Dollar to U.S. Dollar
A40: WTIC (BULLISH) | B40: 59.89 | C40: 65.3 | D40: 63.21
A41: Light Crude Oil Continuous Contract
A42: BRENT (BULLISH) | B42: 64.06 | C42: 69.3 | D42: 68.4
A43: Brent Crude Oil Continuous Contract
A44: NATGAS (BULLISH) | B44: 3.52 | C44: 6.8 | D44: 3.76
A45: Natural Gas Continuous Contract
A46: GOLD (BULLISH) | B46: 4993 | C46: 5548 | D46: 5534
A47: Gold Spot Price
A48: COPPER (BULLISH) | B48: 5.76 | C48: 6.35 | D48: 6.01
A49: Copper Continuous Contract
A50: SILVER (BULLISH) | B50: 99 | C50: 121 | D50: 118.4
A51: Silver Spot Price
A52: PPLT (BULLISH) | B52: 222 | C52: 263 | D52: 245.16
A53: abrdn Physical Platinum Shares ETF
A54: MSFT (BEARISH) | B54: 432 | C54: 483 | D54: 482
A55: Microsoft Corp.
A56: AAPL (BEARISH) | B56: 241 | C56: 261 | D56: 256
A57: Apple Inc.
A58: AMZN (BULLISH) | B58: 232 | C58: 249 | D58: 243
A59: Amazon Inc.
A60: META (BULLISH) | B60: 605 | C60: 730 | D60: 669
A61: Meta Platforms Inc.
A62: GOOGL (BULLISH) | B62: 324 | C62: 346 | D62: 336
A63: Alphabet Inc.
A64: NFLX (BEARISH) | B64: 81 | C64: 88 | D64: 85
A65: Netflix Inc.
A66: TSLA (BULLISH) | B66: 421 | C66: 467 | D66: 431
A67: Tesla Inc.
A68: NVDA (BULLISH) | B68: 183 | C68: 196 | D68: 192
A69: NVIDIA Corporation
A70: ORCL (BEARISH) | B70: 166 | C70: 189 | D70: 173
A71: Oracle Corporation
A72: BITCOIN (BEARISH) | B72: 85856 | C72: 90331 | D72: 87844
A73: Bitcoin Spot Price

Sheet Jan 30. 2026
A1: INDEX | B1: BUY TRADE | C1: SELL TRADE | D1: PREV. CLOSE
A2: UST30Y (BULLISH) | B2: 4.91 | C2: 4.79 | D2: 4.86
A3: 30-Year U.S. Treasury Yield
A4: UST10Y (BULLISH) | B4: 4.3 | C4: 4.17 | D4: 4.24
A5: 10-Year U.S. Treasury Yield
A6: UST2Y (BEARISH) | B6: 3.61 | C6: 3.52 | D6: 3.57
A7: 2-Year U.S. Treasury Yield
A8: HYG (BULLISH) | B8: 80.86 | C8: 81.31 | D8: 81.03
A9: High Yield
A10: LQD (BULLISH) | B10: 110.2 | C10: 111.1 | D10: 110.7
A11: Investment Grade Corporate Bond ETF
A12: SPX (BULLISH) | B12: 6845 | C12: 7037 | D12: 6969
A13: S&P 500
A14: COMPQ (BULLISH) | B14: 23061 | C14: 24067 | D14: 23685
A15: NASDAQ Composite
A16: RUT (BULLISH) | B16: 2622 | C16: 2726 | D16: 2654
A17: Russell 2000
A18: XLK (BULLISH) | B18: 142 | C18: 151 | D18: 147
A19: Technology Select Sector SPDR Fund
A20: XLI (BULLISH) | B20: 162 | C20: 168 | D20: 166
A21: Industrial Select Sector SPDR Fund
A22: SSEC (BULLISH) | B22: 4092 | C22: 4165 | D22: 4117
A23: Shanghai Composite
A24: NIKK (BULLISH) | B24: 52399 | C24: 54201 | D24: 53322
A25: Nikkei 225 Index
A26: DAX (BULLISH) | B26: 24211 | C26: 25195 | D26: 24309
A27: German DAX Composite
A28: VIX (BEARISH) | B28: 14.03 | C28: 19.32 | D28: 16.88
A29: Volatility Index
A30: USD (BEARISH) | B30: 95.4 | C30: 97.98 | D30: 96.43
A31: U.S. Dollar Index
A32: EUR/USD (BULLISH) | B32: 1.176 | C32: 1.207 | D32: 1.194
A33: Euro to U.S. Dollar
A34: USD/YEN (BEARISH) | B34: 151.9 | C34: 156.14 | D34: 153.92
A35: U.S. Dollar to Japanese Yen
A36: GBP/USD (BULLISH) | B36: 1.352 | C36: 1.393 | D36: 1.378
A37: British Pound to U.S. Dollar
A38: CAD/USD (BULLISH) | B38: 0.725 | C38: 0.744 | D38: 0.74
A39: Canadian Dollar to U.S. Dollar
A40: WTIC (BULLISH) | B40: 60.12 | C40: 65.72 | D40: 65.42
A41: Light Crude Oil Continuous Contract
A42: BRENT (BULLISH) | B42: 64.33 | C42: 70.91 | D42: 70.71
A43: Brent Crude Oil Continuous Contract
A44: NATGAS (BULLISH) | B44: 3.5 | C44: 5.11 | D44: 3.92
A45: Natural Gas Continuous Contract
A46: GOLD (BULLISH) | B46: 5008 | C46: 5574 | D46: 5115
A47: Gold Spot Price
A48: COPPER (BULLISH) | B48: 5.79 | C48: 6.38 | D48: 6.37
A49: Copper Continuous Contract
A50: SILVER (BULLISH) | B50: 94 | C50: 124 | D50: 117
A51: Silver Spot Price
A52: PPLT (BULLISH) | B52: 210 | C52: 258 | D52: 239.13
A53: abrdn Physical Platinum Shares ETF
A54: MSFT (BEARISH) | B54: 426 | C54: 461 | D54: 434
A55: Microsoft Corp.
A56: AAPL (BEARISH) | B56: 242 | C56: 262 | D56: 258
A57: Apple Inc.
A58: AMZN (BULLISH) | B58: 231 | C58: 249 | D58: 242
A59: Amazon Inc.
A60: META (BULLISH) | B60: 664 | C60: 758 | D60: 738
A61: Meta Platforms Inc.
A62: GOOGL (BULLISH) | B62: 325 | C62: 345 | D62: 338
A63: Alphabet Inc.
A64: NFLX (BEARISH) | B64: 81 | C64: 87 | D64: 83
A65: Netflix Inc.
A66: TSLA (BEARISH) | B66: 392 | C66: 442 | D66: 417
A67: Tesla Inc.
A68: NVDA (BULLISH) | B68: 183 | C68: 197 | D68: 193
A69: NVIDIA Corporation
A70: ORCL (BEARISH) | B70: 163 | C70: 182 | D70: 169
A71: Oracle Corporation
A72: BITCOIN (BEARISH) | B72: 81993 | C72: 89502 | D72: 82654
A73: Bitcoin Spot Price

Sheet Feb 2. 2026
A1: INDEX | B1: BUY TRADE | C1: SELL TRADE | D1: PREV. CLOSE
A2: UST30Y (BULLISH) | B2: 4.91 | C2: 4.78 | D2: 4.88
A3: 30-Year U.S. Treasury Yield
A4: UST10Y (NEUTRAL) | B4: 4.28 | C4: 4.17 | D4: 4.24
A5: 10-Year U.S. Treasury Yield
A6: UST2Y (BEARISH) | B6: 3.6 | C6: 3.5 | D6: 3.54
A7: 2-Year U.S. Treasury Yield
A8: HYG (BULLISH) | B8: 80.87 | C8: 81.32 | D8: 81.12
A9: High Yield
A10: LQD (BULLISH) | B10: 110.1 | C10: 111.1 | D10: 110.6
A11: Investment Grade Corporate Bond ETF
A12: SPX (BULLISH) | B12: 6846 | C12: 7039 | D12: 6939
A13: S&P 500
A14: COMPQ (BULLISH) | B14: 23059 | C14: 24045 | D14: 23461
A15: NASDAQ Composite
A16: RUT (BULLISH) | B16: 2581 | C16: 2715 | D16: 2613
A17: Russell 2000
A18: XLK (NEUTRAL) | B18: 140 | C18: 147 | D18: 144
A19: Technology Select Sector SPDR Fund
A20: XLI (BULLISH) | B20: 162 | C20: 167 | D20: 165
A21: Industrial Select Sector SPDR Fund
A22: SSEC (NEUTRAL) | B22: 3978 | C22: 4132 | D22: 4015
A23: Shanghai Composite
A24: NIKK (BULLISH) | B24: 52447 | C24: 53994 | D24: 52655
A25: Nikkei 225 Index
A26: DAX (BULLISH) | B26: 24312 | C26: 25146 | D26: 24538
A27: German DAX Composite
A28: VIX (BEARISH) | B28: 14.26 | C28: 20.08 | D28: 17.44
A29: Volatility Index
A30: USD (BEARISH) | B30: 95.64 | C30: 97.99 | D30: 97.18
A31: U.S. Dollar Index
A32: EUR/USD (BULLISH) | B32: 1.17 | C32: 1.206 | D32: 1.185
A33: Euro to U.S. Dollar
A34: USD/YEN (BEARISH) | B34: 151.5 | C34: 156.11 | D34: 154.93
A35: U.S. Dollar to Japanese Yen
A36: GBP/USD (BULLISH) | B36: 1.354 | C36: 1.394 | D36: 1.369
A37: British Pound to U.S. Dollar
A38: CAD/USD (BULLISH) | B38: 0.726 | C38: 0.744 | D38: 0.733
A39: Canadian Dollar to U.S. Dollar
A40: WTIC (BULLISH) | B40: 60.14 | C40: 66.44 | D40: 65.74
A41: Light Crude Oil Continuous Contract
A42: BRENT (BULLISH) | B42: 64.8 | C42: 70.98 | D42: 69.82
A43: Brent Crude Oil Continuous Contract
A44: NATGAS (NEUTRAL) | B44: 3.21 | C44: 5.04 | D44: 4.42
A45: Natural Gas Continuous Contract
A46: GOLD (BULLISH) | B46: 4601 | C46: 5539 | D46: 4772
A47: Gold Spot Price
A48: COPPER (BULLISH) | B48: 5.75 | C48: 6.22 | D48: 5.97
A49: Copper Continuous Contract
A50: SILVER (BULLISH) | B50: 78 | C50: 120 | D50: 84.63
A51: Silver Spot Price
A52: PPLT (BULLISH) | B52: 180 | C52: 260 | D52: 195.04
A53: abrdn Physical Platinum Shares ETF
A54: MSFT (BEARISH) | B54: 420 | C54: 458 | D54: 430
A55: Microsoft Corp.
A56: AAPL (BEARISH) | B56: 244 | C56: 262 | D56: 259
A57: Apple Inc.
A58: AMZN (BULLISH) | B58: 231 | C58: 247 | D58: 239
A59: Amazon Inc.
A60: META (BULLISH) | B60: 660 | C60: 750 | D60: 717
A61: Meta Platforms Inc.
A62: GOOGL (BULLISH) | B62: 324 | C62: 344 | D62: 338
A63: Alphabet Inc.
A64: NFLX (BEARISH) | B64: 81 | C64: 87 | D64: 83
A65: Netflix Inc.
A66: TSLA (BEARISH) | B66: 399 | C66: 448 | D66: 430
A67: Tesla Inc.
A68: NVDA (BULLISH) | B68: 182 | C68: 195 | D68: 191
A69: NVIDIA Corporation
A70: ORCL (BEARISH) | B70: 160 | C70: 181 | D70: 165
A71: Oracle Corporation
A72: BITCOIN (BEARISH) | B72: 74409 | C72: 84876 | D72: 78035
A73: Bitcoin Spot Price

Sheet Feb 3. 2026
A1: INDEX | B1: BUY TRADE | C1: SELL TRADE | D1: PREV. CLOSE
A2: UST30Y (BULLISH) | B2: 4.94 | C2: 4.8 | D2: 4.92
A3: 30-Year U.S. Treasury Yield
A4: UST10Y (BULLISH) | B4: 4.31 | C4: 4.2 | D4: 4.28
A5: 10-Year U.S. Treasury Yield
A6: UST2Y (BEARISH) | B6: 3.61 | C6: 3.52 | D6: 3.59
A7: 2-Year U.S. Treasury Yield
A8: HYG (BULLISH) | B8: 80.65 | C8: 80.91 | D8: 80.77
A9: High Yield
A10: LQD (BULLISH) | B10: 109.9 | C10: 110.7 | D10: 110.1
A11: Investment Grade Corporate Bond ETF
A12: SPX (BULLISH) | B12: 6906 | C12: 7032 | D12: 6976
A13: S&P 500
A14: COMPQ (BULLISH) | B14: 23103 | C14: 23987 | D14: 23592
A15: NASDAQ Composite
A16: RUT (BULLISH) | B16: 2613 | C16: 2727 | D16: 2640
A17: Russell 2000
A18: XLK (BULLISH) | B18: 142 | C18: 149 | D18: 145
A19: Technology Select Sector SPDR Fund
A20: XLI (BULLISH) | B20: 164 | C20: 169 | D20: 168
A21: Industrial Select Sector SPDR Fund
A22: SSEC (NEUTRAL) | B22: 4001 | C22: 4121 | D22: 4067
A23: Shanghai Composite
A24: NIKK (BULLISH) | B24: 52491 | C24: 54811 | D24: 54720
A25: Nikkei 225 Index
A26: DAX (BULLISH) | B26: 24343 | C26: 25239 | D26: 24797
A27: German DAX Composite
A28: VIX (BEARISH) | B28: 14.49 | C28: 17.97 | D28: 16.34
A29: Volatility Index
A30: USD (BEARISH) | B30: 95.71 | C30: 98.38 | D30: 97.58
A31: U.S. Dollar Index
A32: EUR/USD (BULLISH) | B32: 1.17 | C32: 1.203 | D32: 1.18
A33: Euro to U.S. Dollar
A34: USD/YEN (BULLISH) | B34: 152.54 | C34: 158.21 | D34: 155.92
A35: U.S. Dollar to Japanese Yen
A36: GBP/USD (BULLISH) | B36: 1.352 | C36: 1.386 | D36: 1.367
A37: British Pound to U.S. Dollar
A38: CAD/USD (BULLISH) | B38: 0.724 | C38: 0.741 | D38: 0.731
A39: Canadian Dollar to U.S. Dollar
A40: WTIC (BULLISH) | B40: 60.2 | C40: 66.28 | D40: 62.33
A41: Light Crude Oil Continuous Contract
A42: BRENT (BULLISH) | B42: 64.33 | C42: 70.63 | D42: 66.46
A43: Brent Crude Oil Continuous Contract
A44: NATGAS (BEARISH) | B44: 3.05 | C44: 4.06 | D44: 3.27
A45: Natural Gas Continuous Contract
A46: GOLD (BULLISH) | B46: 4628 | C46: 5505 | D46: 4914
A47: Gold Spot Price
A48: COPPER (BULLISH) | B48: 5.75 | C48: 6.22 | D48: 5.84
A49: Copper Continuous Contract
A50: SILVER (BULLISH) | B50: 76 | C50: 124 | D50: 80.65 | E50: trade level 87
A51: Silver Spot Price
A52: PPLT (BULLISH) | B52: 191 | C52: 261 | D52: 194.64
A53: abrdn Physical Platinum Shares ETF
A54: MSFT (BEARISH) | B54: 410 | C54: 453 | D54: 423
A55: Microsoft Corp.
A56: AAPL (BULLISH) | B56: 246 | C56: 274 | D56: 270
A57: Apple Inc.
A58: AMZN (BULLISH) | B58: 232 | C58: 248 | D58: 243
A59: Amazon Inc.
A60: META (BULLISH) | B60: 663 | C60: 747 | D60: 706
A61: Meta Platforms Inc.
A62: GOOGL (BULLISH) | B62: 325 | C62: 350 | D62: 344
A63: Alphabet Inc.
A64: NFLX (BEARISH) | B64: 80 | C64: 86 | D64: 83
A65: Netflix Inc.
A66: TSLA (BEARISH) | B66: 408 | C66: 445 | D66: 422
A67: Tesla Inc.
A68: NVDA (BULLISH) | B68: 180 | C68: 194 | D68: 186
A69: NVIDIA Corporation
A70: ORCL (BEARISH) | B70: 156 | C70: 182 | D70: 160
A71: Oracle Corporation
A72: BITCOIN (BEARISH) | B72: 73408 | C72: 84079 | D72: 78275
A73: Bitcoin Spot Price

Sheet Feb 4. 2026
A1: INDEX | B1: BUY TRADE | C1: SELL TRADE | D1: PREV. CLOSE
A2: UST30Y (BULLISH) | B2: 4.94 | C2: 4.82 | D2: 4.9
A3: 30-Year U.S. Treasury Yield
A4: UST10Y (BULLISH) | B4: 4.3 | C4: 4.19 | D4: 4.27
A5: 10-Year U.S. Treasury Yield
A6: UST2Y (BEARISH) | B6: 3.62 | C6: 3.52 | D6: 3.58
A7: 2-Year U.S. Treasury Yield
A8: HYG (BULLISH) | B8: 80.61 | C8: 80.91 | D8: 80.72
A9: High Yield
A10: LQD (BULLISH) | B10: 109.7 | C10: 110.7 | D10: 110.1
A11: Investment Grade Corporate Bond ETF
A12: SPX (BULLISH) | B12: 6874 | C12: 7021 | D12: 6917
A13: S&P 500
A14: COMPQ (BULLISH) | B14: 23087 | C14: 23958 | D14: 23255
A15: NASDAQ Composite
A16: RUT (BULLISH) | B16: 2605 | C16: 2715 | D16: 2648
A17: Russell 2000
A18: XLK (BEARISH) | B18: 139 | C18: 147 | D18: 142
A19: Technology Select Sector SPDR Fund
A20: XLI (BULLISH) | B20: 165 | C20: 170 | D20: 169
A21: Industrial Select Sector SPDR Fund
A22: SSEC (BULLISH) | B22: 4015 | C22: 4157 | D22: 4102
A23: Shanghai Composite
A24: NIKK (BULLISH) | B24: 52632 | C24: 54750 | D24: 54293
A25: Nikkei 225 Index
A26: DAX (BULLISH) | B26: 24364 | C26: 25147 | D26: 24780
A27: German DAX Composite
A28: VIX (BEARISH) | B28: 15.02 | C28: 18.99 | D28: 18
A29: Volatility Index
A30: USD (BEARISH) | B30: 95.73 | C30: 98.01 | D30: 97.45
A31: U.S. Dollar Index
A32: EUR/USD (BULLISH) | B32: 1.171 | C32: 1.203 | D32: 1.182
A33: Euro to U.S. Dollar
A34: USD/YEN (BULLISH) | B34: 152.59 | C34: 158.01 | D34: 156.66
A35: U.S. Dollar to Japanese Yen
A36: GBP/USD (BULLISH) | B36: 1.355 | C36: 1.384 | D36: 1.372
A37: British Pound to U.S. Dollar
A38: CAD/USD (BULLISH) | B38: 0.725 | C38: 0.74 | D38: 0.732
A39: Canadian Dollar to U.S. Dollar
A40: WTIC (BULLISH) | B40: 60.82 | C40: 66.57 | D40: 63.9
A41: Light Crude Oil Continuous Contract
A42: BRENT (BULLISH) | B42: 65.03 | C42: 70.78 | D42: 68.01
A43: Brent Crude Oil Continuous Contract
A44: NATGAS (BEARISH) | B44: 2.76 | C44: 4.34 | D44: 3.36
A45: Natural Gas Continuous Contract
A46: GOLD (BULLISH) | B46: 4660 | C46: 5511 | D46: 5052
A47: Gold Spot Price
A48: COPPER (BULLISH) | B48: 5.75 | C48: 6.22 | D48: 6.08
A49: Copper Continuous Contract
A50: SILVER (BULLISH) | B50: 79 | C50: 128 | D50: 84.74 | E50: trade level 86
A51: Silver Spot Price
A52: PPLT (BULLISH) | B52: 194 | C52: 267 | D52: 202.59
A53: abrdn Physical Platinum Shares ETF
A54: MSFT (BEARISH) | B54: 396 | C54: 448 | D54: 411
A55: Microsoft Corp.
A56: AAPL (BULLISH) | B56: 258 | C56: 274 | D56: 269
A57: Apple Inc.
A58: AMZN (BULLISH) | B58: 233 | C58: 247 | D58: 239
A59: Amazon Inc.
A60: META (BULLISH) | B60: 667 | C60: 744 | D60: 692
A61: Meta Platforms Inc.
A62: GOOGL (BULLISH) | B62: 326 | C62: 349 | D62: 340
A63: Alphabet Inc.
A64: NFLX (BEARISH) | B64: 77 | C64: 84 | D64: 80
A65: Netflix Inc.
A66: TSLA (BEARISH) | B66: 406 | C66: 438 | D66: 422
A67: Tesla Inc.
A68: NVDA (BEARISH) | B68: 176 | C68: 186 | D68: 180
A69: NVIDIA Corporation
A70: ORCL (BEARISH) | B70: 151 | C70: 169 | D70: 155
A71: Oracle Corporation
A72: BITCOIN (BEARISH) | B72: 70197 | C72: 81495 | D72: 76039
A73: Bitcoin Spot Price

Sheet Feb 5. 2026
A1: INDEX | B1: BUY TRADE | C1: SELL TRADE | D1: PREV. CLOSE
A2: UST30Y (BULLISH) | B2: 4.96 | C2: 4.83 | D2: 4.92
A3: 30-Year U.S. Treasury Yield
A4: UST10Y (BULLISH) | B4: 4.3 | C4: 4.2 | D4: 4.28
A5: 10-Year U.S. Treasury Yield
A6: UST2Y (BEARISH) | B6: 3.61 | C6: 3.51 | D6: 3.55
A7: 2-Year U.S. Treasury Yield
A8: HYG (BULLISH) | B8: 80.57 | C8: 80.88 | D8: 80.62
A9: High Yield
A10: LQD (NEUTRAL) | B10: 109.6 | C10: 110.5 | D10: 110
A11: Investment Grade Corporate Bond ETF
A12: SPX (BULLISH) | B12: 6846 | C12: 7020 | D12: 6882
A13: S&P 500
A14: COMPQ (BEARISH) | B14: 22701 | C14: 23521 | D14: 22904
A15: NASDAQ Composite
A16: RUT (BULLISH) | B16: 2600 | C16: 2718 | D16: 2624
A17: Russell 2000
A18: XLK (BEARISH) | B18: 135 | C18: 144 | D18: 138
A19: Technology Select Sector SPDR Fund
A20: XLI (BULLISH) | B20: 164 | C20: 171 | D20: 169
A21: Industrial Select Sector SPDR Fund
A22: SSEC (BULLISH) | B22: 4017 | C22: 4157 | D22: 4075
A23: Shanghai Composite
A24: NIKK (BULLISH) | B24: 52743 | C24: 54794 | D24: 53818
A25: Nikkei 225 Index
A26: DAX (BULLISH) | B26: 24340 | C26: 25141 | D26: 24603
A27: German DAX Composite
A28: VIX (BEARISH) | B28: 15.09 | C28: 20.08 | D28: 18.64
A29: Volatility Index
A30: USD (BEARISH) | B30: 95.79 | C30: 98.32 | D30: 97.84
A31: U.S. Dollar Index
A32: EUR/USD (BULLISH) | B32: 1.171 | C32: 1.202 | D32: 1.179
A33: Euro to U.S. Dollar
A34: USD/YEN (BULLISH) | B34: 153.09 | C34: 158.11 | D34: 157.1
A35: U.S. Dollar to Japanese Yen
A36: GBP/USD (BULLISH) | B36: 1.353 | C36: 1.384 | D36: 1.357
A37: British Pound to U.S. Dollar
A38: CAD/USD (BULLISH) | B38: 0.726 | C38: 0.74 | D38: 0.73
A39: Canadian Dollar to U.S. Dollar
A40: WTIC (BULLISH) | B40: 61.02 | C40: 66.41 | D40: 64.47
A41: Light Crude Oil Continuous Contract
A42: BRENT (BULLISH) | B42: 65.24 | C42: 70.73 | D42: 68.73
A43: Brent Crude Oil Continuous Contract
A44: NATGAS (BEARISH) | B44: 2.99 | C44: 4.3 | D44: 3.46
A45: Natural Gas Continuous Contract
A46: GOLD (BULLISH) | B46: 4660 | C46: 5511 | D46: 4858
A47: Gold Spot Price
A48: COPPER (BULLISH) | B48: 5.74 | C48: 6.21 | D48: 5.93
A49: Copper Continuous Contract
A50: SILVER (BULLISH) | B50: 71 | C50: 124 | D50: 88.75 | E50: trade level 86
A51: Silver Spot Price
A52: PPLT (BULLISH) | B52: 175 | C52: 264 | D52: 201.41
A53: abrdn Physical Platinum Shares ETF
A54: MSFT (BEARISH) | B54: 391 | C54: 442 | D54: 414
A55: Microsoft Corp.
A56: AAPL (BULLISH) | B56: 261 | C56: 281 | D56: 276
A57: Apple Inc.
A58: AMZN (BULLISH) | B58: 228 | C58: 249 | D58: 233
A59: Amazon Inc.
A60: META (BULLISH) | B60: 643 | C60: 739 | D60: 669
A61: Meta Platforms Inc.
A62: GOOGL (BULLISH) | B62: 323 | C62: 347 | D62: 333
A63: Alphabet Inc.
A64: NFLX (BEARISH) | B64: 78 | C64: 84 | D64: 80
A65: Netflix Inc.
A66: TSLA (BEARISH) | B66: 393 | C66: 430 | D66: 406
A67: Tesla Inc.
A68: NVDA (BEARISH) | B68: 171 | C68: 185 | D68: 174
A69: NVIDIA Corporation
A70: ORCL (BEARISH) | B70: 141 | C70: 165 | D70: 147
A71: Oracle Corporation
A72: BITCOIN (BEARISH) | B72: 67154 | C72: 79004 | D72: 69583
A73: Bitcoin Spot Price

Sheet Feb 6. 2026
A1: INDEX | B1: BUY TRADE | C1: SELL TRADE | D1: PREV. CLOSE
A2: UST30Y (BULLISH) | B2: 4.92 | C2: 4.8 | D2: 4.85
A3: 30-Year U.S. Treasury Yield
A4: UST10Y (BEARISH) | B4: 4.28 | C4: 4.17 | D4: 4.18
A5: 10-Year U.S. Treasury Yield
A6: UST2Y (BEARISH) | B6: 3.58 | C6: 3.45 | D6: 3.46
A7: 2-Year U.S. Treasury Yield
A8: HYG (BULLISH) | B8: 80 | C8: 80.87 | D8: 80.53
A9: High Yield
A10: LQD (BULLISH) | B10: 109.7 | C10: 110.8 | D10: 110.5
A11: Investment Grade Corporate Bond ETF
A12: SPX (BULLISH) | B12: 6746 | C12: 7051 | D12: 6798 | E12: 6790 trend level
A13: S&P 500
A14: COMPQ (BEARISH) | B14: 22201 | C14: 23414 | D14: 22540
A15: NASDAQ Composite
A16: RUT (BULLISH) | B16: 2546 | C16: 2703 | D16: 2577
A17: Russell 2000
A18: XLK (BEARISH) | B18: 133 | C18: 143 | D18: 136
A19: Technology Select Sector SPDR Fund
A20: XLI (BULLISH) | B20: 163 | C20: 171 | D20: 168
A21: Industrial Select Sector SPDR Fund
A22: SSEC (BULLISH) | B22: 4010 | C22: 4159 | D22: 4065
A23: Shanghai Composite
A24: NIKK (BULLISH) | B24: 52821 | C24: 54808 | D24: 54253
A25: Nikkei 225 Index
A26: DAX (BULLISH) | B26: 24209 | C26: 25161 | D26: 24491
A27: German DAX Composite
A28: VIX (BEARISH) | B28: 14.11 | C28: 23.76 | D28: 21.77
A29: Volatility Index
A30: USD (BEARISH) | B30: 95.81 | C30: 98.42 | D30: 97.84
A31: U.S. Dollar Index
A32: EUR/USD (BULLISH) | B32: 1.17 | C32: 1.202 | D32: 1.179
A33: Euro to U.S. Dollar
A34: USD/YEN (BULLISH) | B34: 153.01 | C34: 158.13 | D34: 157.11
A35: U.S. Dollar to Japanese Yen
A36: GBP/USD (BULLISH) | B36: 1.35 | C36: 1.383 | D36: 1.359
A37: British Pound to U.S. Dollar
A38: CAD/USD (BULLISH) | B38: 0.726 | C38: 0.74 | D38: 0.731
A39: Canadian Dollar to U.S. Dollar
A40: WTIC (BULLISH) | B40: 61.27 | C40: 66.63 | D40: 63.12
A41: Light Crude Oil Continuous Contract
A42: BRENT (BULLISH) | B42: 65.54 | C42: 70.96 | D42: 67.38
A43: Brent Crude Oil Continuous Contract
A44: NATGAS (BEARISH) | B44: 3.01 | C44: 4.3 | D44: 3.52
A45: Natural Gas Continuous Contract
A46: GOLD (BULLISH) | B46: 4708 | C46: 5521 | D46: 4894
A47: Gold Spot Price
A48: COPPER (BULLISH) | B48: 5.7 | C48: 6.22 | D48: 5.73
A49: Copper Continuous Contract
A50: SILVER (BULLISH) | B50: 61 | C50: 130 | D50: 70.75 | E50: trade level 85
A51: Silver Spot Price
A52: PPLT (BULLISH) | B52: 170 | C52: 260 | D52: 181.77
A53: abrdn Physical Platinum Shares ETF
A54: MSFT (BEARISH) | B54: 371 | C54: 436 | D54: 394
A55: Microsoft Corp.
A56: AAPL (BULLISH) | B56: 262 | C56: 282 | D56: 276
A57: Apple Inc.
A58: AMZN (BEARISH) | B58: 201 | C58: 237 | D58: 223
A59: Amazon Inc.
A60: META (BULLISH) | B60: 642 | C60: 738 | D60: 670
A61: Meta Platforms Inc.
A62: GOOGL (BULLISH) | B62: 325 | C62: 345 | D62: 331
A63: Alphabet Inc.
A64: NFLX (BEARISH) | B64: 77 | C64: 84 | D64: 81
A65: Netflix Inc.
A66: TSLA (BEARISH) | B66: 393 | C66: 428 | D66: 397
A67: Tesla Inc.
A68: NVDA (BEARISH) | B68: 169 | C68: 183 | D68: 172
A69: NVIDIA Corporation
A70: ORCL (BEARISH) | B70: 133 | C70: 160 | D70: 136
A71: Oracle Corporation
A72: BTCUSD (BEARISH) | B72: 61065 | C72: 75602 | D72: 66154
A73: Bitcoin Spot Price

Sheet Feb 9. 2026
A1: INDEX | B1: BUY TRADE | C1: SELL TRADE | D1: PREV. CLOSE
A2: ST30Y (BULLISH) | B2: 4.93 | C2: 4.81 | D2: 4.85
A3: 30-Year U.S. Treasury Yield
A4: UST10Y (BEARISH) | B4: 4.3 | C4: 4.18 | D4: 4.22
A5: 10-Year U.S. Treasury Yield
A6: UST2Y (BEARISH) | B6: 3.57 | C6: 3.45 | D6: 3.5
A7: 2-Year U.S. Treasury Yield
A8: HYG (BULLISH) | B8: 80.54 | C8: 80.89 | D8: 80.81
A9: High Yield
A10: LQD (BULLISH) | B10: 109.9 | C10: 110.7 | D10: 110.6
A11: Investment Grade Corporate Bond ETF
A12: SPX (BULLISH) | B12: 6806 | C12: 7053 | D12: 6932 | E12: 6790 trend level
A13: S&P 500
A14: COMPQ (BEARISH) | B14: 22490 | C14: 23596 | D14: 23031
A15: NASDAQ Composite
A16: RUT (BULLISH) | B16: 2621 | C16: 2715 | D16: 2670
A17: Russell 2000
A18: XLK (BEARISH) | B18: 134 | C18: 144 | D18: 141
A19: Technology Select Sector SPDR Fund
A20: XLI (BULLISH) | B20: 165 | C20: 175 | D20: 173
A21: Industrial Select Sector SPDR Fund
A22: SSEC (BULLISH) | B22: 4016 | C22: 4178 | D22: 4123
A23: Shanghai Composite
A24: NIKK (BULLISH) | B24: 52951 | C24: 56667 | D24: 56363
A25: Nikkei 225 Index
A26: DAX (BULLISH) | B26: 24386 | C26: 25129 | D26: 24721
A27: German DAX Composite
A28: VIX (BEARISH) | B28: 14.37 | C28: 20.99 | D28: 17.76
A29: Volatility Index
A30: USD (BEARISH) | B30: 96.02 | C30: 97.98 | D30: 97.22
A31: U.S. Dollar Index
A32: EUR/USD (BULLISH) | B32: 1.171 | C32: 1.2 | D32: 1.188
A33: Euro to U.S. Dollar
A34: USD/YEN (BULLISH) | B34: 152.81 | C34: 158.34 | D34: 156.52
A35: U.S. Dollar to Japanese Yen
A36: GBP/USD (BULLISH) | B36: 1.35 | C36: 1.383 | D36: 1.365
A37: British Pound to U.S. Dollar
A38: CAD/USD (BULLISH) | B38: 0.725 | C38: 0.741 | D38: 0.734
A39: Canadian Dollar to U.S. Dollar
A40: WTIC (BULLISH) | B40: 61.19 | C40: 66.25 | D40: 63.5
A41: Light Crude Oil Continuous Contract
A42: BRENT (BULLISH) | B42: 65.71 | C42: 70.37 | D42: 67.9
A43: Brent Crude Oil Continuous Contract
A44: NATGAS (BEARISH) | B44: 2.91 | C44: 3.82 | D44: 3.4
A45: Natural Gas Continuous Contract
A46: GOLD (BULLISH) | B46: 4751 | C46: 5516 | D46: 5018
A47: Gold Spot Price
A48: COPPER (BULLISH) | B48: 5.7 | C48: 6.2 | D48: 5.88
A49: Copper Continuous Contract
A50: SILVER (BULLISH) | B50: 67 | C50: 127 | D50: 77.98 | E50: trade level 85
A51: Silver Spot Price
A52: PPLT (BULLISH) | B52: 163 | C52: 254 | D52: 191.3
A53: abrdn Physical Platinum Shares ETF
A54: MSFT (BEARISH) | B54: 370 | C54: 431 | D54: 401
A55: Microsoft Corp.
A56: AAPL (BULLISH) | B56: 264 | C56: 285 | D56: 278
A57: Apple Inc.
A58: AMZN (BEARISH) | B58: 202 | C58: 232 | D58: 210
A59: Amazon Inc.
A60: META (NEUTRAL) | B60: 635 | C60: 710 | D60: 661
A61: Meta Platforms Inc.
A62: GOOGL (BULLISH) | B62: 320 | C62: 345 | D62: 323
A63: Alphabet Inc.
A64: NFLX (BEARISH) | B64: 77 | C64: 85 | D64: 82
A65: Netflix Inc.
A66: TSLA (BEARISH) | B66: 394 | C66: 430 | D66: 411
A67: Tesla Inc.
A68: NVDA (BULLISH) | B68: 170 | C68: 192 | D68: 185
A69: NVIDIA Corporation
A70: ORCL (BEARISH) | B70: 131 | C70: 159 | D70: 143
A71: Oracle Corporation
A72: BTCUSD (BEARISH) | B72: 62507 | C72: 72763 | D72: 69096
A73: Bitcoin Spot Price

Sheet Feb 10. 2026
A1: INDEX | B1: BUY TRADE | C1: SELL TRADE | D1: PREV. CLOSE
A2: UST30Y (BULLISH) | B2: 4.91 | C2: 4.8 | D2: 4.86
A3: 30-Year U.S. Treasury Yield
A4: UST10Y (BEARISH) | B4: 4.28 | C4: 4.16 | D4: 4.21
A5: 10-Year U.S. Treasury Yield
A6: UST2Y (BEARISH) | B6: 3.56 | C6: 3.44 | D6: 3.5
A7: 2-Year U.S. Treasury Yield
A8: HYG (BULLISH) | B8: 80.57 | C8: 80.98 | D8: 80.92
A9: High Yield
A10: LQD (BULLISH) | B10: 109.9 | C10: 110.8 | D10: 110.6
A11: Investment Grade Corporate Bond ETF
A12: SPX (BULLISH) | B12: 6824 | C12: 7050 | D12: 6964 | E12: 6790 trend level
A13: S&P 500
A14: COMPQ (BULLISH) | B14: 22500 | C14: 23611 | D14: 23238
A15: NASDAQ Composite
A16: RUT (BULLISH) | B16: 2591 | C16: 2721 | D16: 2689
A17: Russell 2000
A18: XLK (BEARISH) | B18: 135 | C18: 146 | D18: 143
A19: Technology Select Sector SPDR Fund
A20: XLI (BULLISH) | B20: 167 | C20: 176 | D20: 174
A21: Industrial Select Sector SPDR Fund
A22: SSEC (BULLISH) | B22: 4018 | C22: 4185 | D22: 4128
A23: Shanghai Composite
A24: NIKK (BULLISH) | B24: 54008 | C24: 58057 | D24: 57650
A25: Nikkei 225 Index
A26: DAX (BULLISH) | B26: 24401 | C26: 25173 | D26: 25014
A27: German DAX Composite
